Workbook

Sheet 引合書 (値引きなし）
A1: （様式：EL-97A03） | V1: 納入先コード | W1: 納入先カナ名 | X1: 納入先正式名 | Y1: 郵便番号1 | Z1: 住所1 | AA1: 電話番号1-1
A2: 引き合い内容連絡書 | J2: 株式会社オーレック | V2: 61102 | W2: ﾆﾎﾝｸﾘﾝﾄﾝ | X2: 日本クリントン㈱ | Y2: 121-0836 | Z2: 東京都 足立区 入谷5-7-8 | AA2: 03-3854-8221
A3: 得意先NO： | B3: 得意先名 及び 担当者名： | I3: 受注日： | V3: 61103 | W3: ﾄｳｺｳｻﾝｷﾞｮｳ | X3: 東興産業㈱ | Y3: 350-0821 | Z3: 埼玉県 川越市 福田239 | AA3: 0492-23-1217
A4: 61377 | C4: =IFERROR(VLOOKUP(A4,請求先!A:D,2,FALSE)," ") -> 千葉県農業機械商業協同組合 | I4: 46199 | L4: 製品コード検索 | V4: 61105 | W4: ｲﾄｳｻﾝｷﾞｮｳｷｶｲ | X4: 伊藤産業機械㈱ | Y4: 290-0034 | Z4: 千葉県 市原市 島野1978 | AA4: 0436-22-1743
A5: 納入先NO： | B5: 納入先名及び 担当者名： | G5: 生産日 | H5: 46226 | I5: 出荷希望日： | L5: WM746F?M | Q5: → | R5: =IFERROR(VLOOKUP(L5,商品コード!B:F,5,FALSE)," ") -> 0317-0320 | V5: 61106 | W5: ｴﾑｴｽｹｰﾉｳｷﾞｮｳｷｶｲﾁﾊﾞｼﾞｷﾞｮｳｼｮ | X5: MSK東急機械㈱ 千葉事業所 | Y5: 290-0012 | Z5: 千葉県 市原市 藤井3-310 | AA5: 0436-41-1069
A6: 61313 | C6: =IFERROR(VLOOKUP(A6,出荷先!A:F,3,FALSE)," ") -> ㈲鈴木農機 | I6: 46230 | V6: 61107 | W6: ｻｻｷｼｮｳｶｲ | X6: ㈱佐々木商会 | Y6: 294-0037 | Z6: 千葉県 館山市 長須賀123 | AA6: 0470-22-1166
B7: 住所： | C7: 〒 | D7: =IFERROR(VLOOKUP(A6,出荷先!A:F,4,FALSE)," ") -> 283-0046 | I7: TEL | L7: 不需要期値引 | Q7: =IF(Q6="","",VLOOKUP(Q6,#REF!,2,FALSE)) | V7: 61108 | W7: ｽｷﾞｷﾃｯｺｳ | X7: 杉木鉄工㈱ | Y7: 297-0029 | Z7: 千葉県 茂原市 高師1536 | AA7: 0475-22-4587
B8: =IFERROR(VLOOKUP(A6,出荷先!A:F,5,FALSE)," ") -> 千葉県 東金市 上谷956 | I8: =IFERROR(VLOOKUP(A6,出荷先!A:F,6,FALSE)," ") -> 0475-52-4511 | L8: =IF(L7="","",VLOOKUP(L7,商品コード!A:B,2,FALSE)) -> 内掛 | M8: =IF(I8="","",VLOOKUP(I8,商品コード!#REF!,2,FALSE)) -> #REF! | N8: 5 | P8: % | V8: 61109 | W8: ﾀｶﾉｻﾝｷﾞｮｳ | X8: 高野産業㈱ | Y8: 292-0054 | Z8: 千葉県 木更津市 長須賀924-1 | AA8: 0438-22-6251
V9: 61110 | W9: ｶﾝﾄｳｺｼﾝｸﾎﾞﾀﾁﾊﾞｼﾞｷﾞｮｳﾌﾞ | X9: ㈱関東甲信クボタ 南関東事業所 | Y9: 260-0808 | Z9: 千葉県 千葉市 中央区 星久喜町176-4 | AA9: 043-261-3131
A10: 商品番号 | B10: 商品名 | E10: 数量 | F10: 単位 | G10: 単価 | I10: オーダーＮｏ 等 | L10: 税別小売 | N10: 通常 | P10: =IF(A4="","",VLOOKUP(A4,請求先!A:D,4,FALSE)) -> 0.67 | Q10: 値引 | R10: =$N$8/100 -> 0.05 | S10: 最終 | T10: =IF(L8="外掛",P10-R10,IF(L8="内掛",ROUNDDOWN(P10*(100-100*R10)%,5))) -> 0.6365 | V10: 61111 | W10: ﾅｶﾔｼｮｳｶｲ | X10: ㈱中屋商会 | Y10: 289-2146 | Z10: 千葉県 匝瑳市 八日市場ホ452 | AA10: 0479-72-1161
A11: 0353-0020 | B11: =IFERROR(VLOOKUP(A11,商品コード!A:C,2,FALSE)," ") -> SP753B/M | E11: 1 | L11: =IF(A11="","",VLOOKUP(A11,商品コード!A:C,3,FALSE)) -> 328000 | N11: =IFERROR(IF(A4=61121,ROUNDDOWN((L11*P10),-1),IF(A4=61123,ROUNDDOWN((L11*P10),-1),IF(A4=64445001,ROUNDDOWN((L11*P10),-1),IF(A4=64445002,ROUNDDOWN((L11*P10),-1),ROUNDDOWN(L11*P10,-2)))))," ") -> 219700 | Q11: =IFERROR(S11-N11," ") -> -11000 | S11: =IFERROR(IF(OR(A4=61121,A4=61123,A4=64445001,A4=64445002),IF(L8="内掛",ROUNDDOWN(N11*(1-R10),-1),ROUNDDOWN(L11*T10,-1)),IF(L8="内掛",ROUNDDOWN(N11*(1-R10),-2),ROUNDDOWN(L11*T10,-2)))," ") -> 208700 | V11: 61112 | W11: ﾅｶﾑﾗｻﾝｷﾞｮｳ | X11: ㈱中村産業 | Y11: 283-0811 | Z11: 千葉県 東金市 台方246 | AA11: 0475-52-2615
B12: =IFERROR(VLOOKUP(A12,商品コード!A:C,2,FALSE)," ") | L12: =IF(A12="","",VLOOKUP(A12,商品コード!A:C,3,FALSE)) | N12: =IFERROR(IF(A4=61121,ROUNDDOWN((L12*P10),-1),IF(A4=61123,ROUNDDOWN((L12*P10),-1),IF(A4=64445001,ROUNDDOWN((L12*P10),-1),IF(A4=64445002,ROUNDDOWN((L12*P10),-1),ROUNDDOWN(L12*P10,-2)))))," ") | Q12: =IFERROR(S12-N12," ") | S12: =IFERROR(IF(OR(A4=61121,A4=61123,A4=64445001,A4=64445002),IF(L8="内掛",ROUNDDOWN(N12*(1-R10),-1),ROUNDDOWN(L12*T10,-1)),IF(L8="内掛",ROUNDDOWN(N12*(1-R10),-2),ROUNDDOWN(L12*T10,-2)))," ") | V12: 61113 | W12: ﾌﾀﾊﾞｺｳｷ | X12: ㈲双葉工機 | Y12: 270-2222 | Z12: 千葉県 松戸市 高塚新田340-11 | AA12: 0473-92-7256
B13: =IFERROR(VLOOKUP(A13,商品コード!A:C,2,FALSE)," ") | L13: =IF(A13="","",VLOOKUP(A13,商品コード!A:C,3,FALSE)) | N13: =IFERROR(IF(A4=61121,ROUNDDOWN((L13*P10),-1),IF(A4=61123,ROUNDDOWN((L13*P10),-1),IF(A4=64445001,ROUNDDOWN((L13*P10),-1),IF(A4=64445002,ROUNDDOWN((L13*P10),-1),ROUNDDOWN(L13*P10,-2)))))," ") | Q13: =IFERROR(S13-N13," ") | S13: =IFERROR(IF(OR(A4=61121,A4=61123,A4=64445001,A4=64445002),IF(L8="内掛",ROUNDDOWN(N13*(1-R10),-1),ROUNDDOWN(L13*T10,-1)),IF(L8="内掛",ROUNDDOWN(N13*(1-R10),-2),ROUNDDOWN(L13*T10,-2)))," ") | V13: 61114 | W13: ﾓﾊﾞﾗﾌｺｸｼｬ | X13: ㈱茂原富国社 | Y13: 297-0029 | Z13: 千葉県 茂原市 高師1671 | AA13: 0475-25-0325
B14: =IFERROR(VLOOKUP(A14,商品コード!A:C,2,FALSE)," ") | L14: =IF(A14="","",VLOOKUP(A14,商品コード!A:C,3,FALSE)) | N14: =IFERROR(IF(A4=61121,ROUNDDOWN((L14*P10),-1),IF(A4=61123,ROUNDDOWN((L14*P10),-1),IF(A4=64445001,ROUNDDOWN((L14*P10),-1),IF(A4=64445002,ROUNDDOWN((L14*P10),-1),ROUNDDOWN(L14*P10,-2)))))," ") | Q14: =IFERROR(S14-N14," ") | S14: =IFERROR(IF(OR(A4=61121,A4=61123,A4=64445001,A4=64445002),IF(L8="内掛",ROUNDDOWN(N14*(1-R10),-1),ROUNDDOWN(L14*T10,-1)),IF(L8="内掛",ROUNDDOWN(N14*(1-R10),-2),ROUNDDOWN(L14*T10,-2)))," ") | V14: 61115 | W14: ｲﾊﾞﾗｷﾘｮｳﾉｳ | X14: 茨城菱農㈱ | Y14: 300-4201 | Z14: 茨城県 つくば市 寺具1332-9 | AA14: 0298-69-1045
B15: =IFERROR(VLOOKUP(A15,商品コード!A:C,2,FALSE)," ") | V15: 61116 | W15: ｶﾝﾄｳｺｳｼﾝｸﾎﾞﾀｲﾊﾞﾗｷｼﾞﾑｼｮ | X15: ㈱関東甲信クボタ 茨城事務所 | Y15: 300-2402 | Z15: 茨城県 つくばみらい市 坂野新田12-42 | AA15: 0297-52-1111
B16: =IFERROR(VLOOKUP(A16,商品コード!A:C,2,FALSE)," ") | V16: 61117 | W16: ｵｵｶﾜｷｶｲ | X16: 大川機械 | Y16: 300-0024 | Z16: 茨城県 土浦市 田村町988-2 | AA16: 0298-28-0755
A17: 倉庫（ | B17: 011 | C17: ） | D17: 運賃 | E17: 元払い | F17: 伝票NO： | V17: 61118 | W17: ﾐﾂﾋﾞｼﾉｳｷﾊﾝﾊﾞｲｲﾊﾞﾗｷｼﾃﾝ | X17: 三菱農機販売㈱ 茨城支店 | Y17: 311-0133 | Z17: 茨城県 那珂市 鴻巣1135-1 | AA17: 0293-53-2140
B18: 0 | E18: 立 元 | F18: 出荷確認 | H18: 受注可否検討 | J18: 連絡書作成 | V18: 61120 | W18: ｼﾏｻﾉｳｷ | X18: ㈱嶋田農機 | Y18: 300-3544 | Z18: 茨城県 結城郡 八千代町 若996 | AA18: 0296-48-1025
E19: 着払い | F19: 承認 | H19: 承認 | J19: 作成者 | V19: 61121 | W19: ｸﾎﾞﾀｲﾊﾞﾗｷｹﾝｴｲｷﾞｮｳﾀﾝﾄｳ | X19: ㈱クボタ 茨城県営業担当 | Y19: 338-0832 | Z19: 埼玉県 さいたま市 桜区 西堀5-2-36 | AA19: 048-862-1125
C20: 便名： | D20: 福山便 西濃便 JPロジ | V20: 61122 | W20: ﾅﾘﾀｶﾄｳﾉｳｷ | X20: 成田加藤農機（有） | Y20: 286-0021 | Z20: 千葉県 成田市 土屋1375-1 | AA20: 0476-22-0579
V21: 61123 | W21: ｸﾎﾞﾀﾄﾁｷﾞｹﾝｴｲｷﾞｮｳﾀﾝﾄｳ | X21: ㈱クボタ 栃木県営業担当 | Y21: 338-0832 | Z21: 埼玉県 さいたま市 桜区 西堀5-2-36 | AA21: 048-862-1125
V22: 61124 | W22: ﾈﾓﾄｼｮｳｶｲ | X22: ㈲根本商会 | Y22: 286-0801 | Z22: 千葉県 成田市 竜台468 | AA22: 0476-37-1211
A23: 製品コード検索 | V23: 61125 | W23: ﾏﾙﾃﾝｻﾝｷﾞｮｳｷｶｲ | X23: マルテン産業機械㈱ | Y23: 293-0001 | Z23: 千葉県 富津市 大堀1434 | AA23: 0439-87-0052
A24: RCSP530/Y | F24: → | G24: =IFERROR(VLOOKUP(A24,商品コード!B:F,5,FALSE)," ") | V24: 61126 | W24: ﾐﾂﾋﾞｼﾉｳｷﾊﾝﾊﾞｲﾁﾊﾞｼﾃﾝ | X24: 三菱農機販売㈱ 千葉支店 | Y24: 300-1312 | Z24: 茨城県 稲敷郡 河内町 長竿字西の町1596-2 | AA24: 0297-63-4633
V25: 61127 | W25: ｸﾎﾞﾀｸﾞﾝﾏｹﾝｴｲｷﾞｮｳﾀﾝﾄｳ | X25: ㈱クボタ 群馬県営業担当 | Y25: 338-0832 | Z25: 埼玉県 さいたま市 桜区 西堀5-2-36 | AA25: 048-862-1125
V26: 61133 | W26: ﾏｷﾀﾇﾏﾂﾞﾋｶﾞｼﾆﾎﾝ | X26: ㈱マキタ沼津 東日本支店 | Y26: 362-0031 | Z26: 埼玉県 上尾市 東町2-8-4 | AA26: 048-779-2262
V27: 61134 | W27: ｸﾎﾞﾀｹﾝｷｼﾞｬﾊﾟﾝﾁﾊﾞｴｲｷﾞｮｳｼｮ | X27: ㈱クボタ建機ジャパン千葉営業所 | Y27: 283-0823 | Z27: 千葉県 東金市 山田 字新田1201-10 | AA27: 茨城菱農
V28: 61135 | W28: ｵｵｻﾜｷｶｲ | X28: 大沢機械 | Y28: 191-0043 | Z28: 東京都 日野市 平山6-2-1 | AA28: 042-591-1588
V29: 61136 | W29: ｼﾊﾞﾀ | X29: ㈱シバタ | Y29: 104-0032 | Z29: 東京都 中央区 八丁堀4-3-1 | AA29: 03-3552-0381
V30: 61140 | W30: ﾏｷﾀﾇﾏﾂﾞｷﾞｮｳﾑﾌﾞｼｮｳﾋﾝｶ | X30: ㈱マキタ沼津 業務部商品課 | Y30: 410-0022 | Z30: 静岡県 沼津市 大岡35 | AA30: 055-963-1112
V31: 61301 | W31: ｶﾅｴｻﾝｷﾞｮｳ | X31: カナエ産業㈱ | Y31: 194-0215 | Z31: 東京都 町田市 小山ケ丘3-7-10 | AA31: 042-798-7181
V32: 61302 | W32: ﾖｼｻﾞﾜｹﾞﾝﾄﾞｳｷ | X32: 吉澤原動機 | Y32: 114-0013 | Z32: 東京都 北区 東田端2-8-6 | AA32: 03-3810-2700
V33: 61303 | W33: ﾐﾔｼﾞｷｶｲ | X33: ㈱宮地機械（出荷停止） | Y33: 177-0033 | Z33: 東京都 練馬区 高野台4-11-28 | AA33: 03-3997-3155
V34: 61304 | W34: ﾊﾁｷﾞｮｳｼｮｳｼﾞ | X34: 八丈商事 | Y34: 100-1401 | Z34: 東京都 八丈島 八丈町 大賀郷1098-2 | AA34: 04996-2-2189
V35: 61305 | W35: ｲｼｲﾃﾞﾝｷｼｮｳﾃﾝ | X35: ㈱石井電気商店 | Y35: 294-0042 | Z35: 千葉県 館山市 上野原294-5 | AA35: 0470-22-0542
V36: 61306 | W36: ｲｺﾞｳﾉｳｷ | X36: ㈲井合農機店 | Y36: 273-0047 | Z36: 千葉県 船橋市 藤原5-22-31 | AA36: 047-439-5477
... V95: 61376 | W95: ﾘｮｳｴｲｼｬ | X95: ㈲良栄社商会 | Y95: 299-1151 | Z95: 千葉県 君津市 中野4-15-18 | AA95: 0439-52-0035
W96: ｺｼﾞﾝｷｬｸ | X96: 個人客
V97: 61400 | W97: ｺﾐﾔﾉｳｻﾝｷｼｮｳｶｲ | X97: ㈲古宮農蚕機商会 | Y97: 192-0051 | Z97: 東京都 八王子市 元本郷町1-5-5 | AA97: 042-625-2328
V98: 63102 | W98: ﾐﾂﾋﾞｼﾉｳｷﾊﾝﾊﾞｲｶﾝﾄｳｺｳｼﾝｴﾂ | X98: 三菱農機販売㈱ 関東甲信越支店 | Y98: 340-0203 | Z98: 埼玉県 久喜市 桜田2-133-4 | AA98: 0480-58-9521
V99: 63103 | W99: ｶﾝﾄｳｺｳｼﾝｸﾎﾞﾀｸﾎﾞﾀﾄﾁｷﾞｼﾞﾑｼｮ | X99: ㈱関東甲信クボタ 北関東事業所 （栃木） | Y99: 321-0905 | Z99: 栃木県 宇都宮市 平出工業団地28-2 | AA99: 0286-89-2341
V100: 63105 | W100: ﾐﾂﾋﾞｼﾉｳｷﾊﾝﾊﾞｲﾄﾁｷﾞｼﾃﾝ | X100: 三菱農機販売㈱ 栃木支店 | Y100: 329-1233 | Z100: 栃木県 塩谷郡 高根沢町 宝積寺 中2248-60 | AA100: 0286-75-7321
V101: 63112 | W101: ﾀｶﾀﾞﾗｸﾉｳｷ | X101: 高田酪農機㈱ | Y101: 321-3236 | Z101: 栃木県 宇都宮市 竹下町1101-11 | AA101: 028-667-2825
V102: 63301 | W102: ｺﾋﾞｷﾉｳｷｸﾞﾃﾝ | X102: 小比企農機具店 | Y102: 326-0845 | Z102: 栃木県 足利市 大前町207 | AA102: 0284-62-2065
V103: 63302 | W103: ﾇﾉｶﾜﾉｳｷｸﾞﾃﾝ | X103: 布川農機具店 | Y103: 329-4404 | Z103: 栃木県 栃木市 大平町富田1430 | AA103: 0282-43-2013
V104: 63303 | W104: ｽﾅｶﾉｳｷｸﾞﾃﾝ | X104: 砂川農機具店 | Y104: 326-0323 | Z104: 栃木県 足利市 瑞穂野町495 | AA104: 0284-71-9033
V105: 63304 | W105: ｽｽﾞｷﾔ | X105: ㈱鈴木屋 | Y105: 329-0205 | Z105: 栃木県 小山市 間々田1290 | AA105: 0285-45-0070
V106: 63305 | W106: ｶﾜﾀ | X106: ㈱川田 | Y106: 322-0002 | Z106: 栃木県 鹿沼市 千渡2315-66 | AA106: 0289-65-3366
V107: 63306 | W107: ｺﾀﾞｲﾗﾉｳｷｼｮｳｶｲ | X107: 小平農機商会 | Y107: 321-1261 | Z107: 栃木県 日光市 今市107-22 | AA107: 0288-21-0845
V108: 63307 | W108: ｻｲﾄｳﾉｳｷｼｮｳｶｲ | X108: ㈲斉藤農機商会 | Y108: 329-2161 | Z108: 栃木県 矢板市 扇町1-11-19 | AA108: 0287-43-0475
... V206: 64391 | W206: ｶﾝﾄｳｺｳｼﾝｸﾎﾞﾀｸﾞﾝﾏｼﾞﾑｼｮ | X206: ㈱関東甲信クボタ 群馬事務所 | Y206: 379-2154 | Z206: 群馬県 前橋市 天川大島町1364-1 | AA206: 027-261-6010
V207: 64398 | W207: ｶﾝﾄｳｹﾞﾝｷﾝｷｬｸ | X207: 関東現金客
V208: 64399 | W208: ｺｼﾞﾝｷｬｸ | X208: 個人客
V209: 64444 | W209: ﾐﾂﾋﾞｼﾉｳｷﾋｶﾞｼﾆﾎﾝﾌﾞﾋﾝｷｶﾝｾﾝﾀｰ | X209: 三菱農機㈱ 東日本部品基幹センター | Y209: 340-0203 | Z209: 埼玉県 久喜市 桜田2-133-4 | AA209: 0480-58-9515
V210: 64445 | W210: ﾐﾂﾋﾞｼﾉｳｷ | X210: 三菱ﾏﾋﾝﾄﾞﾗ農機㈱ 島根県 | Y210: 699-0101 | Z210: 島根県 松江市 東出雲町 揖屋667-1 | AA210: 0852-52-2111
V211: 65130 | W211: ｿｳﾌﾞｷｶｲ | X211: ㈱相武機械 | Y211: 215-0003 | Z211: 神奈川県 川崎市 麻生区 高石3-31-27 | AA211: 044-966-4161
V212: 65131 | W212: ﾓﾘﾁｮｳ | X212: 森長 | Y212: 254-0041 | Z212: 神奈川県 平塚市 浅間町5-27 | AA212: 0463-31-2195
V213: 65132 | W213: ｶﾝﾄｳｺｼﾝｸﾎﾞﾀｾｲｼﾝｼﾞｷﾞｮｳﾌﾞ | X213: ㈱関東甲信クボタ 静神事業部 | Y213: 411-0817 | Z213: 静岡県 三島市 八反畑 字鶴田100 | AA213: 055-972-0800
V214: 65137 | W214: ｴﾙﾀ | X214: ㈱エルタ | Y214: 190-1221 | Z214: 東京都 西多摩郡 瑞穂町 箱根ケ崎 東松原20-1 | AA214: 0425-56-0184
V215: 65323 | W215: ｵｵﾀｹﾉｳｷ | X215: 大竹農機㈱ | Y215: 289-1115 | Z215: 千葉県 八街市 八街ほ244 | AA215: 043-444-0225
V216: 65347 | W216: ｶﾓｼﾀﾞｼｮｳｶｲ | X216: 鴨志田商会 | Y216: 226-0000 | Z216: 神奈川県 横浜市 緑区 川和町1437 | AA216: 045-931-1038
V217: 65348 | W217: ｷｼﾀﾞﾉｳｷｼｮｳｶｲ | X217: ㈱岸田農機商会 | Y217: 259-1131 | Z217: 神奈川県 伊勢原市 伊勢原1-7-18 | AA217: 0463-95-0121
V218: 65350 | W218: ｻｶﾞﾐﾉｳｷ | X218: さがみ農機 | Y218: 258-0001 | Z218: 神奈川県 足柄上郡 松田町 寄5501 | AA218: 0465-89-2329
V219: 65351 | W219: ｽｽﾞﾉﾉｳｷ | X219: ㈲鈴野農機 | Y219: 252-0826 | Z219: 神奈川県 藤沢市 宮原1348 | AA219: 0466-48-1048
V220: 65352 | W220: ﾀﾅｶﾉｳｷｼｮｳｶｲ | X220: 田中農機商会 | Y220: 252-0807 | Z220: 神奈川県 藤沢市 下土棚444 | AA220: 0466-44-2005
... V244: 2133075 | W244: ﾂｸﾊﾞｼｻｸﾗﾉｳｷｾﾝﾀｰ | X244: JAつくば市 桜農機センター | Y244: 305-0027 | Z244: 茨城県 つくば市 東岡335 | AA244: 029-857-3116
V245: 2133107 | X245: JA常陸 みなみ農機センター | Y245: 319-1234 | Z245: 茨城県 日立市 大和田町1992 | AA245: 0294-53-2121
V246: 2133110 | W246: ﾏｼｰﾈｵﾐﾀﾏ | X246: JAマシーネ 小美玉 | Y246: 311-3412 | Z246: 茨城県 小美玉市 川戸1450-58 | AA246: 0299-58-5644
V247: 2133115 | W247: ﾐﾄﾉｳｷｮｳﾐﾄﾉｳｷｾﾝﾀｰ | X247: JA水戸農協 水戸農機センター | Y247: 311-4141 | Z247: 茨城県 水戸市 赤塚2-27 | AA247: 029-252-2076
V248: 2133147 | W248: ﾅﾒｶﾞﾀﾉｳｷﾈﾝﾘｮｳ | X248: JAなめがた農機燃料㈱ 南部農機センター | Y248: 311-3835 | Z248: 茨城県 行方市 島並857-16 | AA248: 0299-72-1651
V249: 2134054 | W249: ｸﾏｶﾞﾔｸﾏｶﾞﾔﾉｳｷｾﾝﾀｰ | X249: JAくまがや 熊谷農機センター | Y249: 360-0805 | Z249: 埼玉県 熊谷市 上奈良1079-1 | AA249: 048-523-9291
V250: 2134057 | W250: ｸﾏｶﾞﾔｺｳﾅﾝﾉｳｷｾﾝﾀｰ | X250: JAくまがや 江南農機センター | Y250: 360-0115 | Z250: 埼玉県 熊谷市 成沢490-1 | AA250: 048-536-1404
V251: 2134071 | W251: ｲﾙﾏﾉﾎｸﾌﾞﾉｳｷｾﾝﾀｰ | X251: JAいるま野 北部農機センター | Y251: 350-0212 | Z251: 埼玉県 坂戸市 石井1880 | AA251: 049-289-2172
V252: 2134072 | W252: ｻｲﾀﾏｻｼｵｳｷﾞｼﾃﾝ | X252: JAさいたま 指扇支店 | Y252: 331-0071 | Z252: 埼玉県 さいたま市 西区 高木337-3 | AA252: 048-623-5011
V253: 2134091 | W253: ｲﾙﾏﾉﾄｺﾛｻﾞﾜﾉｳｷｾﾝﾀｰ | X253: JAいるま野 所沢農機センター | Y253: 359-0001 | Z253: 埼玉県 所沢市 下富627-10 | AA253: 042-942-3467
V254: 2134092 | X254: JAちちぶ農協秩父自動車センター | Y254: 368-0056 | Z254: 埼玉県 秩父市 寺尾3218-1 | AA254: 0494-25-2555
V255: 2134107 | W255: ｻｲﾀﾏﾁｭｳｵｳﾋｶﾞｼﾏﾂﾔﾏﾉｳｷｾﾝﾀｰ | X255: JA埼玉中央 東松山農機センター | Y255: 355-0073 | Z255: 埼玉県 東松山市 上野本1405-1 | AA255: 0493-24-3159
V256: 2135169 | W256: ｷﾐﾂ | X256: JAきみつ 平川農機整備工場 | Y256: 299-0205 | Z256: 千葉県 袖ヶ浦市 上泉366 | AA256: 0438-75-4007
V257: 2135181 | W257: ﾁｮｳｾｲﾉｳｷｮｳ | X257: JA長生農協 睦沢農機センター | Y257: 299-4403 | Z257: 千葉県 長生郡 睦沢町 上市場914 | AA257: 0475-44-1236
V258: 2135187 | W258: ｷﾐﾂ | X258: JAきみつ 天羽農機整備工場 | Y258: 299-1618 | Z258: 千葉県 富津市 花輪150 | AA258: 0439-80-7650
V259: 2135190 | W259: ｲﾁﾊﾗｼﾉｳｷｾﾝﾀｰ | X259: JA市原市 農機センター | Y259: 290-0225 | Z259: 千葉県 市原市 牛久573-1 | AA259: 0436-92-5650
V260: 2135192 | W260: ｱﾜﾉｳｷｮｳｳﾁﾎﾞｳﾉｳｷｾﾝﾀｰ | X260: JA安房農協 内房農機ｾﾝﾀｰ | Y260: 294-0813 | Z260: 千葉県 南房総市 谷向56 | AA260: 0470-36-4070
V261: 2135198 | X261: JA君津市農業協同組合上総農機 SS | Y261: 292-0503 | Z261: 千葉県 君津市 広岡1771 | AA261: 0439-29-2080
V262: 2135221 | W262: ﾆｼﾝﾊﾞﾉｳｷﾖｳｾｲｶﾂﾌﾞ | X262: JA西印旛農協 生活部 機械課 | Y262: 270-1337 | Z262: 千葉県 印西市 草深1230 | AA262: 0476-47-3133
V263: 2135223 | W263: ｷｻﾗﾂﾞｼﾉｳｷﾞｮｳｷｮｳﾄﾞｳ | X263: JA木更津市農業協同組合 中郷農機事業 ｾﾝﾀｰ | Y263: 292-0026 | Z263: 千葉県 木更津市 井尻525-1 | AA263: 0438-98-0279
V264: 2135424 | W264: ﾄﾐｻﾄｼﾉｳｷｾﾝﾀｰ | X264: JA富里市農機センター | Y264: 286-0212 | Z264: 千葉県 富里市 十倉431-1 | AA264: 0476-93-8683
V265: 2135424 | W265: ﾄﾐｻﾄｼﾉｳｷﾞｮｳｷｮｳﾄﾞｳｾﾝﾀｰ | X265: JA富里市 農業共同センター | Y265: 286-0212 | Z265: 千葉県 富里市 十倉431-1 | AA265: 0476-93-8683
V266: 2135424 | W266: ﾄﾐｻﾄｼﾉｳｷﾞｮｳｷｮｳﾄﾞｳｾﾝﾀｰ | X266: JA富里市 農機共同センター
V267: 2135428 | W267: ｷﾐﾂｿｳｺﾞｳｷｶｲｾﾝﾀｰ | X267: JA君津総合機械センター | Y267: 299-1104 | Z267: 千葉県 君津市 糠田169 | AA267: 0439-32-5081
V268: 2135542 | W268: ﾁﾊﾞﾐﾄﾞﾘﾉｳｷｾﾝﾀｰ | X268: JAちばみどり 農機センター | Y268: 289-2503 | Z268: 千葉県 旭市 江ヶ崎661 | AA268: 0479-63-7009
V269: 2136069 | W269: ﾄｳｷｮｳﾐﾗｲ | X269: JA東京みらい 農機センター | Y269: 189-0014 | Z269: 東京都 東村山市 本町1-16-5 | AA269: 0423-93-5211
V270: 2136073 | W270: ﾏﾁﾀﾞｼﾉｳｷｮｳﾉｳｷｾﾝﾀｰ | X270: JA町田市農協 農機センター | Y270: 194-0035 | Z270: 東京都 町田市 忠生1-29-4 | AA270: 042-792-2811
V271: 2137003 | W271: ｹﾝｵｳｱｲｶﾜｹｲｻﾞｲｾﾝﾀｰ | X271: JA県央愛川経済センター | Y271: 243-0308 | Z271: 神奈川県 愛甲郡 愛川町 三増891 | AA271: 0462-81-5000
V272: 2137004 | W272: ｻｶﾞﾐﾉｳｷｮｳｱﾔｾｴｲﾉｳｹｲｻﾞｲ | X272: JAさがみ農協 綾瀬営農経済 | Y272: 252-1103 | Z272: 神奈川県 綾瀬市 深谷3333 | AA272: 0467-78-0521
V273: 2137008 | W273: ｻｶﾞﾐﾉｳｷｮｳｴﾋﾞﾅ | X273: JAさがみ農協 海老名営農センター | Y273: 243-0411 | Z273: 神奈川県 海老名市 大谷240 | AA273: 046-234-2514
V274: 2137010 | W274: ｶﾅｶﾞﾜｾｲﾌﾞﾉｳｷｮｳﾉｳｷｾﾝﾀｰ | X274: JAかながわ西部農協農機センター | Y274: 258-0016 | Z274: 神奈川県 足柄上郡 大井町 上大井238 | AA274: 0465-83-4171
V275: 2137051 | W275: ｼｮｳﾅﾝﾉｳｷｮｳｼﾞｷﾞｮｳｾﾝﾀｰﾉｳｷ | X275: JA湘南農協 事業センター農機 | Y275: 259-1213 | Z275: 神奈川県 平塚市 片岡657 | AA275: 0463-58-2125
V276: 2137063 | W276: ｾﾞﾝﾉｳｶﾅｶﾞﾜｹﾝﾎﾝﾌﾞﾄｳﾌﾞｷﾀﾉｳｷｾﾝﾀｰ | X276: JA全農神奈川県本部 東部きた 農機センター | Y276: 224-0045 | Z276: 神奈川県 横浜市 都筑区 東方町1401 | AA276: 045-942-8666
V277: 69009226 | W277: ｳｴﾉ | X277: ㈱上野 | Y277: 323-0012 | Z277: 栃木県 小山市 羽川777-35 | AA277: 0285-23-5212
V278: 69009166 | W278: ｵｵﾇｷｷｶｲﾃﾝ | X278: ㈲大貫機械店 | Y278: 329-2161 | Z278: 栃木県 矢板市 扇町1-16-22 | AA278: 0287-43-0366
...

Sheet 実演機分
A1: （様式：EL-97A03） | W1: 納入先コード | X1: 納入先カナ名 | Y1: 納入先正式名 | Z1: 郵便番号1 | AA1: 住所1 | AB1: 電話番号1-1
A2: 引き合い内容連絡書 | J2: 株式会社オーレック | W2: 61102 | X2: ﾆﾎﾝｸﾘﾝﾄﾝ | Y2: 日本クリントン㈱ | Z2: 121-0836 | AA2: 東京都 足立区 入谷5-7-8 | AB2: 03-3854-8221
A3: 得意先NO： | B3: 得意先名 及び 担当者名： | I3: 受注日： | W3: 61103 | X3: ﾄｳｺｳｻﾝｷﾞｮｳ | Y3: 東興産業㈱ | Z3: 350-0821 | AA3: 埼玉県 川越市 福田239 | AB3: 0492-23-1217
A4: 61125 | C4: =IFERROR(VLOOKUP(A4,請求先!A:D,2,FALSE)," ") -> マルテン産業機械㈱ | I4: 46199 | L4: 製品コード検索 | W4: 61105 | X4: ｲﾄｳｻﾝｷﾞｮｳｷｶｲ | Y4: 伊藤産業機械㈱ | Z4: 290-0034 | AA4: 千葉県 市原市 島野1978 | AB4: 0436-22-1743
A5: 納入先NO： | B5: 納入先名及び 担当者名： | G5: 生産日 | I5: 出荷希望日： | L5: RM984X/K | Q5: → | R5: =IFERROR(VLOOKUP(L5,商品コード!B:F,5,FALSE)," ") -> 0352-0110 | W5: 61106 | X5: ｴﾑｴｽｹｰﾉｳｷﾞｮｳｷｶｲﾁﾊﾞｼﾞｷﾞｮｳｼｮ | Y5: MSK東急機械㈱ 千葉事業所 | Z5: 290-0012 | AA5: 千葉県 市原市 藤井3-310 | AB5: 0436-41-1069
A6: 61125 | C6: =IFERROR(VLOOKUP(A6,出荷先!A:F,3,FALSE)," ") -> マルテン産業機械㈱ | I6: 46199 | W6: 61107 | X6: ｻｻｷｼｮｳｶｲ | Y6: ㈱佐々木商会 | Z6: 294-0037 | AA6: 千葉県 館山市 長須賀123 | AB6: 0470-22-1166
B7: 住所： | C7: 〒 | D7: =IFERROR(VLOOKUP(A6,出荷先!A:F,4,FALSE)," ") -> 293-0001 | I7: TEL | L7: 実演機値引 | Q7: =IF(Q6="","",VLOOKUP(Q6,#REF!,2,FALSE)) | W7: 61108 | X7: ｽｷﾞｷﾃｯｺｳ | Y7: 杉木鉄工㈱ | Z7: 297-0029 | AA7: 千葉県 茂原市 高師1536 | AB7: 0475-22-4587
B8: =IFERROR(VLOOKUP(A6,出荷先!A:F,5,FALSE)," ") -> 千葉県 富津市 大堀1434 | I8: =IFERROR(VLOOKUP(A6,出荷先!A:F,6,FALSE)," ") -> 0439-87-0052 | L8: =IF(L7="","",VLOOKUP(L7,商品コード!A:B,2,FALSE)) -> 外掛 | M8: =IF(I8="","",VLOOKUP(I8,商品コード!#REF!,2,FALSE)) -> #REF! | N8: 8 | P8: % | W8: 61109 | X8: ﾀｶﾉｻﾝｷﾞｮｳ | Y8: 高野産業㈱ | Z8: 292-0054 | AA8: 千葉県 木更津市 長須賀924-1 | AB8: 0438-22-6251
N9: ] | W9: 61110 | X9: ｶﾝﾄｳｺｼﾝｸﾎﾞﾀﾁﾊﾞｼﾞｷﾞｮｳﾌﾞ | Y9: ㈱関東甲信クボタ 南関東事業所 | Z9: 260-0808 | AA9: 千葉県 千葉市 中央区 星久喜町176-4 | AB9: 043-261-3131
A10: 商品番号 | B10: 商品名 | E10: 数量 | F10: 単位 | G10: 単価 | I10: オーダーＮｏ 等 | L10: 税別小売 | N10: 通常 | P10: =IF(A4="","",VLOOKUP(A4,請求先!A:D,4,FALSE)) -> 0.7 | Q10: 値引 | R10: =$N$8/100 -> 0.08 | S10: 最終 | T10: =IF(L8="外掛",P10-R10,IF(L8="内掛",ROUNDDOWN(P10*(100-100*R10)%,5))) -> 0.62 | W10: 61111 | X10: ﾅｶﾔｼｮｳｶｲ | Y10: ㈱中屋商会 | Z10: 289-2146 | AA10: 千葉県 匝瑳市 八日市場ホ452 | AB10: 0479-72-1161
A11: 0334-0420 | B11: =IFERROR(VLOOKUP(A11,商品コード!A:C,2,FALSE)," ") -> HRC665S/M (ｾﾙ仕様） | E11: 1 | G11: =O13 -> 0 | K11: → | L11: =IF(A11="","",VLOOKUP(A11,商品コード!A:C,3,FALSE)) -> 698000 | N11: =IFERROR(IF(A4=61121,ROUNDDOWN((L11*P10),-1),IF(A4=61123,ROUNDDOWN((L11*P10),-1),IF(A4=64445001,ROUNDDOWN((L11*P10),-1),IF(A4=64445002,ROUNDDOWN((L11*P10),-1),ROUNDDOWN(L11*P10,-2)))))," ") -> 488600 | Q11: =IFERROR(S11-N11," ") -> -55900 | S11: =IFERROR(IF(OR(A4=61121,A4=61123,A4=64445001,A4=64445002),IF(L8="内掛",ROUNDDOWN(N11*(1-R10),-1),ROUNDDOWN(L11*T10,-1)),IF(L8="内掛",ROUNDDOWN(N11*(1-R10),-2),ROUNDDOWN(L11*T10,-2)))," ") -> 432700 | W11: 61112 | X11: ﾅｶﾑﾗｻﾝｷﾞｮｳ | Y11: ㈱中村産業 | Z11: 283-0811 | AA11: 千葉県 東金市 台方246 | AB11: 0475-52-2615
B12: =IFERROR(VLOOKUP(A12,商品コード!A:C,2,FALSE)," ") | G12: =O14 -> 0 | K12: → | L12: =IF(A12="","",VLOOKUP(A12,商品コード!A:C,3,FALSE)) | N12: =IFERROR(IF(A4=61121,ROUNDDOWN((L12*P10),-1),IF(A4=61123,ROUNDDOWN((L12*P10),-1),IF(A4=64445001,ROUNDDOWN((L12*P10),-1),IF(A4=64445002,ROUNDDOWN((L12*P10),-1),ROUNDDOWN(L12*P10,-2)))))," ") | Q12: =IFERROR(S12-N12," ") | S12: =IFERROR(IF(OR(A4=61121,A4=61123,A4=64445001,A4=64445002),IF(L8="内掛",ROUNDDOWN(N12*(1-R10),-1),ROUNDDOWN(L12*T10,-1)),IF(L9="内掛",ROUNDDOWN(N12*(1-R10),-2),ROUNDDOWN(L12*T10,-2)))," ") | W12: 61113 | X12: ﾌﾀﾊﾞｺｳｷ | Y12: ㈲双葉工機 | Z12: 270-2222 | AA12: 千葉県 松戸市 高塚新田340-11 | AB12: 0473-92-7256
B13: =IFERROR(VLOOKUP(A13,商品コード!A:C,2,FALSE)," ") | G13: =O15 -> 0 | K13: → | L13: =IF(A13="","",VLOOKUP(A13,商品コード!A:C,3,FALSE)) | N13: =IFERROR(IF(A4=61121,ROUNDDOWN((L13*P10),-1),IF(A4=61123,ROUNDDOWN((L13*P10),-1),IF(A4=64445001,ROUNDDOWN((L13*P10),-1),IF(A4=64445002,ROUNDDOWN((L13*P10),-1),ROUNDDOWN(L13*P10,-2)))))," ") | Q13: =IFERROR(S13-N13," ") | S13: =IFERROR(IF(OR(A4=61121,A4=61123,A4=64445001,A4=64445002),IF(L8="内掛",ROUNDDOWN(N13*(1-R10),-1),ROUNDDOWN(L13*T10,-1)),IF(L10="内掛",ROUNDDOWN(N13*(1-R10),-2),ROUNDDOWN(L13*T10,-2)))," ") | W13: 61114 | X13: ﾓﾊﾞﾗﾌｺｸｼｬ | Y13: ㈱茂原富国社 | Z13: 297-0029 | AA13: 千葉県 茂原市 高師1671 | AB13: 0475-25-0325
B14: =IFERROR(VLOOKUP(A14,商品コード!A:C,2,FALSE)," ") | G14: =O16 -> 0 | K14: → | L14: =IF(A14="","",VLOOKUP(A14,商品コード!A:C,3,FALSE)) | N14: =IFERROR(IF(A4=61121,ROUNDDOWN((L14*P10),-1),IF(A4=61123,ROUNDDOWN((L14*P10),-1),IF(A4=64445001,ROUNDDOWN((L14*P10),-1),IF(A4=64445002,ROUNDDOWN((L14*P10),-1),ROUNDDOWN(L14*P10,-2)))))," ") | Q14: =IFERROR(S14-N14," ") | S14: =IFERROR(IF(OR(A4=61121,A4=61123,A4=64445001,A4=64445002),IF(L8="内掛",ROUNDDOWN(N14*(1-R10),-1),ROUNDDOWN(L14*T10,-1)),IF(L10="内掛",ROUNDDOWN(N14*(1-R10),-2),ROUNDDOWN(L14*T10,-2)))," ") | W14: 61115 | X14: ｲﾊﾞﾗｷﾘｮｳﾉｳ | Y14: 茨城菱農㈱ | Z14: 300-4201 | AA14: 茨城県 つくば市 寺具1332-9 | AB14: 0298-69-1045
B15: =IFERROR(VLOOKUP(A15,商品コード!A:C,2,FALSE)," ") | G15: =O17 -> 0 | L15: 生産日 | N15: 45870 | W15: 61116 | X15: ｶﾝﾄｳｺｳｼﾝｸﾎﾞﾀｲﾊﾞﾗｷｼﾞﾑｼｮ | Y15: ㈱関東甲信クボタ 茨城事務所 | Z15: 300-2402 | AA15: 茨城県 つくばみらい市 坂野新田12-42 | AB15: 0297-52-1111
B16: =IFERROR(VLOOKUP(A16,商品コード!A:C,2,FALSE)," ") | G16: =O18 -> 0 | W16: 61117 | X16: ｵｵｶﾜｷｶｲ | Y16: 大川機械 | Z16: 300-0024 | AA16: 茨城県 土浦市 田村町988-2 | AB16: 0298-28-0755
A17: 倉庫（ | B17: 2001 | C17: ） | D17: 運賃 | E17: 元払い | F17: 伝票NO： | W17: 61118 | X17: ﾐﾂﾋﾞｼﾉｳｷﾊﾝﾊﾞｲｲﾊﾞﾗｷｼﾃﾝ | Y17: 三菱農機販売㈱ 茨城支店 | Z17: 311-0133 | AA17: 茨城県 那珂市 鴻巣1135-1 | AB17: 0293-53-2140
A18: 納入済み 機番:JQBFB00062 | E18: 立 元 | F18: 出荷確認 | H18: 受注可否検討 | J18: 連絡書作成 | W18: 61120 | X18: ｼﾏｻﾉｳｷ | Y18: ㈱嶋田農機 | Z18: 300-3544 | AA18: 茨城県 結城郡 八千代町 若996 | AB18: 0296-48-1025
E19: 着払い | F19: 承認 | H19: 承認 | J19: 作成者 | W19: 61121 | X19: ｸﾎﾞﾀｲﾊﾞﾗｷｹﾝｴｲｷﾞｮｳﾀﾝﾄｳ | Y19: ㈱クボタ 茨城県営業担当 | Z19: 338-0832 | AA19: 埼玉県 さいたま市 桜区 西堀5-2-36 | AB19: 048-862-1125
C20: 便名： | D20: 福山便 西濃便 JPロジ | W20: 61122 | X20: ﾅﾘﾀｶﾄｳﾉｳｷ | Y20: 成田加藤農機（有） | Z20: 286-0021 | AA20: 千葉県 成田市 土屋1375-1 | AB20: 0476-22-0579
W21: 61123 | X21: ｸﾎﾞﾀﾄﾁｷﾞｹﾝｴｲｷﾞｮｳﾀﾝﾄｳ | Y21: ㈱クボタ 栃木県営業担当 | Z21: 338-0832 | AA21: 埼玉県 さいたま市 桜区 西堀5-2-36 | AB21: 048-862-1125
W22: 61124 | X22: ﾈﾓﾄｼｮｳｶｲ | Y22: ㈲根本商会 | Z22: 286-0801 | AA22: 千葉県 成田市 竜台468 | AB22: 0476-37-1211
A23: （様式：EL-97A03） | D23: 【 値引 】 | W23: 61125 | X23: ﾏﾙﾃﾝｻﾝｷﾞｮｳｷｶｲ | Y23: マルテン産業機械㈱ | Z23: 293-0001 | AA23: 千葉県 富津市 大堀1434 | AB23: 0439-87-0052
A24: 引き合い内容連絡書 | J24: 株式会社オーレック | W24: 61126 | X24: ﾐﾂﾋﾞｼﾉｳｷﾊﾝﾊﾞｲﾁﾊﾞｼﾃﾝ | Y24: 三菱農機販売㈱ 千葉支店 | Z24: 300-1312 | AA24: 茨城県 稲敷郡 河内町 長竿字西の町1596-2 | AB24: 0297-63-4633
A25: 得意先NO： | B25: 得意先名 及び 担当者名： | I25: 受注日： | W25: 61127 | X25: ｸﾎﾞﾀｸﾞﾝﾏｹﾝｴｲｷﾞｮｳﾀﾝﾄｳ | Y25: ㈱クボタ 群馬県営業担当 | Z25: 338-0832 | AA25: 埼玉県 さいたま市 桜区 西堀5-2-36 | AB25: 048-862-1125
A26: 61377 | C26: =C4 -> マルテン産業機械㈱ | I26: =I4 -> 46199 | W26: 61133 | X26: ﾏｷﾀﾇﾏﾂﾞﾋｶﾞｼﾆﾎﾝ | Y26: ㈱マキタ沼津 東日本支店 | Z26: 362-0031 | AA26: 埼玉県 上尾市 東町2-8-4 | AB26: 048-779-2262
A27: 納入先NO： | B27: 納入先名及び 担当者名： | I27: 出荷希望日： | W27: 61134 | X27: ｸﾎﾞﾀｹﾝｷｼﾞｬﾊﾟﾝﾁﾊﾞｴｲｷﾞｮｳｼｮ | Y27: ㈱クボタ建機ジャパン千葉営業所 | Z27: 283-0823 | AA27: 千葉県 東金市 山田 字新田1201-10 | AB27: 茨城菱農
A28: 69012068 | C28: =C6 -> マルテン産業機械㈱ | I28: =I6 -> 46199 | W28: 61135 | X28: ｵｵｻﾜｷｶｲ | Y28: 大沢機械 | Z28: 191-0043 | AA28: 東京都 日野市 平山6-2-1 | AB28: 042-591-1588
B29: 住所： | I29: TEL | W29: 61136 | X29: ｼﾊﾞﾀ | Y29: ㈱シバタ | Z29: 104-0032 | AA29: 東京都 中央区 八丁堀4-3-1 | AB29: 03-3552-0381
W30: 61140 | X30: ﾏｷﾀﾇﾏﾂﾞｷﾞｮｳﾑﾌﾞｼｮｳﾋﾝｶ | Y30: ㈱マキタ沼津 業務部商品課 | Z30: 410-0022 | AA30: 静岡県 沼津市 大岡35 | AB30: 055-963-1112
W31: 61301 | X31: ｶﾅｴｻﾝｷﾞｮｳ | Y31: カナエ産業㈱ | Z31: 194-0215 | AA31: 東京都 町田市 小山ケ丘3-7-10 | AB31: 042-798-7181
A32: 商品番号 | B32: 商品名 | E32: 数量 | F32: 値引後(仕切) | H32: 単価 | J32: 合計 | W32: 61302 | X32: ﾖｼｻﾞﾜｹﾞﾝﾄﾞｳｷ | Y32: 吉澤原動機 | Z32: 114-0013 | AA32: 東京都 北区 東田端2-8-6 | AB32: 03-3810-2700
A33: =A11 -> 0334-0420 | B33: =B11 -> HRC665S/M (ｾﾙ仕様） | E33: =E11 -> 1 | F33: =S11 -> 432700 | H33: =IFERROR(Q11," ") -> -55900 | J33: =IFERROR(H33*E33," ") -> -55900 | W33: 61303 | X33: ﾐﾔｼﾞｷｶｲ | Y33: ㈱宮地機械（出荷停止） | Z33: 177-0033 | AA33: 東京都 練馬区 高野台4-11-28 | AB33: 03-3997-3155
A34: =A12 -> 0 | B34: =B12 | E34: =E12 -> 0 | F34: =S12 | H34: =IFERROR(Q12," ") | J34: =IFERROR(H34*E34," ") | W34: 61304 | X34: ﾊﾁｷﾞｮｳｼｮｳｼﾞ | Y34: 八丈商事 | Z34: 100-1401 | AA34: 東京都 八丈島 八丈町 大賀郷1098-2 | AB34: 04996-2-2189
A35: =A13 -> 0 | E35: =E13 -> 0 | F35: =S13 | H35: =IFERROR(Q13," ") | J35: =IFERROR(H35*E35," ") | W35: 61305 | X35: ｲｼｲﾃﾞﾝｷｼｮｳﾃﾝ | Y35: ㈱石井電気商店 | Z35: 294-0042 | AA35: 千葉県 館山市 上野原294-5 | AB35: 0470-22-0542
A36: =A14 -> 0 | B36: =B14 | E36: =E14 -> 0 | F36: =S14 | H36: =IFERROR(Q14," ") | J36: =IFERROR(H36*E36," ") | W36: 61306 | X36: ｲｺﾞｳﾉｳｷ | Y36: ㈲井合農機店 | Z36: 273-0047 | AA36: 千葉県 船橋市 藤原5-22-31 | AB36: 047-439-5477
A37: =A15 -> 0 | B37: =B15 | E37: =E15 -> 0 | F37: =S15 -> 0 | H37: =IFERROR(-(S17)," ") -> 0 | J37: =IFERROR(H37*E37," ") -> 0 | W37: 61307 | X37: ｲｼｲﾃｯｺｳ | Y37: 石井鉄工㈱ | Z37: 299-4218 | AA37: 千葉県 長生郡 白子町 関4549-2 | AB37: 0475-33-3528
A38: =A16 -> 0 | B38: =B16 | E38: =E16 -> 0 | F38: =Q18 -> 0 | H38: =IFERROR(-(S18)," ") -> 0 | J38: =IFERROR(H38*E38," ") -> 0 | W38: 61308 | X38: ｲﾉｳｴﾉｳｷｼｮｳｶｲ | Y38: ㈲井上農機商会 | Z38: 299-4501 | AA38: 千葉県 いすみ市 岬町椎木1793 | AB38: 0470-87-2823
A39: 税抜小売 | B39: 掛率 | C39: 単価 | D39: OBIC照合 | F39: 伝票NO： | H39: 合計 | J39: =SUM(J33:J36) -> -55900 | W39: 61309 | X39: ｵｵﾏﾁﾉｳｷ | Y39: ㈲大町農機 | Z39: 272-0801 | AA39: 千葉県 市川市 大町453 | AB39: 047-338-1210
A40: =L11 -> 698000 | B40: =T10 -> 0.62 | C40: =F33 -> 432700 | D40: =IFERROR((E33*C40)," ") -> 432700 | F40: 出荷確認 | H40: 受注可否検討 | J40: 連絡書作成 | W40: 61310 | X40: ｲｼﾞﾏｼｮｳﾃﾝ | Y40: ㈲木嶋商店 | Z40: 289-1115 | AA40: 千葉県 八街市 八街ほ377 | AB40: 0434-44-2481
A41: =L12 | B41: =T10 -> 0.62 | C41: =F34 | D41: =IFERROR((E34*C41)," ") | F41: 承認 | H41: 承認 | J41: 作成者 | W41: 61311 | X41: ｻｻｿﾈﾉｳｷ | Y41: 笹曽根農機 | Z41: 289-2135 | AA41: 千葉県 匝瑳市 高野898 | AB41: 0479-72-0781
A42: =L13 | B42: =T10 -> 0.62 | C42: =F35 | D42: =IFERROR((E35*C42)," ") | E42: OBIC計 | W42: 61312 | X42: ﾌｶｻﾜﾉｳｷｼｮｳｶｲ | Y42: 深沢農機商会 | Z42: 196-0004 | AA42: 東京都 昭島市 緑町3-6-26 | AB42: 042-543-2759
A43: =L14 | B43: =T10 -> 0.62 | C43: =F36 | D43: =IFERROR((E36*C43)," ") | E43: =SUM(D40:D43) -> 432700 | W43: 61313 | X43: ｽｽﾞｷﾉｳｷ | Y43: ㈲鈴木農機 | Z43: 283-0046 | AA43: 千葉県 東金市 上谷956 | AB43: 0475-52-4511
A44: 値引理由； | B44: =L7 -> 実演機値引 | C44: =N8/100 -> 0.08 | D44: 通常仕切； | E44: =IFERROR(VLOOKUP(A4,請求先!A:D,4,FALSE)," ") -> 0.7 | W44: 61314 | X44: ｽﾐﾉﾃｯｺｳｼｮ | Y44: 住野鉄工所 | Z44: 289-1107 | AA44: 千葉県 八街市 八街は15 | AB44: 0434-44-1904
W45: 61315 | X45: ﾀｶﾊｼｷｶｲ | Y45: ㈲高橋機械 | Z45: 271-0092 | AA45: 千葉県 松戸市 松戸1877-1 | AB45: 0473-62-0101
W46: 61317 | X46: ﾋｶﾘﾐﾅﾄﾔｼｮｳｶｲ | Y46: ㈲光港屋商会 | Z46: 289-1727 | AA46: 千葉県 山武郡 横芝光町 宮川5460-1 | AB46: 0479-84-0611
W47: 61319 | X47: ﾐﾔｳﾁｷｺｳ | Y47: 宮内機工 | Z47: 286-0211 | AA47: 千葉県 富里市 御料69-8 | AB47: 0476-93-5793
W48: 61320 | X48: ﾐﾅﾄﾔﾉｳｷｼｮｳｶｲ | Y48: ㈲港屋農機商会 | Z48: 283-0005 | AA48: 千葉県 東金市 田間2132 | AB48: 0475-52-2246
W49: 61321 | X49: ﾔﾏｷﾉｳｷﾃﾝ | Y49: ㈲山木農機店 | Z49: 294-0052 | AA49: 千葉県 館山市 亀ヶ原835 | AB49: 0470-36-2021
W50: 61322 | X50: ﾖｳｶｲﾁﾊﾞﾉｳｷ | Y50: ㈲八日市場農機 | Z50: 289-2144 | AA50: 千葉県 匝瑳市 八日市場イ780-1 | AB50: 0479-72-1287
W51: 61323 | X51: ｵｵﾀｹｻﾝｷﾞｮｳ | Y51: ㈱大竹産業 | Z51: 286-0041 | AA51: 千葉県 成田市 飯田町1-6 | AB51: 0476-22-2333
W52: 61324 | X52: ﾀｹﾂﾞｶｷｶｲﾃﾝ | Y52: ㈱竹塚機械店 | Z52: 278-0033 | AA52: 千葉県 野田市 上花輪849 | AB52: 04-7125-1711
W53: 61325 | X53: ｺﾝﾄﾞｳﾉｳｺｳｼｬ | Y53: ㈱近藤農工舎 | Z53: 290-0008 | AA53: 千葉県 市原市 古市場347 | AB53: 0436-41-3723
W54: 61328 | X54: ｲｼﾀﾞｷｶｲﾃﾝ | Y54: ㈱石田機械店 | Z54: 270-0176 | AA54: 千葉県 流山市 加6丁目1545 | AB54: 04-7158-1257
W55: 61329 | X55: ｶﾏﾘ | Y55: ㈱カマリ | Z55: 310-0836 | AA55: 茨城県 水戸市 元吉田町1267-4 | AB55: 029-304-3366
W56: 61330 | X56: ﾋﾗｶﾞｷｺｳ | Y56: 平賀機工 | Z56: 309-1703 | AA56: 茨城県 笠間市 鯉淵6520-67 | AB56: 0296-77-0183
... W95: 61376 | X95: ﾘｮｳｴｲｼｬ | Y95: ㈲良栄社商会 | Z95: 299-1151 | AA95: 千葉県 君津市 中野4-15-18 | AB95: 0439-52-0035
X96: ｺｼﾞﾝｷｬｸ | Y96: 個人客
W97: 61400 | X97: ｺﾐﾔﾉｳｻﾝｷｼｮｳｶｲ | Y97: ㈲古宮農蚕機商会 | Z97: 192-0051 | AA97: 東京都 八王子市 元本郷町1-5-5 | AB97: 042-625-2328
W98: 63102 | X98: ﾐﾂﾋﾞｼﾉｳｷﾊﾝﾊﾞｲｶﾝﾄｳｺｳｼﾝｴﾂ | Y98: 三菱農機販売㈱ 関東甲信越支店 | Z98: 340-0203 | AA98: 埼玉県 久喜市 桜田2-133-4 | AB98: 0480-58-9521
W99: 63103 | X99: ｶﾝﾄｳｺｳｼﾝｸﾎﾞﾀｸﾎﾞﾀﾄﾁｷﾞｼﾞﾑｼｮ | Y99: ㈱関東甲信クボタ 北関東事業所 （栃木） | Z99: 321-0905 | AA99: 栃木県 宇都宮市 平出工業団地28-2 | AB99: 0286-89-2341
W100: 63105 | X100: ﾐﾂﾋﾞｼﾉｳｷﾊﾝﾊﾞｲﾄﾁｷﾞｼﾃﾝ | Y100: 三菱農機販売㈱ 栃木支店 | Z100: 329-1233 | AA100: 栃木県 塩谷郡 高根沢町 宝積寺 中2248-60 | AB100: 0286-75-7321
W101: 63112 | X101: ﾀｶﾀﾞﾗｸﾉｳｷ | Y101: 高田酪農機㈱ | Z101: 321-3236 | AA101: 栃木県 宇都宮市 竹下町1101-11 | AB101: 028-667-2825
W102: 63301 | X102: ｺﾋﾞｷﾉｳｷｸﾞﾃﾝ | Y102: 小比企農機具店 | Z102: 326-0845 | AA102: 栃木県 足利市 大前町207 | AB102: 0284-62-2065
W103: 63302 | X103: ﾇﾉｶﾜﾉｳｷｸﾞﾃﾝ | Y103: 布川農機具店 | Z103: 329-4404 | AA103: 栃木県 栃木市 大平町富田1430 | AB103: 0282-43-2013
W104: 63303 | X104: ｽﾅｶﾉｳｷｸﾞﾃﾝ | Y104: 砂川農機具店 | Z104: 326-0323 | AA104: 栃木県 足利市 瑞穂野町495 | AB104: 0284-71-9033
W105: 63304 | X105: ｽｽﾞｷﾔ | Y105: ㈱鈴木屋 | Z105: 329-0205 | AA105: 栃木県 小山市 間々田1290 | AB105: 0285-45-0070
W106: 63305 | X106: ｶﾜﾀ | Y106: ㈱川田 | Z106: 322-0002 | AA106: 栃木県 鹿沼市 千渡2315-66 | AB106: 0289-65-3366
W107: 63306 | X107: ｺﾀﾞｲﾗﾉｳｷｼｮｳｶｲ | Y107: 小平農機商会 | Z107: 321-1261 | AA107: 栃木県 日光市 今市107-22 | AB107: 0288-21-0845
W108: 63307 | X108: ｻｲﾄｳﾉｳｷｼｮｳｶｲ | Y108: ㈲斉藤農機商会 | Z108: 329-2161 | AA108: 栃木県 矢板市 扇町1-11-19 | AB108: 0287-43-0475
... W206: 64391 | X206: ｶﾝﾄｳｺｳｼﾝｸﾎﾞﾀｸﾞﾝﾏｼﾞﾑｼｮ | Y206: ㈱関東甲信クボタ 群馬事務所 | Z206: 379-2154 | AA206: 群馬県 前橋市 天川大島町1364-1 | AB206: 027-261-6010
W207: 64398 | X207: ｶﾝﾄｳｹﾞﾝｷﾝｷｬｸ | Y207: 関東現金客
W208: 64399 | X208: ｺｼﾞﾝｷｬｸ | Y208: 個人客
W209: 64444 | X209: ﾐﾂﾋﾞｼﾉｳｷﾋｶﾞｼﾆﾎﾝﾌﾞﾋﾝｷｶﾝｾﾝﾀｰ | Y209: 三菱農機㈱ 東日本部品基幹センター | Z209: 340-0203 | AA209: 埼玉県 久喜市 桜田2-133-4 | AB209: 0480-58-9515
W210: 64445 | X210: ﾐﾂﾋﾞｼﾉｳｷ | Y210: 三菱ﾏﾋﾝﾄﾞﾗ農機㈱ 島根県 | Z210: 699-0101 | AA210: 島根県 松江市 東出雲町 揖屋667-1 | AB210: 0852-52-2111
W211: 65130 | X211: ｿｳﾌﾞｷｶｲ | Y211: ㈱相武機械 | Z211: 215-0003 | AA211: 神奈川県 川崎市 麻生区 高石3-31-27 | AB211: 044-966-4161
W212: 65131 | X212: ﾓﾘﾁｮｳ | Y212: 森長 | Z212: 254-0041 | AA212: 神奈川県 平塚市 浅間町5-27 | AB212: 0463-31-2195
W213: 65132 | X213: ｶﾝﾄｳｺｼﾝｸﾎﾞﾀｾｲｼﾝｼﾞｷﾞｮｳﾌﾞ | Y213: ㈱関東甲信クボタ 静神事業部 | Z213: 411-0817 | AA213: 静岡県 三島市 八反畑 字鶴田100 | AB213: 055-972-0800
W214: 65137 | X214: ｴﾙﾀ | Y214: ㈱エルタ | Z214: 190-1221 | AA214: 東京都 西多摩郡 瑞穂町 箱根ケ崎 東松原20-1 | AB214: 0425-56-0184
W215: 65323 | X215: ｵｵﾀｹﾉｳｷ | Y215: 大竹農機㈱ | Z215: 289-1115 | AA215: 千葉県 八街市 八街ほ244 | AB215: 043-444-0225
W216: 65347 | X216: ｶﾓｼﾀﾞｼｮｳｶｲ | Y216: 鴨志田商会 | Z216: 226-0000 | AA216: 神奈川県 横浜市 緑区 川和町1437 | AB216: 045-931-1038
W217: 65348 | X217: ｷｼﾀﾞﾉｳｷｼｮｳｶｲ | Y217: ㈱岸田農機商会 | Z217: 259-1131 | AA217: 神奈川県 伊勢原市 伊勢原1-7-18 | AB217: 0463-95-0121
W218: 65350 | X218: ｻｶﾞﾐﾉｳｷ | Y218: さがみ農機 | Z218: 258-0001 | AA218: 神奈川県 足柄上郡 松田町 寄5501 | AB218: 0465-89-2329
W219: 65351 | X219: ｽｽﾞﾉﾉｳｷ | Y219: ㈲鈴野農機 | Z219: 252-0826 | AA219: 神奈川県 藤沢市 宮原1348 | AB219: 0466-48-1048
W220: 65352 | X220: ﾀﾅｶﾉｳｷｼｮｳｶｲ | Y220: 田中農機商会 | Z220: 252-0807 | AA220: 神奈川県 藤沢市 下土棚444 | AB220: 0466-44-2005
... W244: 2133075 | X244: ﾂｸﾊﾞｼｻｸﾗﾉｳｷｾﾝﾀｰ | Y244: JAつくば市 桜農機センター | Z244: 305-0027 | AA244: 茨城県 つくば市 東岡335 | AB244: 029-857-3116
W245: 2133107 | Y245: JA常陸 みなみ農機センター | Z245: 319-1234 | AA245: 茨城県 日立市 大和田町1992 | AB245: 0294-53-2121
W246: 2133110 | X246: ﾏｼｰﾈｵﾐﾀﾏ | Y246: JAマシーネ 小美玉 | Z246: 311-3412 | AA246: 茨城県 小美玉市 川戸1450-58 | AB246: 0299-58-5644
W247: 2133115 | X247: ﾐﾄﾉｳｷｮｳﾐﾄﾉｳｷｾﾝﾀｰ | Y247: JA水戸農協 水戸農機センター | Z247: 311-4141 | AA247: 茨城県 水戸市 赤塚2-27 | AB247: 029-252-2076
W248: 2133147 | X248: ﾅﾒｶﾞﾀﾉｳｷﾈﾝﾘｮｳ | Y248: JAなめがた農機燃料㈱ 南部農機センター | Z248: 311-3835 | AA248: 茨城県 行方市 島並857-16 | AB248: 0299-72-1651
W249: 2134054 | X249: ｸﾏｶﾞﾔｸﾏｶﾞﾔﾉｳｷｾﾝﾀｰ | Y249: JAくまがや 熊谷農機センター | Z249: 360-0805 | AA249: 埼玉県 熊谷市 上奈良1079-1 | AB249: 048-523-9291
W250: 2134057 | X250: ｸﾏｶﾞﾔｺｳﾅﾝﾉｳｷｾﾝﾀｰ | Y250: JAくまがや 江南農機センター | Z250: 360-0115 | AA250: 埼玉県 熊谷市 成沢490-1 | AB250: 048-536-1404
W251: 2134071 | X251: ｲﾙﾏﾉﾎｸﾌﾞﾉｳｷｾﾝﾀｰ | Y251: JAいるま野 北部農機センター | Z251: 350-0212 | AA251: 埼玉県 坂戸市 石井1880 | AB251: 049-289-2172
W252: 2134072 | X252: ｻｲﾀﾏｻｼｵｳｷﾞｼﾃﾝ | Y252: JAさいたま 指扇支店 | Z252: 331-0071 | AA252: 埼玉県 さいたま市 西区 高木337-3 | AB252: 048-623-5011
W253: 2134091 | X253: ｲﾙﾏﾉﾄｺﾛｻﾞﾜﾉｳｷｾﾝﾀｰ | Y253: JAいるま野 所沢農機センター | Z253: 359-0001 | AA253: 埼玉県 所沢市 下富627-10 | AB253: 042-942-3467
W254: 2134092 | Y254: JAちちぶ農協秩父自動車センター | Z254: 368-0056 | AA254: 埼玉県 秩父市 寺尾3218-1 | AB254: 0494-25-2555
W255: 2134107 | X255: ｻｲﾀﾏﾁｭｳｵｳﾋｶﾞｼﾏﾂﾔﾏﾉｳｷｾﾝﾀｰ | Y255: JA埼玉中央 東松山農機センター | Z255: 355-0073 | AA255: 埼玉県 東松山市 上野本1405-1 | AB255: 0493-24-3159
W256: 2135169 | X256: ｷﾐﾂ | Y256: JAきみつ 平川農機整備工場 | Z256: 299-0205 | AA256: 千葉県 袖ヶ浦市 上泉366 | AB256: 0438-75-4007
W257: 2135181 | X257: ﾁｮｳｾｲﾉｳｷｮｳ | Y257: JA長生農協 睦沢農機センター | Z257: 299-4403 | AA257: 千葉県 長生郡 睦沢町 上市場914 | AB257: 0475-44-1236
W258: 2135187 | X258: ｷﾐﾂ | Y258: JAきみつ 天羽農機整備工場 | Z258: 299-1618 | AA258: 千葉県 富津市 花輪150 | AB258: 0439-80-7650
...

Sheet 引合書+値引
A1: （様式：EL-97A03） | V1: 納入先コード | W1: 納入先カナ名 | X1: 納入先正式名 | Y1: 郵便番号1 | Z1: 住所1 | AA1: 電話番号1-1
A2: 引き合い内容連絡書 | J2: 株式会社オーレック | V2: 61102 | W2: ﾆﾎﾝｸﾘﾝﾄﾝ | X2: 日本クリントン㈱ | Y2: 121-0836 | Z2: 東京都 足立区 入谷5-7-8 | AA2: 03-3854-8221
A3: 得意先NO： | B3: 得意先名 及び 担当者名： | I3: 受注日： | V3: 61103 | W3: ﾄｳｺｳｻﾝｷﾞｮｳ | X3: 東興産業㈱ | Y3: 350-0821 | Z3: 埼玉県 川越市 福田239 | AA3: 0492-23-1217
A4: 61376 | C4: =IFERROR(VLOOKUP(A4,請求先!A:D,2,FALSE)," ") -> 有限会社 良栄社商会 | I4: =TODAY() -> 46201 | L4: 製品コード検索 | V4: 61105 | W4: ｲﾄｳｻﾝｷﾞｮｳｷｶｲ | X4: 伊藤産業機械㈱ | Y4: 290-0034 | Z4: 千葉県 市原市 島野1978 | AA4: 0436-22-1743
A5: 納入先NO： | B5: 納入先名及び 担当者名： | G5: 生産日 | H5: 在庫 | I5: 出荷希望日： | L5: RM984X/K | Q5: → | R5: =IFERROR(VLOOKUP(L5,商品コード!B:F,5,FALSE)," ") -> 0352-0110 | V5: 61106 | W5: ｴﾑｴｽｹｰﾉｳｷﾞｮｳｷｶｲﾁﾊﾞｼﾞｷﾞｮｳｼｮ | X5: MSK東急機械㈱ 千葉事業所 | Y5: 290-0012 | Z5: 千葉県 市原市 藤井3-310 | AA5: 0436-41-1069
A6: 61376 | C6: =IFERROR(VLOOKUP(A6,出荷先!A:F,3,FALSE)," ") -> ㈲良栄社商会 | I6: 46196 | V6: 61107 | W6: ｻｻｷｼｮｳｶｲ | X6: ㈱佐々木商会 | Y6: 294-0037 | Z6: 千葉県 館山市 長須賀123 | AA6: 0470-22-1166
B7: 住所： | C7: 〒 | D7: =IFERROR(VLOOKUP(A6,出荷先!A:F,4,FALSE)," ") -> 299-1151 | I7: TEL | L7: 実演機対応値引 | Q7: =IF(Q6="","",VLOOKUP(Q6,#REF!,2,FALSE)) | V7: 61108 | W7: ｽｷﾞｷﾃｯｺｳ | X7: 杉木鉄工㈱ | Y7: 297-0029 | Z7: 千葉県 茂原市 高師1536 | AA7: 0475-22-4587
B8: =IFERROR(VLOOKUP(A6,出荷先!A:F,5,FALSE)," ") -> 千葉県 君津市 中野4-15-18 | I8: =IFERROR(VLOOKUP(A6,出荷先!A:F,6,FALSE)," ") -> 0439-52-0035 | L8: =IF(L7="","",VLOOKUP(L7,商品コード!A:B,2,FALSE)) -> 外掛 | M8: =IF(I8="","",VLOOKUP(I8,商品コード!#REF!,2,FALSE)) -> #REF! | N8: 8 | P8: % | V8: 61109 | W8: ﾀｶﾉｻﾝｷﾞｮｳ | X8: 高野産業㈱ | Y8: 292-0054 | Z8: 千葉県 木更津市 長須賀924-1 | AA8: 0438-22-6251
N9: ] | V9: 61110 | W9: ｶﾝﾄｳｺｼﾝｸﾎﾞﾀﾁﾊﾞｼﾞｷﾞｮｳﾌﾞ | X9: ㈱関東甲信クボタ 南関東事業所 | Y9: 260-0808 | Z9: 千葉県 千葉市 中央区 星久喜町176-4 | AA9: 043-261-3131
A10: 商品番号 | B10: 商品名 | E10: 数量 | F10: 単位 | G10: 単価 | I10: オーダーＮｏ 等 | L10: 税別小売 | N10: 通常 | P10: =IF(A4="","",VLOOKUP(A4,請求先!A:D,4,FALSE)) -> 0.68 | Q10: 値引 | R10: =$N$8/100 -> 0.08 | S10: 最終 | T10: =IF(L8="外掛",P10-R10,IF(L8="内掛",ROUNDDOWN(P10*(100-100*R10)%,5))) -> 0.6 | V10: 61111 | W10: ﾅｶﾔｼｮｳｶｲ | X10: ㈱中屋商会 | Y10: 289-2146 | Z10: 千葉県 匝瑳市 八日市場ホ452 | AA10: 0479-72-1161
A11: 0353-0020 | B11: =IFERROR(VLOOKUP(A11,商品コード!A:C,2,FALSE)," ") -> SP753B/M | E11: 1 | G11: =O13 -> 0 | K11: → | L11: =IF(A11="","",VLOOKUP(A11,商品コード!A:C,3,FALSE)) -> 328000 | N11: =IFERROR(IF(A4=61121,ROUNDDOWN((L11*P10),-1),IF(A4=61123,ROUNDDOWN((L11*P10),-1),IF(A4=64445001,ROUNDDOWN((L11*P10),-1),IF(A4=64445002,ROUNDDOWN((L11*P10),-1),ROUNDDOWN(L11*P10,-2)))))," ") -> 223000 | Q11: =IFERROR(S11-N11," ") -> -26200 | S11: =IFERROR(IF(OR(A4=61121,A4=61123,A4=64445001,A4=64445002),IF(L8="内掛",ROUNDDOWN(N11*(1-R10),-1),ROUNDDOWN(L11*T10,-1)),IF(L8="内掛",ROUNDDOWN(N11*(1-R10),-2),ROUNDDOWN(L11*T10,-2)))," ") -> 196800 | V11: 61112 | W11: ﾅｶﾑﾗｻﾝｷﾞｮｳ | X11: ㈱中村産業 | Y11: 283-0811 | Z11: 千葉県 東金市 台方246 | AA11: 0475-52-2615
B12: =IFERROR(VLOOKUP(A12,商品コード!A:C,2,FALSE)," ") | G12: =O14 -> 0 | K12: → | L12: =IF(A12="","",VLOOKUP(A12,商品コード!A:C,3,FALSE)) | N12: =IFERROR(IF(A4=61121,ROUNDDOWN((L12*P10),-1),IF(A4=61123,ROUNDDOWN((L12*P10),-1),IF(A4=64445001,ROUNDDOWN((L12*P10),-1),IF(A4=64445002,ROUNDDOWN((L12*P10),-1),ROUNDDOWN(L12*P10,-2)))))," ") | Q12: =IFERROR(S12-N12," ") | S12: =IFERROR(IF(OR(A4=61121,A4=61123,A4=64445001,A4=64445002),IF(L8="内掛",ROUNDDOWN(N12*(1-R10),-1),ROUNDDOWN(L12*T10,-1)),IF(L9="内掛",ROUNDDOWN(N12*(1-R10),-2),ROUNDDOWN(L12*T10,-2)))," ") | V12: 61113 | W12: ﾌﾀﾊﾞｺｳｷ | X12: ㈲双葉工機 | Y12: 270-2222 | Z12: 千葉県 松戸市 高塚新田340-11 | AA12: 0473-92-7256
B13: =IFERROR(VLOOKUP(A13,商品コード!A:C,2,FALSE)," ") | G13: =O15 -> 0 | K13: → | L13: =IF(A13="","",VLOOKUP(A13,商品コード!A:C,3,FALSE)) | N13: =IFERROR(IF(A4=61121,ROUNDDOWN((L13*P10),-1),IF(A4=61123,ROUNDDOWN((L13*P10),-1),IF(A4=64445001,ROUNDDOWN((L13*P10),-1),IF(A4=64445002,ROUNDDOWN((L13*P10),-1),ROUNDDOWN(L13*P10,-2)))))," ") | Q13: =IFERROR(S13-N13," ") | S13: =IFERROR(IF(OR(A4=61121,A4=61123,A4=64445001,A4=64445002),IF(L8="内掛",ROUNDDOWN(N13*(1-R10),-1),ROUNDDOWN(L13*T10,-1)),IF(L10="内掛",ROUNDDOWN(N13*(1-R10),-2),ROUNDDOWN(L13*T10,-2)))," ") | V13: 61114 | W13: ﾓﾊﾞﾗﾌｺｸｼｬ | X13: ㈱茂原富国社 | Y13: 297-0029 | Z13: 千葉県 茂原市 高師1671 | AA13: 0475-25-0325
B14: =IFERROR(VLOOKUP(A14,商品コード!A:C,2,FALSE)," ") | G14: =O16 -> 0 | K14: → | L14: =IF(A14="","",VLOOKUP(A14,商品コード!A:C,3,FALSE)) | N14: =IFERROR(IF(A4=61121,ROUNDDOWN((L14*P10),-1),IF(A4=61123,ROUNDDOWN((L14*P10),-1),IF(A4=64445001,ROUNDDOWN((L14*P10),-1),IF(A4=64445002,ROUNDDOWN((L14*P10),-1),ROUNDDOWN(L14*P10,-2)))))," ") | Q14: =IFERROR(S14-N14," ") | S14: =IFERROR(IF(OR(A4=61121,A4=61123,A4=64445001,A4=64445002),IF(L8="内掛",ROUNDDOWN(N14*(1-R10),-1),ROUNDDOWN(L14*T10,-1)),IF(L10="内掛",ROUNDDOWN(N14*(1-R10),-2),ROUNDDOWN(L14*T10,-2)))," ") | V14: 61115 | W14: ｲﾊﾞﾗｷﾘｮｳﾉｳ | X14: 茨城菱農㈱ | Y14: 300-4201 | Z14: 茨城県 つくば市 寺具1332-9 | AA14: 0298-69-1045
B15: =IFERROR(VLOOKUP(A15,商品コード!A:C,2,FALSE)," ") | G15: =O17 -> 0 | L15: 生産日 | N15: 45870 | V15: 61116 | W15: ｶﾝﾄｳｺｳｼﾝｸﾎﾞﾀｲﾊﾞﾗｷｼﾞﾑｼｮ | X15: ㈱関東甲信クボタ 茨城事務所 | Y15: 300-2402 | Z15: 茨城県 つくばみらい市 坂野新田12-42 | AA15: 0297-52-1111
B16: =IFERROR(VLOOKUP(A16,商品コード!A:C,2,FALSE)," ") | G16: =O18 -> 0 | V16: 61117 | W16: ｵｵｶﾜｷｶｲ | X16: 大川機械 | Y16: 300-0024 | Z16: 茨城県 土浦市 田村町988-2 | AA16: 0298-28-0755
A17: 倉庫（ | B17: 031 | C17: ） | D17: 運賃 | E17: 元払い | F17: 伝票NO： | V17: 61118 | W17: ﾐﾂﾋﾞｼﾉｳｷﾊﾝﾊﾞｲｲﾊﾞﾗｷｼﾃﾝ | X17: 三菱農機販売㈱ 茨城支店 | Y17: 311-0133 | Z17: 茨城県 那珂市 鴻巣1135-1 | AA17: 0293-53-2140
E18: 立 元 | F18: 出荷確認 | H18: 受注可否検討 | J18: 連絡書作成 | V18: 61120 | W18: ｼﾏｻﾉｳｷ | X18: ㈱嶋田農機 | Y18: 300-3544 | Z18: 茨城県 結城郡 八千代町 若996 | AA18: 0296-48-1025
E19: 着払い | F19: 承認 | H19: 承認 | J19: 作成者 | V19: 61121 | W19: ｸﾎﾞﾀｲﾊﾞﾗｷｹﾝｴｲｷﾞｮｳﾀﾝﾄｳ | X19: ㈱クボタ 茨城県営業担当 | Y19: 338-0832 | Z19: 埼玉県 さいたま市 桜区 西堀5-2-36 | AA19: 048-862-1125
C20: 便名： | D20: 福山便 西濃便 JPロジ | V20: 61122 | W20: ﾅﾘﾀｶﾄｳﾉｳｷ | X20: 成田加藤農機（有） | Y20: 286-0021 | Z20: 千葉県 成田市 土屋1375-1 | AA20: 0476-22-0579
V21: 61123 | W21: ｸﾎﾞﾀﾄﾁｷﾞｹﾝｴｲｷﾞｮｳﾀﾝﾄｳ | X21: ㈱クボタ 栃木県営業担当 | Y21: 338-0832 | Z21: 埼玉県 さいたま市 桜区 西堀5-2-36 | AA21: 048-862-1125
V22: 61124 | W22: ﾈﾓﾄｼｮｳｶｲ | X22: ㈲根本商会 | Y22: 286-0801 | Z22: 千葉県 成田市 竜台468 | AA22: 0476-37-1211
A23: （様式：EL-97A03） | D23: 【 値引 】 | V23: 61125 | W23: ﾏﾙﾃﾝｻﾝｷﾞｮｳｷｶｲ | X23: マルテン産業機械㈱ | Y23: 293-0001 | Z23: 千葉県 富津市 大堀1434 | AA23: 0439-87-0052
A24: 引き合い内容連絡書 | J24: 株式会社オーレック | V24: 61126 | W24: ﾐﾂﾋﾞｼﾉｳｷﾊﾝﾊﾞｲﾁﾊﾞｼﾃﾝ | X24: 三菱農機販売㈱ 千葉支店 | Y24: 300-1312 | Z24: 茨城県 稲敷郡 河内町 長竿字西の町1596-2 | AA24: 0297-63-4633
A25: 得意先NO： | B25: 得意先名 及び 担当者名： | I25: 受注日： | V25: 61127 | W25: ｸﾎﾞﾀｸﾞﾝﾏｹﾝｴｲｷﾞｮｳﾀﾝﾄｳ | X25: ㈱クボタ 群馬県営業担当 | Y25: 338-0832 | Z25: 埼玉県 さいたま市 桜区 西堀5-2-36 | AA25: 048-862-1125
A26: =A4 -> 61376 | C26: =C4 -> 有限会社 良栄社商会 | I26: =I4 -> 46201 | V26: 61133 | W26: ﾏｷﾀﾇﾏﾂﾞﾋｶﾞｼﾆﾎﾝ | X26: ㈱マキタ沼津 東日本支店 | Y26: 362-0031 | Z26: 埼玉県 上尾市 東町2-8-4 | AA26: 048-779-2262
A27: 納入先NO： | B27: 納入先名及び 担当者名： | I27: 出荷希望日： | V27: 61134 | W27: ｸﾎﾞﾀｹﾝｷｼﾞｬﾊﾟﾝﾁﾊﾞｴｲｷﾞｮｳｼｮ | X27: ㈱クボタ建機ジャパン千葉営業所 | Y27: 283-0823 | Z27: 千葉県 東金市 山田 字新田1201-10 | AA27: 茨城菱農
A28: =A6 -> 61376 | C28: =C6 -> ㈲良栄社商会 | I28: =I6 -> 46196 | V28: 61135 | W28: ｵｵｻﾜｷｶｲ | X28: 大沢機械 | Y28: 191-0043 | Z28: 東京都 日野市 平山6-2-1 | AA28: 042-591-1588
B29: 住所： | I29: TEL | V29: 61136 | W29: ｼﾊﾞﾀ | X29: ㈱シバタ | Y29: 104-0032 | Z29: 東京都 中央区 八丁堀4-3-1 | AA29: 03-3552-0381
V30: 61140 | W30: ﾏｷﾀﾇﾏﾂﾞｷﾞｮｳﾑﾌﾞｼｮｳﾋﾝｶ | X30: ㈱マキタ沼津 業務部商品課 | Y30: 410-0022 | Z30: 静岡県 沼津市 大岡35 | AA30: 055-963-1112
V31: 61301 | W31: ｶﾅｴｻﾝｷﾞｮｳ | X31: カナエ産業㈱ | Y31: 194-0215 | Z31: 東京都 町田市 小山ケ丘3-7-10 | AA31: 042-798-7181
A32: 商品番号 | B32: 商品名 | E32: 数量 | F32: 値引後(仕切) | H32: 単価 | J32: 合計 | V32: 61302 | W32: ﾖｼｻﾞﾜｹﾞﾝﾄﾞｳｷ | X32: 吉澤原動機 | Y32: 114-0013 | Z32: 東京都 北区 東田端2-8-6 | AA32: 03-3810-2700
A33: =A11 -> 0353-0020 | B33: =B11 -> SP753B/M | E33: =E11 -> 1 | F33: =S11 -> 196800 | H33: =IFERROR(Q11," ") -> -26200 | J33: =IFERROR(H33*E33," ") -> -26200 | V33: 61303 | W33: ﾐﾔｼﾞｷｶｲ | X33: ㈱宮地機械（出荷停止） | Y33: 177-0033 | Z33: 東京都 練馬区 高野台4-11-28 | AA33: 03-3997-3155
A34: =A12 -> 0 | B34: =B12 | E34: =E12 -> 0 | F34: =S12 | H34: =IFERROR(Q12," ") | J34: =IFERROR(H34*E34," ") | V34: 61304 | W34: ﾊﾁｷﾞｮｳｼｮｳｼﾞ | X34: 八丈商事 | Y34: 100-1401 | Z34: 東京都 八丈島 八丈町 大賀郷1098-2 | AA34: 04996-2-2189
A35: =A13 -> 0 | E35: =E13 -> 0 | F35: =S13 | H35: =IFERROR(Q13," ") | J35: =IFERROR(H35*E35," ") | V35: 61305 | W35: ｲｼｲﾃﾞﾝｷｼｮｳﾃﾝ | X35: ㈱石井電気商店 | Y35: 294-0042 | Z35: 千葉県 館山市 上野原294-5 | AA35: 0470-22-0542
A36: =A14 -> 0 | B36: =B14 | E36: =E14 -> 0 | F36: =S14 | H36: =IFERROR(Q14," ") | J36: =IFERROR(H36*E36," ") | V36: 61306 | W36: ｲｺﾞｳﾉｳｷ | X36: ㈲井合農機店 | Y36: 273-0047 | Z36: 千葉県 船橋市 藤原5-22-31 | AA36: 047-439-5477
A37: =A15 -> 0 | B37: =B15 | E37: =E15 -> 0 | F37: =S15 -> 0 | H37: =IFERROR(-(S17)," ") -> 0 | J37: =IFERROR(H37*E37," ") -> 0 | V37: 61307 | W37: ｲｼｲﾃｯｺｳ | X37: 石井鉄工㈱ | Y37: 299-4218 | Z37: 千葉県 長生郡 白子町 関4549-2 | AA37: 0475-33-3528
A38: =A16 -> 0 | B38: =B16 | E38: =E16 -> 0 | F38: =Q18 -> 0 | H38: =IFERROR(-(S18)," ") -> 0 | J38: =IFERROR(H38*E38," ") -> 0 | V38: 61308 | W38: ｲﾉｳｴﾉｳｷｼｮｳｶｲ | X38: ㈲井上農機商会 | Y38: 299-4501 | Z38: 千葉県 いすみ市 岬町椎木1793 | AA38: 0470-87-2823
A39: 税抜小売 | B39: 掛率 | C39: 単価 | D39: OBIC照合 | F39: 伝票NO： | H39: 合計 | J39: =SUM(J33:J36) -> -26200 | V39: 61309 | W39: ｵｵﾏﾁﾉｳｷ | X39: ㈲大町農機 | Y39: 272-0801 | Z39: 千葉県 市川市 大町453 | AA39: 047-338-1210
A40: =L11 -> 328000 | B40: =T10 -> 0.6 | C40: =F33 -> 196800 | D40: =IFERROR((E33*C40)," ") -> 196800 | F40: 出荷確認 | H40: 受注可否検討 | J40: 連絡書作成 | V40: 61310 | W40: ｲｼﾞﾏｼｮｳﾃﾝ | X40: ㈲木嶋商店 | Y40: 289-1115 | Z40: 千葉県 八街市 八街ほ377 | AA40: 0434-44-2481
A41: =L12 | B41: =T10 -> 0.6 | C41: =F34 | D41: =IFERROR((E34*C41)," ") | F41: 承認 | H41: 承認 | J41: 作成者 | V41: 61311 | W41: ｻｻｿﾈﾉｳｷ | X41: 笹曽根農機 | Y41: 289-2135 | Z41: 千葉県 匝瑳市 高野898 | AA41: 0479-72-0781
A42: =L13 | B42: =T10 -> 0.6 | C42: =F35 | D42: =IFERROR((E35*C42)," ") | E42: OBIC計 | V42: 61312 | W42: ﾌｶｻﾜﾉｳｷｼｮｳｶｲ | X42: 深沢農機商会 | Y42: 196-0004 | Z42: 東京都 昭島市 緑町3-6-26 | AA42: 042-543-2759
A43: =L14 | B43: =T10 -> 0.6 | C43: =F36 | D43: =IFERROR((E36*C43)," ") | E43: =SUM(D40:D43) -> 196800 | V43: 61313 | W43: ｽｽﾞｷﾉｳｷ | X43: ㈲鈴木農機 | Y43: 283-0046 | Z43: 千葉県 東金市 上谷956 | AA43: 0475-52-4511
A44: 値引理由； | B44: =L7 -> 実演機対応値引 | C44: =N8/100 -> 0.08 | D44: 通常仕切； | E44: =IFERROR(VLOOKUP(A4,請求先!A:D,4,FALSE)," ") -> 0.68 | V44: 61314 | W44: ｽﾐﾉﾃｯｺｳｼｮ | X44: 住野鉄工所 | Y44: 289-1107 | Z44: 千葉県 八街市 八街は15 | AA44: 0434-44-1904
V45: 61315 | W45: ﾀｶﾊｼｷｶｲ | X45: ㈲高橋機械 | Y45: 271-0092 | Z45: 千葉県 松戸市 松戸1877-1 | AA45: 0473-62-0101
V46: 61317 | W46: ﾋｶﾘﾐﾅﾄﾔｼｮｳｶｲ | X46: ㈲光港屋商会 | Y46: 289-1727 | Z46: 千葉県 山武郡 横芝光町 宮川5460-1 | AA46: 0479-84-0611
V47: 61319 | W47: ﾐﾔｳﾁｷｺｳ | X47: 宮内機工 | Y47: 286-0211 | Z47: 千葉県 富里市 御料69-8 | AA47: 0476-93-5793
V48: 61320 | W48: ﾐﾅﾄﾔﾉｳｷｼｮｳｶｲ | X48: ㈲港屋農機商会 | Y48: 283-0005 | Z48: 千葉県 東金市 田間2132 | AA48: 0475-52-2246
V49: 61321 | W49: ﾔﾏｷﾉｳｷﾃﾝ | X49: ㈲山木農機店 | Y49: 294-0052 | Z49: 千葉県 館山市 亀ヶ原835 | AA49: 0470-36-2021
V50: 61322 | W50: ﾖｳｶｲﾁﾊﾞﾉｳｷ | X50: ㈲八日市場農機 | Y50: 289-2144 | Z50: 千葉県 匝瑳市 八日市場イ780-1 | AA50: 0479-72-1287
V51: 61323 | W51: ｵｵﾀｹｻﾝｷﾞｮｳ | X51: ㈱大竹産業 | Y51: 286-0041 | Z51: 千葉県 成田市 飯田町1-6 | AA51: 0476-22-2333
V52: 61324 | W52: ﾀｹﾂﾞｶｷｶｲﾃﾝ | X52: ㈱竹塚機械店 | Y52: 278-0033 | Z52: 千葉県 野田市 上花輪849 | AA52: 04-7125-1711
V53: 61325 | W53: ｺﾝﾄﾞｳﾉｳｺｳｼｬ | X53: ㈱近藤農工舎 | Y53: 290-0008 | Z53: 千葉県 市原市 古市場347 | AA53: 0436-41-3723
V54: 61328 | W54: ｲｼﾀﾞｷｶｲﾃﾝ | X54: ㈱石田機械店 | Y54: 270-0176 | Z54: 千葉県 流山市 加6丁目1545 | AA54: 04-7158-1257
V55: 61329 | W55: ｶﾏﾘ | X55: ㈱カマリ | Y55: 310-0836 | Z55: 茨城県 水戸市 元吉田町1267-4 | AA55: 029-304-3366
V56: 61330 | W56: ﾋﾗｶﾞｷｺｳ | X56: 平賀機工 | Y56: 309-1703 | Z56: 茨城県 笠間市 鯉淵6520-67 | AA56: 0296-77-0183
... V95: 61376 | W95: ﾘｮｳｴｲｼｬ | X95: ㈲良栄社商会 | Y95: 299-1151 | Z95: 千葉県 君津市 中野4-15-18 | AA95: 0439-52-0035
W96: ｺｼﾞﾝｷｬｸ | X96: 個人客
V97: 61400 | W97: ｺﾐﾔﾉｳｻﾝｷｼｮｳｶｲ | X97: ㈲古宮農蚕機商会 | Y97: 192-0051 | Z97: 東京都 八王子市 元本郷町1-5-5 | AA97: 042-625-2328
V98: 63102 | W98: ﾐﾂﾋﾞｼﾉｳｷﾊﾝﾊﾞｲｶﾝﾄｳｺｳｼﾝｴﾂ | X98: 三菱農機販売㈱ 関東甲信越支店 | Y98: 340-0203 | Z98: 埼玉県 久喜市 桜田2-133-4 | AA98: 0480-58-9521
V99: 63103 | W99: ｶﾝﾄｳｺｳｼﾝｸﾎﾞﾀｸﾎﾞﾀﾄﾁｷﾞｼﾞﾑｼｮ | X99: ㈱関東甲信クボタ 北関東事業所 （栃木） | Y99: 321-0905 | Z99: 栃木県 宇都宮市 平出工業団地28-2 | AA99: 0286-89-2341
V100: 63105 | W100: ﾐﾂﾋﾞｼﾉｳｷﾊﾝﾊﾞｲﾄﾁｷﾞｼﾃﾝ | X100: 三菱農機販売㈱ 栃木支店 | Y100: 329-1233 | Z100: 栃木県 塩谷郡 高根沢町 宝積寺 中2248-60 | AA100: 0286-75-7321
V101: 63112 | W101: ﾀｶﾀﾞﾗｸﾉｳｷ | X101: 高田酪農機㈱ | Y101: 321-3236 | Z101: 栃木県 宇都宮市 竹下町1101-11 | AA101: 028-667-2825
V102: 63301 | W102: ｺﾋﾞｷﾉｳｷｸﾞﾃﾝ | X102: 小比企農機具店 | Y102: 326-0845 | Z102: 栃木県 足利市 大前町207 | AA102: 0284-62-2065
V103: 63302 | W103: ﾇﾉｶﾜﾉｳｷｸﾞﾃﾝ | X103: 布川農機具店 | Y103: 329-4404 | Z103: 栃木県 栃木市 大平町富田1430 | AA103: 0282-43-2013
V104: 63303 | W104: ｽﾅｶﾉｳｷｸﾞﾃﾝ | X104: 砂川農機具店 | Y104: 326-0323 | Z104: 栃木県 足利市 瑞穂野町495 | AA104: 0284-71-9033
V105: 63304 | W105: ｽｽﾞｷﾔ | X105: ㈱鈴木屋 | Y105: 329-0205 | Z105: 栃木県 小山市 間々田1290 | AA105: 0285-45-0070
V106: 63305 | W106: ｶﾜﾀ | X106: ㈱川田 | Y106: 322-0002 | Z106: 栃木県 鹿沼市 千渡2315-66 | AA106: 0289-65-3366
V107: 63306 | W107: ｺﾀﾞｲﾗﾉｳｷｼｮｳｶｲ | X107: 小平農機商会 | Y107: 321-1261 | Z107: 栃木県 日光市 今市107-22 | AA107: 0288-21-0845
V108: 63307 | W108: ｻｲﾄｳﾉｳｷｼｮｳｶｲ | X108: ㈲斉藤農機商会 | Y108: 329-2161 | Z108: 栃木県 矢板市 扇町1-11-19 | AA108: 0287-43-0475
... V206: 64391 | W206: ｶﾝﾄｳｺｳｼﾝｸﾎﾞﾀｸﾞﾝﾏｼﾞﾑｼｮ | X206: ㈱関東甲信クボタ 群馬事務所 | Y206: 379-2154 | Z206: 群馬県 前橋市 天川大島町1364-1 | AA206: 027-261-6010
V207: 64398 | W207: ｶﾝﾄｳｹﾞﾝｷﾝｷｬｸ | X207: 関東現金客
V208: 64399 | W208: ｺｼﾞﾝｷｬｸ | X208: 個人客
V209: 64444 | W209: ﾐﾂﾋﾞｼﾉｳｷﾋｶﾞｼﾆﾎﾝﾌﾞﾋﾝｷｶﾝｾﾝﾀｰ | X209: 三菱農機㈱ 東日本部品基幹センター | Y209: 340-0203 | Z209: 埼玉県 久喜市 桜田2-133-4 | AA209: 0480-58-9515
V210: 64445 | W210: ﾐﾂﾋﾞｼﾉｳｷ | X210: 三菱ﾏﾋﾝﾄﾞﾗ農機㈱ 島根県 | Y210: 699-0101 | Z210: 島根県 松江市 東出雲町 揖屋667-1 | AA210: 0852-52-2111
V211: 65130 | W211: ｿｳﾌﾞｷｶｲ | X211: ㈱相武機械 | Y211: 215-0003 | Z211: 神奈川県 川崎市 麻生区 高石3-31-27 | AA211: 044-966-4161
V212: 65131 | W212: ﾓﾘﾁｮｳ | X212: 森長 | Y212: 254-0041 | Z212: 神奈川県 平塚市 浅間町5-27 | AA212: 0463-31-2195
V213: 65132 | W213: ｶﾝﾄｳｺｼﾝｸﾎﾞﾀｾｲｼﾝｼﾞｷﾞｮｳﾌﾞ | X213: ㈱関東甲信クボタ 静神事業部 | Y213: 411-0817 | Z213: 静岡県 三島市 八反畑 字鶴田100 | AA213: 055-972-0800
V214: 65137 | W214: ｴﾙﾀ | X214: ㈱エルタ | Y214: 190-1221 | Z214: 東京都 西多摩郡 瑞穂町 箱根ケ崎 東松原20-1 | AA214: 0425-56-0184
V215: 65323 | W215: ｵｵﾀｹﾉｳｷ | X215: 大竹農機㈱ | Y215: 289-1115 | Z215: 千葉県 八街市 八街ほ244 | AA215: 043-444-0225
V216: 65347 | W216: ｶﾓｼﾀﾞｼｮｳｶｲ | X216: 鴨志田商会 | Y216: 226-0000 | Z216: 神奈川県 横浜市 緑区 川和町1437 | AA216: 045-931-1038
V217: 65348 | W217: ｷｼﾀﾞﾉｳｷｼｮｳｶｲ | X217: ㈱岸田農機商会 | Y217: 259-1131 | Z217: 神奈川県 伊勢原市 伊勢原1-7-18 | AA217: 0463-95-0121
V218: 65350 | W218: ｻｶﾞﾐﾉｳｷ | X218: さがみ農機 | Y218: 258-0001 | Z218: 神奈川県 足柄上郡 松田町 寄5501 | AA218: 0465-89-2329
V219: 65351 | W219: ｽｽﾞﾉﾉｳｷ | X219: ㈲鈴野農機 | Y219: 252-0826 | Z219: 神奈川県 藤沢市 宮原1348 | AA219: 0466-48-1048
V220: 65352 | W220: ﾀﾅｶﾉｳｷｼｮｳｶｲ | X220: 田中農機商会 | Y220: 252-0807 | Z220: 神奈川県 藤沢市 下土棚444 | AA220: 0466-44-2005
... V244: 2133075 | W244: ﾂｸﾊﾞｼｻｸﾗﾉｳｷｾﾝﾀｰ | X244: JAつくば市 桜農機センター | Y244: 305-0027 | Z244: 茨城県 つくば市 東岡335 | AA244: 029-857-3116
V245: 2133107 | X245: JA常陸 みなみ農機センター | Y245: 319-1234 | Z245: 茨城県 日立市 大和田町1992 | AA245: 0294-53-2121
V246: 2133110 | W246: ﾏｼｰﾈｵﾐﾀﾏ | X246: JAマシーネ 小美玉 | Y246: 311-3412 | Z246: 茨城県 小美玉市 川戸1450-58 | AA246: 0299-58-5644
V247: 2133115 | W247: ﾐﾄﾉｳｷｮｳﾐﾄﾉｳｷｾﾝﾀｰ | X247: JA水戸農協 水戸農機センター | Y247: 311-4141 | Z247: 茨城県 水戸市 赤塚2-27 | AA247: 029-252-2076
V248: 2133147 | W248: ﾅﾒｶﾞﾀﾉｳｷﾈﾝﾘｮｳ | X248: JAなめがた農機燃料㈱ 南部農機センター | Y248: 311-3835 | Z248: 茨城県 行方市 島並857-16 | AA248: 0299-72-1651
V249: 2134054 | W249: ｸﾏｶﾞﾔｸﾏｶﾞﾔﾉｳｷｾﾝﾀｰ | X249: JAくまがや 熊谷農機センター | Y249: 360-0805 | Z249: 埼玉県 熊谷市 上奈良1079-1 | AA249: 048-523-9291
V250: 2134057 | W250: ｸﾏｶﾞﾔｺｳﾅﾝﾉｳｷｾﾝﾀｰ | X250: JAくまがや 江南農機センター | Y250: 360-0115 | Z250: 埼玉県 熊谷市 成沢490-1 | AA250: 048-536-1404
V251: 2134071 | W251: ｲﾙﾏﾉﾎｸﾌﾞﾉｳｷｾﾝﾀｰ | X251: JAいるま野 北部農機センター | Y251: 350-0212 | Z251: 埼玉県 坂戸市 石井1880 | AA251: 049-289-2172
V252: 2134072 | W252: ｻｲﾀﾏｻｼｵｳｷﾞｼﾃﾝ | X252: JAさいたま 指扇支店 | Y252: 331-0071 | Z252: 埼玉県 さいたま市 西区 高木337-3 | AA252: 048-623-5011
V253: 2134091 | W253: ｲﾙﾏﾉﾄｺﾛｻﾞﾜﾉｳｷｾﾝﾀｰ | X253: JAいるま野 所沢農機センター | Y253: 359-0001 | Z253: 埼玉県 所沢市 下富627-10 | AA253: 042-942-3467
V254: 2134092 | X254: JAちちぶ農協秩父自動車センター | Y254: 368-0056 | Z254: 埼玉県 秩父市 寺尾3218-1 | AA254: 0494-25-2555
V255: 2134107 | W255: ｻｲﾀﾏﾁｭｳｵｳﾋｶﾞｼﾏﾂﾔﾏﾉｳｷｾﾝﾀｰ | X255: JA埼玉中央 東松山農機センター | Y255: 355-0073 | Z255: 埼玉県 東松山市 上野本1405-1 | AA255: 0493-24-3159
V256: 2135169 | W256: ｷﾐﾂ | X256: JAきみつ 平川農機整備工場 | Y256: 299-0205 | Z256: 千葉県 袖ヶ浦市 上泉366 | AA256: 0438-75-4007
V257: 2135181 | W257: ﾁｮｳｾｲﾉｳｷｮｳ | X257: JA長生農協 睦沢農機センター | Y257: 299-4403 | Z257: 千葉県 長生郡 睦沢町 上市場914 | AA257: 0475-44-1236
V258: 2135187 | W258: ｷﾐﾂ | X258: JAきみつ 天羽農機整備工場 | Y258: 299-1618 | Z258: 千葉県 富津市 花輪150 | AA258: 0439-80-7650
...

Sheet 三菱+値引
A1: （様式：EL-97A03） | Y1: 納入先コード | Z1: 納入先カナ名 | AA1: 納入先正式名 | AB1: 郵便番号1 | AC1: 住所1 | AD1: 電話番号1-1
A2: 引き合い内容連絡書 | J2: 株式会社オーレック | Y2: 61102 | Z2: ﾆﾎﾝｸﾘﾝﾄﾝ | AA2: 日本クリントン㈱ | AB2: 121-0836 | AC2: 東京都 足立区 入谷5-7-8 | AD2: 03-3854-8221
A3: 得意先NO： | B3: 得意先名 及び 担当者名： | I3: 受注日： | Y3: 61103 | Z3: ﾄｳｺｳｻﾝｷﾞｮｳ | AA3: 東興産業㈱ | AB3: 350-0821 | AC3: 埼玉県 川越市 福田239 | AD3: 0492-23-1217
A4: 64445005 | C4: =IFERROR(VLOOKUP(A4,請求先!A:D,2,FALSE)," ") -> 三菱マヒンドラ農機㈱（千葉県） | I4: 46080 | L4: 製品コード検索 | Y4: 61105 | Z4: ｲﾄｳｻﾝｷﾞｮｳｷｶｲ | AA4: 伊藤産業機械㈱ | AB4: 290-0034 | AC4: 千葉県 市原市 島野1978 | AD4: 0436-22-1743
A5: 納入先NO： | B5: 納入先名及び 担当者名： | G5: 生産日 | H5: 在庫分 | I5: 出荷希望日： | L5: SP853/Y | Q5: → | R5: =IFERROR(VLOOKUP(L5,商品コード!B:F,5,FALSE)," ") | Y5: 61106 | Z5: ｴﾑｴｽｹｰﾉｳｷﾞｮｳｷｶｲﾁﾊﾞｼﾞｷﾞｮｳｼｮ | AA5: MSK東急機械㈱ 千葉事業所 | AB5: 290-0012 | AC5: 千葉県 市原市 藤井3-310 | AD5: 0436-41-1069
A6: 2135542 | C6: =IFERROR(VLOOKUP(A6,出荷先!A:F,3,FALSE)," ") -> JAちばみどり 農機センター | I6: 46084 | Y6: 61107 | Z6: ｻｻｷｼｮｳｶｲ | AA6: ㈱佐々木商会 | AB6: 294-0037 | AC6: 千葉県 館山市 長須賀123 | AD6: 0470-22-1166
B7: 住所： | C7: 〒 | D7: =IFERROR(VLOOKUP(A6,出荷先!A:F,4,FALSE)," ") -> 289-2503 | L7: 実演機対応値引 | Q7: =IF(Q6="","",VLOOKUP(Q6,#REF!,2,FALSE)) | S7: M-TOS 報告 | Y7: 61108 | Z7: ｽｷﾞｷﾃｯｺｳ | AA7: 杉木鉄工㈱ | AB7: 297-0029 | AC7: 千葉県 茂原市 高師1536 | AD7: 0475-22-4587
B8: =IFERROR(VLOOKUP(A6,出荷先!A:F,5,FALSE)," ") -> 千葉県 旭市 江ヶ崎661 | I8: =IFERROR(VLOOKUP(A6,出荷先!A:F,6,FALSE)," ") -> 0479-63-7009 | L8: =IF(L7="","",VLOOKUP(L7,商品コード!A:B,2,FALSE)) -> 外掛 | M8: =IF(I8="","",VLOOKUP(I8,商品コード!#REF!,2,FALSE)) -> #REF! | N8: 2 | P8: % | S8: 三菱マヒンドラ | U8: 三菱販社 | Y8: 61109 | Z8: ﾀｶﾉｻﾝｷﾞｮｳ | AA8: 高野産業㈱ | AB8: 292-0054 | AC8: 千葉県 木更津市 長須賀924-1 | AD8: 0438-22-6251
Y9: 61110 | Z9: ｶﾝﾄｳｺｼﾝｸﾎﾞﾀﾁﾊﾞｼﾞｷﾞｮｳﾌﾞ | AA9: ㈱関東甲信クボタ 南関東事業所 | AB9: 260-0808 | AC9: 千葉県 千葉市 中央区 星久喜町176-4 | AD9: 043-261-3131
A10: 商品番号 | B10: 商品名 | E10: 数量 | F10: 単位 | G10: 単価 | I10: オーダーＮｏ 等 | L10: 税別小売 | N10: 通常 | P10: =IF(A4="","",VLOOKUP(A4,請求先!A:D,4,FALSE)) -> 0.637 | Q10: 値引 | R10: =$N$8/100 -> 0.02 | S10: 最終 | T10: =IF(L8="外掛",P10-R10,IF(L8="内掛",ROUNDDOWN(P10*(100-100*R10)%,5))) -> 0.617 | U10: =IF(L8="外掛",(65-N8)%,IF(L8="内掛",(65*(1-N8/100))%)) -> 0.63 | Y10: 61111 | Z10: ﾅｶﾔｼｮｳｶｲ | AA10: ㈱中屋商会 | AB10: 289-2146 | AC10: 千葉県 匝瑳市 八日市場ホ452 | AD10: 0479-72-1161
A11: 0353-0260 | B11: =IFERROR(VLOOKUP(A11,商品コード!A:C,2,FALSE)," ") -> SP853A/Y | E11: 1 | G11: =O13 -> 0 | I11: A44208 | K11: → | L11: =IF(A11="","",VLOOKUP(A11,商品コード!A:C,3,FALSE)) -> 308000 | N11: =IFERROR(IF(A4=61121,ROUNDDOWN((L11*P10),-1),IF(A4=61123,ROUNDDOWN((L11*P10),-1),IF(A4=64445001,ROUNDDOWN((L11*P10),-1),IF(A4=64445002,ROUNDDOWN((L11*P10),-1),ROUNDDOWN(L11*P10,-1)))))," ") -> 196190 | Q11: =IFERROR(S11-N11," ") -> -6070 | S11: =IFERROR(ROUNDDOWN(U11*0.98,-1)," ") -> 190120 | U11: =IFERROR(IF(L8="外掛",ROUNDDOWN(L11*((65-N8)/100),-2),IF(L8="内掛",ROUNDDOWN(ROUNDDOWN(L11*0.65,-2)*(1-N8/100),-2)))," ") -> 194000 | Y11: 61112 | Z11: ﾅｶﾑﾗｻﾝｷﾞｮｳ | AA11: ㈱中村産業 | AB11: 283-0811 | AC11: 千葉県 東金市 台方246 | AD11: 0475-52-2615
G12: =O14 -> 0 | K12: → | L12: =IF(A12="","",VLOOKUP(A12,商品コード!A:C,3,FALSE)) | N12: =IFERROR(IF(A4=61121,ROUNDDOWN((L12*P10),-1),IF(A4=61123,ROUNDDOWN((L12*P10),-1),IF(A4=64445001,ROUNDDOWN((L12*P10),-1),IF(A4=64445002,ROUNDDOWN((L12*P10),-1),ROUNDDOWN(L12*P10,-2)))))," ") | Q12: =IFERROR(S12-N12," ") | S12: =IFERROR(ROUNDDOWN(U12*0.98,-1)," ") | U12: =IFERROR(IF(L8="外掛",ROUNDDOWN(L12*((65-N8)/100),-2),IF(L8="内掛",ROUNDDOWN(ROUNDDOWN(L12*0.65,-2)*(1-N8/100),-2)))," ") | Y12: 61113 | Z12: ﾌﾀﾊﾞｺｳｷ | AA12: ㈲双葉工機 | AB12: 270-2222 | AC12: 千葉県 松戸市 高塚新田340-11 | AD12: 0473-92-7256
B13: =IFERROR(VLOOKUP(A13,商品コード!A:C,2,FALSE)," ") | G13: =O15 -> 0 | K13: → | L13: =IF(A13="","",VLOOKUP(A13,商品コード!A:C,3,FALSE)) | N13: =IFERROR(IF(A4=61121,ROUNDDOWN((L13*P10),-1),IF(A4=61123,ROUNDDOWN((L13*P10),-1),IF(A4=64445001,ROUNDDOWN((L13*P10),-1),IF(A4=64445002,ROUNDDOWN((L13*P10),-1),ROUNDDOWN(L13*P10,-2)))))," ") | Q13: =IFERROR(S13-N13," ") | S13: =IFERROR(ROUNDDOWN(U13*0.98,-1)," ") | U13: =IFERROR(IF(L8="外掛",ROUNDDOWN(L13*((65-N8)/100),-2),IF(L8="内掛",ROUNDDOWN(ROUNDDOWN(L13*0.65,-2)*(1-N8/100),-2)))," ") | Y13: 61114 | Z13: ﾓﾊﾞﾗﾌｺｸｼｬ | AA13: ㈱茂原富国社 | AB13: 297-0029 | AC13: 千葉県 茂原市 高師1671 | AD13: 0475-25-0325
B14: =IFERROR(VLOOKUP(A14,商品コード!A:C,2,FALSE)," ") | G14: =O16 -> 0 | K14: → | L14: =IF(A14="","",VLOOKUP(A14,商品コード!A:C,3,FALSE)) | N14: =IFERROR(IF(A4=61121,ROUNDDOWN((L14*P10),-1),IF(A4=61123,ROUNDDOWN((L14*P10),-1),IF(A4=64445001,ROUNDDOWN((L14*P10),-1),IF(A4=64445002,ROUNDDOWN((L14*P10),-1),ROUNDDOWN(L14*P10,-2)))))," ") | Q14: =IFERROR(S14-N14," ") | S14: =IFERROR(ROUNDDOWN(U14*0.98,-1)," ") | U14: =IFERROR(IF(L8="外掛",ROUNDDOWN(L14*((65-N8)/100),-2),IF(L8="内掛",ROUNDDOWN(ROUNDDOWN(L14*0.65,-2)*(1-N8/100),-2)))," ") | Y14: 61115 | Z14: ｲﾊﾞﾗｷﾘｮｳﾉｳ | AA14: 茨城菱農㈱ | AB14: 300-4201 | AC14: 茨城県 つくば市 寺具1332-9 | AD14: 0298-69-1045
B15: =IFERROR(VLOOKUP(A15,商品コード!A:C,2,FALSE)," ") | G15: =O17 -> 0 | Y15: 61116 | Z15: ｶﾝﾄｳｺｳｼﾝｸﾎﾞﾀｲﾊﾞﾗｷｼﾞﾑｼｮ | AA15: ㈱関東甲信クボタ 茨城事務所 | AB15: 300-2402 | AC15: 茨城県 つくばみらい市 坂野新田12-42 | AD15: 0297-52-1111
B16: =IFERROR(VLOOKUP(A16,商品コード!A:C,2,FALSE)," ") | G16: =O18 -> 0 | Y16: 61117 | Z16: ｵｵｶﾜｷｶｲ | AA16: 大川機械 | AB16: 300-0024 | AC16: 茨城県 土浦市 田村町988-2 | AD16: 0298-28-0755
A17: 倉庫（ | B17: 033 | C17: ） | D17: 運賃 | E17: 元払い | F17: 伝票NO： | Y17: 61118 | Z17: ﾐﾂﾋﾞｼﾉｳｷﾊﾝﾊﾞｲｲﾊﾞﾗｷｼﾃﾝ | AA17: 三菱農機販売㈱ 茨城支店 | AB17: 311-0133 | AC17: 茨城県 那珂市 鴻巣1135-1 | AD17: 0293-53-2140
E18: 立 元 | F18: 出荷確認 | H18: 受注可否検討 | J18: 連絡書作成 | Y18: 61120 | Z18: ｼﾏｻﾉｳｷ | AA18: ㈱嶋田農機 | AB18: 300-3544 | AC18: 茨城県 結城郡 八千代町 若996 | AD18: 0296-48-1025
E19: 着払い | F19: 承認 | H19: 承認 | J19: 作成者 | Y19: 61121 | Z19: ｸﾎﾞﾀｲﾊﾞﾗｷｹﾝｴｲｷﾞｮｳﾀﾝﾄｳ | AA19: ㈱クボタ 茨城県営業担当 | AB19: 338-0832 | AC19: 埼玉県 さいたま市 桜区 西堀5-2-36 | AD19: 048-862-1125
C20: 便名： | D20: 福山便 西濃便 JPロジ | Y20: 61122 | Z20: ﾅﾘﾀｶﾄｳﾉｳｷ | AA20: 成田加藤農機（有） | AB20: 286-0021 | AC20: 千葉県 成田市 土屋1375-1 | AD20: 0476-22-0579
Y21: 61123 | Z21: ｸﾎﾞﾀﾄﾁｷﾞｹﾝｴｲｷﾞｮｳﾀﾝﾄｳ | AA21: ㈱クボタ 栃木県営業担当 | AB21: 338-0832 | AC21: 埼玉県 さいたま市 桜区 西堀5-2-36 | AD21: 048-862-1125
Y22: 61124 | Z22: ﾈﾓﾄｼｮｳｶｲ | AA22: ㈲根本商会 | AB22: 286-0801 | AC22: 千葉県 成田市 竜台468 | AD22: 0476-37-1211
A23: （様式：EL-97A03） | D23: 【 値引 】 | Y23: 61125 | Z23: ﾏﾙﾃﾝｻﾝｷﾞｮｳｷｶｲ | AA23: マルテン産業機械㈱ | AB23: 293-0001 | AC23: 千葉県 富津市 大堀1434 | AD23: 0439-87-0052
A24: 引き合い内容連絡書 | J24: 株式会社オーレック | Y24: 61126 | Z24: ﾐﾂﾋﾞｼﾉｳｷﾊﾝﾊﾞｲﾁﾊﾞｼﾃﾝ | AA24: 三菱農機販売㈱ 千葉支店 | AB24: 300-1312 | AC24: 茨城県 稲敷郡 河内町 長竿字西の町1596-2 | AD24: 0297-63-4633
A25: 得意先NO： | B25: 得意先名 及び 担当者名： | I25: 受注日： | Y25: 61127 | Z25: ｸﾎﾞﾀｸﾞﾝﾏｹﾝｴｲｷﾞｮｳﾀﾝﾄｳ | AA25: ㈱クボタ 群馬県営業担当 | AB25: 338-0832 | AC25: 埼玉県 さいたま市 桜区 西堀5-2-36 | AD25: 048-862-1125
A26: =A4 -> 64445005 | C26: =C4 -> 三菱マヒンドラ農機㈱（千葉県） | I26: =I4 -> 46080 | Y26: 61133 | Z26: ﾏｷﾀﾇﾏﾂﾞﾋｶﾞｼﾆﾎﾝ | AA26: ㈱マキタ沼津 東日本支店 | AB26: 362-0031 | AC26: 埼玉県 上尾市 東町2-8-4 | AD26: 048-779-2262
A27: 納入先NO： | B27: 納入先名及び 担当者名： | I27: 出荷希望日： | Y27: 61134 | Z27: ｸﾎﾞﾀｹﾝｷｼﾞｬﾊﾟﾝﾁﾊﾞｴｲｷﾞｮｳｼｮ | AA27: ㈱クボタ建機ジャパン千葉営業所 | AB27: 283-0823 | AC27: 千葉県 東金市 山田 字新田1201-10 | AD27: 茨城菱農
A28: =A6 -> 2135542 | C28: =C6 -> JAちばみどり 農機センター | I28: =I6 -> 46084 | Y28: 61135 | Z28: ｵｵｻﾜｷｶｲ | AA28: 大沢機械 | AB28: 191-0043 | AC28: 東京都 日野市 平山6-2-1 | AD28: 042-591-1588
B29: 住所： | I29: TEL | Y29: 61136 | Z29: ｼﾊﾞﾀ | AA29: ㈱シバタ | AB29: 104-0032 | AC29: 東京都 中央区 八丁堀4-3-1 | AD29: 03-3552-0381
Y30: 61140 | Z30: ﾏｷﾀﾇﾏﾂﾞｷﾞｮｳﾑﾌﾞｼｮｳﾋﾝｶ | AA30: ㈱マキタ沼津 業務部商品課 | AB30: 410-0022 | AC30: 静岡県 沼津市 大岡35 | AD30: 055-963-1112
Y31: 61301 | Z31: ｶﾅｴｻﾝｷﾞｮｳ | AA31: カナエ産業㈱ | AB31: 194-0215 | AC31: 東京都 町田市 小山ケ丘3-7-10 | AD31: 042-798-7181
A32: 商品番号 | B32: 商品名 | E32: 数量 | F32: 値引後(仕切) | H32: 単価 | J32: 合計 | Y32: 61302 | Z32: ﾖｼｻﾞﾜｹﾞﾝﾄﾞｳｷ | AA32: 吉澤原動機 | AB32: 114-0013 | AC32: 東京都 北区 東田端2-8-6 | AD32: 03-3810-2700
A33: =A11 -> 0353-0260 | B33: =B11 -> SP853A/Y | E33: =E11 -> 1 | F33: =S11 -> 190120 | H33: =IFERROR(Q11," ") -> -6070 | J33: =IFERROR(H33*E33," ") -> -6070 | Y33: 61303 | Z33: ﾐﾔｼﾞｷｶｲ | AA33: ㈱宮地機械（出荷停止） | AB33: 177-0033 | AC33: 東京都 練馬区 高野台4-11-28 | AD33: 03-3997-3155
A34: =A12 -> 0 | B34: =B12 -> 0 | E34: =E12 -> 0 | F34: =S12 | H34: =IFERROR(Q12," ") | J34: =IFERROR(H34*E34," ") | Y34: 61304 | Z34: ﾊﾁｷﾞｮｳｼｮｳｼﾞ | AA34: 八丈商事 | AB34: 100-1401 | AC34: 東京都 八丈島 八丈町 大賀郷1098-2 | AD34: 04996-2-2189
A35: =A13 -> 0 | B35: =B13 | E35: =E13 -> 0 | F35: =S13 | H35: =IFERROR(Q13," ") | J35: =IFERROR(H35*E35," ") | Y35: 61305 | Z35: ｲｼｲﾃﾞﾝｷｼｮｳﾃﾝ | AA35: ㈱石井電気商店 | AB35: 294-0042 | AC35: 千葉県 館山市 上野原294-5 | AD35: 0470-22-0542
A36: =A14 -> 0 | B36: =B14 | E36: =E14 -> 0 | F36: =S14 | H36: =IFERROR(Q14," ") | J36: =IFERROR(H36*E36," ") | Y36: 61306 | Z36: ｲｺﾞｳﾉｳｷ | AA36: ㈲井合農機店 | AB36: 273-0047 | AC36: 千葉県 船橋市 藤原5-22-31 | AD36: 047-439-5477
A37: =A15 -> 0 | B37: =B15 | E37: =E15 -> 0 | F37: =S15 -> 0 | H37: =IFERROR(-(S17)," ") -> 0 | J37: =IFERROR(H37*E37," ") -> 0 | Y37: 61307 | Z37: ｲｼｲﾃｯｺｳ | AA37: 石井鉄工㈱ | AB37: 299-4218 | AC37: 千葉県 長生郡 白子町 関4549-2 | AD37: 0475-33-3528
A38: =A16 -> 0 | B38: =B16 | E38: =E16 -> 0 | F38: =Q18 -> 0 | H38: =IFERROR(-(S18)," ") -> 0 | J38: =IFERROR(H38*E38," ") -> 0 | Y38: 61308 | Z38: ｲﾉｳｴﾉｳｷｼｮｳｶｲ | AA38: ㈲井上農機商会 | AB38: 299-4501 | AC38: 千葉県 いすみ市 岬町椎木1793 | AD38: 0470-87-2823
A39: 定価 | B39: 掛率 | C39: 単価 | D39: OBIC照合 | E39: 三菱マ/販 | F39: 伝票NO： | H39: 合計 | J39: =SUM(J33:J36) -> -6070 | Y39: 61309 | Z39: ｵｵﾏﾁﾉｳｷ | AA39: ㈲大町農機 | AB39: 272-0801 | AC39: 千葉県 市川市 大町453 | AD39: 047-338-1210
A40: =L11 -> 308000 | B40: =T10 -> 0.617 | C40: =F33 -> 190120 | D40: =IFERROR((E33*C40)," ") -> 190120 | E40: =S11 -> 190120 | F40: 出荷確認 | H40: 受注可否検討 | J40: 連絡書作成 | Y40: 61310 | Z40: ｲｼﾞﾏｼｮｳﾃﾝ | AA40: ㈲木嶋商店 | AB40: 289-1115 | AC40: 千葉県 八街市 八街ほ377 | AD40: 0434-44-2481
C41: =F34 | D41: =IFERROR((E34*C41)," ") | E41: =U11 -> 194000 | F41: 承認 | H41: 承認 | J41: 作成者 | Y41: 61311 | Z41: ｻｻｿﾈﾉｳｷ | AA41: 笹曽根農機 | AB41: 289-2135 | AC41: 千葉県 匝瑳市 高野898 | AD41: 0479-72-0781
C42: =F35 | D42: =IFERROR((E35*C42)," ") | E42: OBIC計 | Y42: 61312 | Z42: ﾌｶｻﾜﾉｳｷｼｮｳｶｲ | AA42: 深沢農機商会 | AB42: 196-0004 | AC42: 東京都 昭島市 緑町3-6-26 | AD42: 042-543-2759
D43: =IFERROR((E36*C43)," ") -> 0 | E43: =SUM(D40:D43) -> 190120 | Y43: 61313 | Z43: ｽｽﾞｷﾉｳｷ | AA43: ㈲鈴木農機 | AB43: 283-0046 | AC43: 千葉県 東金市 上谷956 | AD43: 0475-52-4511
A44: 値引理由； | B44: =L7 -> 実演機対応値引 | C44: =N8 -> 2 | D44: % | Y44: 61314 | Z44: ｽﾐﾉﾃｯｺｳｼｮ | AA44: 住野鉄工所 | AB44: 289-1107 | AC44: 千葉県 八街市 八街は15 | AD44: 0434-44-1904
Y45: 61315 | Z45: ﾀｶﾊｼｷｶｲ | AA45: ㈲高橋機械 | AB45: 271-0092 | AC45: 千葉県 松戸市 松戸1877-1 | AD45: 0473-62-0101
Y46: 61317 | Z46: ﾋｶﾘﾐﾅﾄﾔｼｮｳｶｲ | AA46: ㈲光港屋商会 | AB46: 289-1727 | AC46: 千葉県 山武郡 横芝光町 宮川5460-1 | AD46: 0479-84-0611
Y47: 61319 | Z47: ﾐﾔｳﾁｷｺｳ | AA47: 宮内機工 | AB47: 286-0211 | AC47: 千葉県 富里市 御料69-8 | AD47: 0476-93-5793
Y48: 61320 | Z48: ﾐﾅﾄﾔﾉｳｷｼｮｳｶｲ | AA48: ㈲港屋農機商会 | AB48: 283-0005 | AC48: 千葉県 東金市 田間2132 | AD48: 0475-52-2246
Y49: 61321 | Z49: ﾔﾏｷﾉｳｷﾃﾝ | AA49: ㈲山木農機店 | AB49: 294-0052 | AC49: 千葉県 館山市 亀ヶ原835 | AD49: 0470-36-2021
Y50: 61322 | Z50: ﾖｳｶｲﾁﾊﾞﾉｳｷ | AA50: ㈲八日市場農機 | AB50: 289-2144 | AC50: 千葉県 匝瑳市 八日市場イ780-1 | AD50: 0479-72-1287
Y51: 61323 | Z51: ｵｵﾀｹｻﾝｷﾞｮｳ | AA51: ㈱大竹産業 | AB51: 286-0041 | AC51: 千葉県 成田市 飯田町1-6 | AD51: 0476-22-2333
Y52: 61324 | Z52: ﾀｹﾂﾞｶｷｶｲﾃﾝ | AA52: ㈱竹塚機械店 | AB52: 278-0033 | AC52: 千葉県 野田市 上花輪849 | AD52: 04-7125-1711
Y53: 61325 | Z53: ｺﾝﾄﾞｳﾉｳｺｳｼｬ | AA53: ㈱近藤農工舎 | AB53: 290-0008 | AC53: 千葉県 市原市 古市場347 | AD53: 0436-41-3723
Y54: 61328 | Z54: ｲｼﾀﾞｷｶｲﾃﾝ | AA54: ㈱石田機械店 | AB54: 270-0176 | AC54: 千葉県 流山市 加6丁目1545 | AD54: 04-7158-1257
Y55: 61329 | Z55: ｶﾏﾘ | AA55: ㈱カマリ | AB55: 310-0836 | AC55: 茨城県 水戸市 元吉田町1267-4 | AD55: 029-304-3366
Y56: 61330 | Z56: ﾋﾗｶﾞｷｺｳ | AA56: 平賀機工 | AB56: 309-1703 | AC56: 茨城県 笠間市 鯉淵6520-67 | AD56: 0296-77-0183
... Y95: 61376 | Z95: ﾘｮｳｴｲｼｬ | AA95: ㈲良栄社商会 | AB95: 299-1151 | AC95: 千葉県 君津市 中野4-15-18 | AD95: 0439-52-0035
Z96: ｺｼﾞﾝｷｬｸ | AA96: 個人客
Y97: 61400 | Z97: ｺﾐﾔﾉｳｻﾝｷｼｮｳｶｲ | AA97: ㈲古宮農蚕機商会 | AB97: 192-0051 | AC97: 東京都 八王子市 元本郷町1-5-5 | AD97: 042-625-2328
Y98: 63102 | Z98: ﾐﾂﾋﾞｼﾉｳｷﾊﾝﾊﾞｲｶﾝﾄｳｺｳｼﾝｴﾂ | AA98: 三菱農機販売㈱ 関東甲信越支店 | AB98: 340-0203 | AC98: 埼玉県 久喜市 桜田2-133-4 | AD98: 0480-58-9521
Y99: 63103 | Z99: ｶﾝﾄｳｺｳｼﾝｸﾎﾞﾀｸﾎﾞﾀﾄﾁｷﾞｼﾞﾑｼｮ | AA99: ㈱関東甲信クボタ 北関東事業所 （栃木） | AB99: 321-0905 | AC99: 栃木県 宇都宮市 平出工業団地28-2 | AD99: 0286-89-2341
Y100: 63105 | Z100: ﾐﾂﾋﾞｼﾉｳｷﾊﾝﾊﾞｲﾄﾁｷﾞｼﾃﾝ | AA100: 三菱農機販売㈱ 栃木支店 | AB100: 329-1233 | AC100: 栃木県 塩谷郡 高根沢町 宝積寺 中2248-60 | AD100: 0286-75-7321
Y101: 63112 | Z101: ﾀｶﾀﾞﾗｸﾉｳｷ | AA101: 高田酪農機㈱ | AB101: 321-3236 | AC101: 栃木県 宇都宮市 竹下町1101-11 | AD101: 028-667-2825
Y102: 63301 | Z102: ｺﾋﾞｷﾉｳｷｸﾞﾃﾝ | AA102: 小比企農機具店 | AB102: 326-0845 | AC102: 栃木県 足利市 大前町207 | AD102: 0284-62-2065
Y103: 63302 | Z103: ﾇﾉｶﾜﾉｳｷｸﾞﾃﾝ | AA103: 布川農機具店 | AB103: 329-4404 | AC103: 栃木県 栃木市 大平町富田1430 | AD103: 0282-43-2013
Y104: 63303 | Z104: ｽﾅｶﾉｳｷｸﾞﾃﾝ | AA104: 砂川農機具店 | AB104: 326-0323 | AC104: 栃木県 足利市 瑞穂野町495 | AD104: 0284-71-9033
Y105: 63304 | Z105: ｽｽﾞｷﾔ | AA105: ㈱鈴木屋 | AB105: 329-0205 | AC105: 栃木県 小山市 間々田1290 | AD105: 0285-45-0070
Y106: 63305 | Z106: ｶﾜﾀ | AA106: ㈱川田 | AB106: 322-0002 | AC106: 栃木県 鹿沼市 千渡2315-66 | AD106: 0289-65-3366
Y107: 63306 | Z107: ｺﾀﾞｲﾗﾉｳｷｼｮｳｶｲ | AA107: 小平農機商会 | AB107: 321-1261 | AC107: 栃木県 日光市 今市107-22 | AD107: 0288-21-0845
Y108: 63307 | Z108: ｻｲﾄｳﾉｳｷｼｮｳｶｲ | AA108: ㈲斉藤農機商会 | AB108: 329-2161 | AC108: 栃木県 矢板市 扇町1-11-19 | AD108: 0287-43-0475
... Y206: 64391 | Z206: ｶﾝﾄｳｺｳｼﾝｸﾎﾞﾀｸﾞﾝﾏｼﾞﾑｼｮ | AA206: ㈱関東甲信クボタ 群馬事務所 | AB206: 379-2154 | AC206: 群馬県 前橋市 天川大島町1364-1 | AD206: 027-261-6010
Y207: 64398 | Z207: ｶﾝﾄｳｹﾞﾝｷﾝｷｬｸ | AA207: 関東現金客
Y208: 64399 | Z208: ｺｼﾞﾝｷｬｸ | AA208: 個人客
Y209: 64444 | Z209: ﾐﾂﾋﾞｼﾉｳｷﾋｶﾞｼﾆﾎﾝﾌﾞﾋﾝｷｶﾝｾﾝﾀｰ | AA209: 三菱農機㈱ 東日本部品基幹センター | AB209: 340-0203 | AC209: 埼玉県 久喜市 桜田2-133-4 | AD209: 0480-58-9515
Y210: 64445 | Z210: ﾐﾂﾋﾞｼﾉｳｷ | AA210: 三菱ﾏﾋﾝﾄﾞﾗ農機㈱ 島根県 | AB210: 699-0101 | AC210: 島根県 松江市 東出雲町 揖屋667-1 | AD210: 0852-52-2111
Y211: 65130 | Z211: ｿｳﾌﾞｷｶｲ | AA211: ㈱相武機械 | AB211: 215-0003 | AC211: 神奈川県 川崎市 麻生区 高石3-31-27 | AD211: 044-966-4161
Y212: 65131 | Z212: ﾓﾘﾁｮｳ | AA212: 森長 | AB212: 254-0041 | AC212: 神奈川県 平塚市 浅間町5-27 | AD212: 0463-31-2195
Y213: 65132 | Z213: ｶﾝﾄｳｺｼﾝｸﾎﾞﾀｾｲｼﾝｼﾞｷﾞｮｳﾌﾞ | AA213: ㈱関東甲信クボタ 静神事業部 | AB213: 411-0817 | AC213: 静岡県 三島市 八反畑 字鶴田100 | AD213: 055-972-0800
Y214: 65137 | Z214: ｴﾙﾀ | AA214: ㈱エルタ | AB214: 190-1221 | AC214: 東京都 西多摩郡 瑞穂町 箱根ケ崎 東松原20-1 | AD214: 0425-56-0184
Y215: 65323 | Z215: ｵｵﾀｹﾉｳｷ | AA215: 大竹農機㈱ | AB215: 289-1115 | AC215: 千葉県 八街市 八街ほ244 | AD215: 043-444-0225
Y216: 65347 | Z216: ｶﾓｼﾀﾞｼｮｳｶｲ | AA216: 鴨志田商会 | AB216: 226-0000 | AC216: 神奈川県 横浜市 緑区 川和町1437 | AD216: 045-931-1038
Y217: 65348 | Z217: ｷｼﾀﾞﾉｳｷｼｮｳｶｲ | AA217: ㈱岸田農機商会 | AB217: 259-1131 | AC217: 神奈川県 伊勢原市 伊勢原1-7-18 | AD217: 0463-95-0121
Y218: 65350 | Z218: ｻｶﾞﾐﾉｳｷ | AA218: さがみ農機 | AB218: 258-0001 | AC218: 神奈川県 足柄上郡 松田町 寄5501 | AD218: 0465-89-2329
Y219: 65351 | Z219: ｽｽﾞﾉﾉｳｷ | AA219: ㈲鈴野農機 | AB219: 252-0826 | AC219: 神奈川県 藤沢市 宮原1348 | AD219: 0466-48-1048
Y220: 65352 | Z220: ﾀﾅｶﾉｳｷｼｮｳｶｲ | AA220: 田中農機商会 | AB220: 252-0807 | AC220: 神奈川県 藤沢市 下土棚444 | AD220: 0466-44-2005
... Y244: 2133075 | Z244: ﾂｸﾊﾞｼｻｸﾗﾉｳｷｾﾝﾀｰ | AA244: JAつくば市 桜農機センター | AB244: 305-0027 | AC244: 茨城県 つくば市 東岡335 | AD244: 029-857-3116
Y245: 2133107 | AA245: JA常陸 みなみ農機センター | AB245: 319-1234 | AC245: 茨城県 日立市 大和田町1992 | AD245: 0294-53-2121
Y246: 2133110 | Z246: ﾏｼｰﾈｵﾐﾀﾏ | AA246: JAマシーネ 小美玉 | AB246: 311-3412 | AC246: 茨城県 小美玉市 川戸1450-58 | AD246: 0299-58-5644
Y247: 2133115 | Z247: ﾐﾄﾉｳｷｮｳﾐﾄﾉｳｷｾﾝﾀｰ | AA247: JA水戸農協 水戸農機センター | AB247: 311-4141 | AC247: 茨城県 水戸市 赤塚2-27 | AD247: 029-252-2076
Y248: 2133147 | Z248: ﾅﾒｶﾞﾀﾉｳｷﾈﾝﾘｮｳ | AA248: JAなめがた農機燃料㈱ 南部農機センター | AB248: 311-3835 | AC248: 茨城県 行方市 島並857-16 | AD248: 0299-72-1651
Y249: 2134054 | Z249: ｸﾏｶﾞﾔｸﾏｶﾞﾔﾉｳｷｾﾝﾀｰ | AA249: JAくまがや 熊谷農機センター | AB249: 360-0805 | AC249: 埼玉県 熊谷市 上奈良1079-1 | AD249: 048-523-9291
Y250: 2134057 | Z250: ｸﾏｶﾞﾔｺｳﾅﾝﾉｳｷｾﾝﾀｰ | AA250: JAくまがや 江南農機センター | AB250: 360-0115 | AC250: 埼玉県 熊谷市 成沢490-1 | AD250: 048-536-1404
Y251: 2134071 | Z251: ｲﾙﾏﾉﾎｸﾌﾞﾉｳｷｾﾝﾀｰ | AA251: JAいるま野 北部農機センター | AB251: 350-0212 | AC251: 埼玉県 坂戸市 石井1880 | AD251: 049-289-2172
Y252: 2134072 | Z252: ｻｲﾀﾏｻｼｵｳｷﾞｼﾃﾝ | AA252: JAさいたま 指扇支店 | AB252: 331-0071 | AC252: 埼玉県 さいたま市 西区 高木337-3 | AD252: 048-623-5011
Y253: 2134091 | Z253: ｲﾙﾏﾉﾄｺﾛｻﾞﾜﾉｳｷｾﾝﾀｰ | AA253: JAいるま野 所沢農機センター | AB253: 359-0001 | AC253: 埼玉県 所沢市 下富627-10 | AD253: 042-942-3467
Y254: 2134092 | AA254: JAちちぶ農協秩父自動車センター | AB254: 368-0056 | AC254: 埼玉県 秩父市 寺尾3218-1 | AD254: 0494-25-2555
Y255: 2134107 | Z255: ｻｲﾀﾏﾁｭｳｵｳﾋｶﾞｼﾏﾂﾔﾏﾉｳｷｾﾝﾀｰ | AA255: JA埼玉中央 東松山農機センター | AB255: 355-0073 | AC255: 埼玉県 東松山市 上野本1405-1 | AD255: 0493-24-3159
Y256: 2135169 | Z256: ｷﾐﾂ | AA256: JAきみつ 平川農機整備工場 | AB256: 299-0205 | AC256: 千葉県 袖ヶ浦市 上泉366 | AD256: 0438-75-4007
Y257: 2135181 | Z257: ﾁｮｳｾｲﾉｳｷｮｳ | AA257: JA長生農協 睦沢農機センター | AB257: 299-4403 | AC257: 千葉県 長生郡 睦沢町 上市場914 | AD257: 0475-44-1236
Y258: 2135187 | Z258: ｷﾐﾂ | AA258: JAきみつ 天羽農機整備工場 | AB258: 299-1618 | AC258: 千葉県 富津市 花輪150 | AD258: 0439-80-7650
...

Sheet 三菱
A1: （様式：EL-97A03）
A2: 引き合い内容連絡書 | J2: 株式会社オーレック
A3: 得意先NO： | B3: 得意先名 及び 担当者名： | I3: 受注日：
A4: 64445005 | C4: =IFERROR(VLOOKUP(A4,請求先!A:D,2,FALSE)," ") -> 三菱マヒンドラ農機㈱（千葉県） | I4: 45996
A5: 納入先NO： | B5: 納入先名及び 担当者名： | G5: 生産日 | H5: 46007 | I5: 出荷希望日：
A6: 69012116 | C6: =IFERROR(VLOOKUP(A6,出荷先!A:F,3,FALSE)," ") -> 平和機械㈱ | I6: 46009
B7: 住所： | C7: 〒 | D7: =IFERROR(VLOOKUP(A6,出荷先!A:F,4,FALSE)," ") -> 299-3266 | I7: TEL
B8: =IFERROR(VLOOKUP(A6,出荷先!A:F,5,FALSE)," ") -> 千葉県 大網白里市 北横川115-4 | I8: =IFERROR(VLOOKUP(A6,出荷先!A:F,6,FALSE)," ") -> 0475-72-0345
A10: 商品番号 | B10: 商品名 | E10: 数量 | F10: 単位 | G10: 単価 | I10: オーダーＮｏ 等
A11: 0353-0260 | B11: =IFERROR(VLOOKUP(A11,商品コード!A:C,2,FALSE)," ") -> SP853A/Y | E11: 1
B12: =IFERROR(VLOOKUP(A12,商品コード!A:C,2,FALSE)," ")
B13: =IFERROR(VLOOKUP(A13,商品コード!A:C,2,FALSE)," ")
B14: =IFERROR(VLOOKUP(A14,商品コード!A:C,2,FALSE)," ")
B15: =IFERROR(VLOOKUP(A15,商品コード!A:C,2,FALSE)," ")
B16: =IFERROR(VLOOKUP(A16,商品コード!A:C,2,FALSE)," ")
A17: 倉庫（ | B17: 011 | C17: ） | D17: 運賃 | E17: 元払い | F17: 伝票NO：
E18: 立 元 | F18: 出荷確認 | H18: 受注可否検討 | J18: 連絡書作成
E19: 着払い | F19: 承認 | H19: 承認 | J19: 作成者
C20: 便名： | D20: 福山便 西濃便 JPロジ
A23: 製品コード検索
A24: HR665/M | F24: → | G24: =IFERROR(VLOOKUP(A24,商品コード!B:F,5,FALSE)," ") -> 0285-0520
A26: M-TOS 報告 | F26: 0.637 | I26: 0.65
A27: 製品型式 | C27: 税別小売 | F27: 三菱マヒンドラ | I27: 三菱販社
A28: =B11 -> SP853A/Y | C28: =IF(A11="","",VLOOKUP(A11,商品コード!$A:$C,3,FALSE)) -> 308000 | F28: =IFERROR(ROUNDDOWN((C28*0.637),-1)," ") -> 196190 | I28: =IFERROR(ROUNDDOWN((C28*0.65),-2)," ") -> 200200
A29: =B12 | C29: =IF(A12="","",VLOOKUP(A12,商品コード!$A:$C,3,FALSE)) | F29: =IFERROR(ROUNDDOWN((C29*0.637),-1)," ") | I29: =IFERROR(ROUNDDOWN((C29*0.65),-2)," ")
A30: =B13 | C30: =IF(A13="","",VLOOKUP(A13,商品コード!$A:$C,3,FALSE)) | F30: =IFERROR(ROUNDDOWN((C30*0.637),-1)," ") | I30: =IFERROR(ROUNDDOWN((C30*0.65),-2)," ")
A31: =B14 | C31: =IF(A14="","",VLOOKUP(A14,商品コード!$A:$C,3,FALSE)) | F31: =IFERROR(ROUNDDOWN((C31*0.637),-1)," ") | I31: =IFERROR(ROUNDDOWN((C31*0.65),-2)," ")
A32: =B15 | C32: =IF(A15="","",VLOOKUP(A15,商品コード!$A:$C,3,FALSE)) | F32: =IFERROR(ROUNDDOWN((C32*0.637),-1)," ") | I32: =IFERROR(ROUNDDOWN((C32*0.65),-2)," ")
A33: =B16 | C33: =IF(A16="","",VLOOKUP(A16,商品コード!$A:$C,3,FALSE)) | F33: =IFERROR(ROUNDDOWN((C33*0.637),-1)," ") | I33: =IFERROR(ROUNDDOWN((C33*0.65),-2)," ")

Sheet 商組不需要期
A1: （様式：EL-97A03） | AA1: 納入先コード | AB1: 納入先カナ名 | AC1: 納入先正式名 | AD1: 郵便番号1 | AE1: 住所1 | AF1: 電話番号1-1
A2: 引き合い内容連絡書 | J2: 株式会社オーレック | AA2: 61102 | AB2: ﾆﾎﾝｸﾘﾝﾄﾝ | AC2: 日本クリントン㈱ | AD2: 121-0836 | AE2: 東京都 足立区 入谷5-7-8 | AF2: 03-3854-8221
A3: 得意先NO： | B3: 得意先名 及び 担当者名： | I3: 受注日： | AA3: 61103 | AB3: ﾄｳｺｳｻﾝｷﾞｮｳ | AC3: 東興産業㈱ | AD3: 350-0821 | AE3: 埼玉県 川越市 福田239 | AF3: 0492-23-1217
C4: =IFERROR(VLOOKUP(A4,請求先!A:D,2,FALSE)," ") | I4: 45957 | L4: 製品コード検索 | AA4: 61105 | AB4: ｲﾄｳｻﾝｷﾞｮｳｷｶｲ | AC4: 伊藤産業機械㈱ | AD4: 290-0034 | AE4: 千葉県 市原市 島野1978 | AF4: 0436-22-1743
A5: 納入先NO： | B5: 納入先名及び 担当者名： | G5: 生産日 | H5: 2月 | I5: 出荷希望日： | L5: SP853/Y | Q5: → | R5: =IFERROR(VLOOKUP(L5,商品コード!B:F,5,FALSE)," ") | AA5: 61106 | AB5: ｴﾑｴｽｹｰﾉｳｷﾞｮｳｷｶｲﾁﾊﾞｼﾞｷﾞｮｳｼｮ | AC5: MSK東急機械㈱ 千葉事業所 | AD5: 290-0012 | AE5: 千葉県 市原市 藤井3-310 | AF5: 0436-41-1069
A6: 61344 | C6: =IFERROR(VLOOKUP(A6,出荷先!A:F,3,FALSE)," ") -> ㈲土子機械店 | I6: 45986 | AA6: 61107 | AB6: ｻｻｷｼｮｳｶｲ | AC6: ㈱佐々木商会 | AD6: 294-0037 | AE6: 千葉県 館山市 長須賀123 | AF6: 0470-22-1166
B7: 住所： | C7: 〒 | D7: =IFERROR(VLOOKUP(A6,出荷先!A:F,4,FALSE)," ") -> 287-0037 | L7: 不需要期値引 | Q7: =IF(Q6="","",VLOOKUP(Q6,#REF!,2,FALSE)) | AA7: 61108 | AB7: ｽｷﾞｷﾃｯｺｳ | AC7: 杉木鉄工㈱ | AD7: 297-0029 | AE7: 千葉県 茂原市 高師1536 | AF7: 0475-22-4587
B8: =IFERROR(VLOOKUP(A6,出荷先!A:F,5,FALSE)," ") -> 千葉県 香取市 与倉73-4 | I8: =IFERROR(VLOOKUP(A6,出荷先!A:F,6,FALSE)," ") -> 0478-58-1134 | L8: =IF(L7="","",VLOOKUP(L7,商品コード!A:B,2,FALSE)) -> 内掛 | M8: =IF(I8="","",VLOOKUP(I8,商品コード!#REF!,2,FALSE)) -> #REF! | N8: 5 | P8: % | AA8: 61109 | AB8: ﾀｶﾉｻﾝｷﾞｮｳ | AC8: 高野産業㈱ | AD8: 292-0054 | AE8: 千葉県 木更津市 長須賀924-1 | AF8: 0438-22-6251
AA9: 61110 | AB9: ｶﾝﾄｳｺｼﾝｸﾎﾞﾀﾁﾊﾞｼﾞｷﾞｮｳﾌﾞ | AC9: ㈱関東甲信クボタ 南関東事業所 | AD9: 260-0808 | AE9: 千葉県 千葉市 中央区 星久喜町176-4 | AF9: 043-261-3131
A10: 商品番号 | B10: 商品名 | E10: 数量 | F10: 単位 | G10: 単価 | I10: オーダーＮｏ 等 | L10: 税別小売 | N10: 通常 | P10: =IF(A4="","",VLOOKUP(A4,請求先!A:D,4,FALSE)) | Q10: 値引 | R10: =$N$8/100 -> 0.05 | S10: 最終 | T10: =IF(L8="外掛",P10-R10,IF(L8="内掛",ROUNDDOWN(P10*(100-100*R10)%,5))) -> #VALUE! | AA10: 61111 | AB10: ﾅｶﾔｼｮｳｶｲ | AC10: ㈱中屋商会 | AD10: 289-2146 | AE10: 千葉県 匝瑳市 八日市場ホ452 | AF10: 0479-72-1161
A11: 0353-0260 | B11: =IFERROR(VLOOKUP(A11,商品コード!A:C,2,FALSE)," ") -> SP853A/Y | E11: 1 | G11: =O13 -> 0 | K11: → | L11: =IF(A11="","",VLOOKUP(A11,商品コード!A:C,3,FALSE)) -> 308000 | N11: =IFERROR(IF(A4=61121,ROUNDDOWN((L11*P10),-1),IF(A4=61123,ROUNDDOWN((L11*P10),-1),IF(A4=64445001,ROUNDDOWN((L11*P10),-1),IF(A4=64445002,ROUNDDOWN((L11*P10),-1),ROUNDDOWN(L11*P10,-2)))))," ") | Q11: =IFERROR(S11-N11," ") | S11: =IFERROR(IF(OR(A4=61121,A4=61123,A4=64445001,A4=64445002),IF(L8="内掛",ROUNDDOWN(N11*(1-R10),-1),ROUNDDOWN(L11*T10,-1)),IF(L8="内掛",ROUNDDOWN(N11*(1-R10),-2),ROUNDDOWN(L11*T10,-2)))," ") | AA11: 61112 | AB11: ﾅｶﾑﾗｻﾝｷﾞｮｳ | AC11: ㈱中村産業 | AD11: 283-0811 | AE11: 千葉県 東金市 台方246 | AF11: 0475-52-2615
B12: =IFERROR(VLOOKUP(A12,商品コード!A:C,2,FALSE)," ") | G12: =O14 -> 0 | K12: → | L12: =IF(A12="","",VLOOKUP(A12,商品コード!A:C,3,FALSE)) | N12: =IFERROR(IF(A4=61121,ROUNDDOWN((L12*P10),-1),IF(A4=61123,ROUNDDOWN((L12*P10),-1),IF(A4=64445001,ROUNDDOWN((L12*P10),-1),IF(A4=64445002,ROUNDDOWN((L12*P10),-1),ROUNDDOWN(L12*P10,-2)))))," ") | Q12: =IFERROR(S12-N12," ") | S12: =IFERROR(IF(OR(A4=61121,A4=61123,A4=64445001,A4=64445002),IF(L8="内掛",ROUNDDOWN(N12*(1-R10),-1),ROUNDDOWN(L12*T10,-1)),IF(L8="内掛",ROUNDDOWN(N12*(1-R10),-2),ROUNDDOWN(L12*T10,-2)))," ") | AA12: 61113 | AB12: ﾌﾀﾊﾞｺｳｷ | AC12: ㈲双葉工機 | AD12: 270-2222 | AE12: 千葉県 松戸市 高塚新田340-11 | AF12: 0473-92-7256
B13: =IFERROR(VLOOKUP(A13,商品コード!A:C,2,FALSE)," ") | G13: =O15 -> 0 | K13: → | L13: =IF(A13="","",VLOOKUP(A13,商品コード!A:C,3,FALSE)) | N13: =IFERROR(IF(A4=61121,ROUNDDOWN((L13*P10),-1),IF(A4=61123,ROUNDDOWN((L13*P10),-1),IF(A4=64445001,ROUNDDOWN((L13*P10),-1),IF(A4=64445002,ROUNDDOWN((L13*P10),-1),ROUNDDOWN(L13*P10,-2)))))," ") | Q13: =IFERROR(S13-N13," ") | S13: =IFERROR(IF(OR(A4=61121,A4=61123,A4=64445001,A4=64445002),IF(L8="内掛",ROUNDDOWN(N13*(1-R10),-1),ROUNDDOWN(L13*T10,-1)),IF(L8="内掛",ROUNDDOWN(N13*(1-R10),-2),ROUNDDOWN(L13*T10,-2)))," ") | AA13: 61114 | AB13: ﾓﾊﾞﾗﾌｺｸｼｬ | AC13: ㈱茂原富国社 | AD13: 297-0029 | AE13: 千葉県 茂原市 高師1671 | AF13: 0475-25-0325
B14: =IFERROR(VLOOKUP(A14,商品コード!A:C,2,FALSE)," ") | G14: =O16 -> 0 | K14: → | L14: =IF(A14="","",VLOOKUP(A14,商品コード!A:C,3,FALSE)) | N14: =IFERROR(IF(A4=61121,ROUNDDOWN((L14*P10),-1),IF(A4=61123,ROUNDDOWN((L14*P10),-1),IF(A4=64445001,ROUNDDOWN((L14*P10),-1),IF(A4=64445002,ROUNDDOWN((L14*P10),-1),ROUNDDOWN(L14*P10,-2)))))," ") | Q14: =IFERROR(S14-N14," ") | S14: =IFERROR(IF(OR(A4=61121,A4=61123,A4=64445001,A4=64445002),IF(L8="内掛",ROUNDDOWN(N14*(1-R10),-1),ROUNDDOWN(L14*T10,-1)),IF(L8="内掛",ROUNDDOWN(N14*(1-R10),-2),ROUNDDOWN(L14*T10,-2)))," ") | AA14: 61115 | AB14: ｲﾊﾞﾗｷﾘｮｳﾉｳ | AC14: 茨城菱農㈱ | AD14: 300-4201 | AE14: 茨城県 つくば市 寺具1332-9 | AF14: 0298-69-1045
B15: =IFERROR(VLOOKUP(A15,商品コード!A:C,2,FALSE)," ") | G15: =O17 -> 0 | AA15: 61116 | AB15: ｶﾝﾄｳｺｳｼﾝｸﾎﾞﾀｲﾊﾞﾗｷｼﾞﾑｼｮ | AC15: ㈱関東甲信クボタ 茨城事務所 | AD15: 300-2402 | AE15: 茨城県 つくばみらい市 坂野新田12-42 | AF15: 0297-52-1111
B16: =IFERROR(VLOOKUP(A16,商品コード!A:C,2,FALSE)," ") | G16: =O18 -> 0 | AA16: 61117 | AB16: ｵｵｶﾜｷｶｲ | AC16: 大川機械 | AD16: 300-0024 | AE16: 茨城県 土浦市 田村町988-2 | AF16: 0298-28-0755
A17: 倉庫（ | B17: 033 | C17: ） | D17: 運賃 | E17: 元払い | F17: 伝票NO： | AA17: 61118 | AB17: ﾐﾂﾋﾞｼﾉｳｷﾊﾝﾊﾞｲｲﾊﾞﾗｷｼﾃﾝ | AC17: 三菱農機販売㈱ 茨城支店 | AD17: 311-0133 | AE17: 茨城県 那珂市 鴻巣1135-1 | AF17: 0293-53-2140
E18: 立 元 | F18: 出荷確認 | H18: 受注可否検討 | J18: 連絡書作成 | AA18: 61120 | AB18: ｼﾏｻﾉｳｷ | AC18: ㈱嶋田農機 | AD18: 300-3544 | AE18: 茨城県 結城郡 八千代町 若996 | AF18: 0296-48-1025
E19: 着払い | F19: 承認 | H19: 承認 | J19: 作成者 | AA19: 61121 | AB19: ｸﾎﾞﾀｲﾊﾞﾗｷｹﾝｴｲｷﾞｮｳﾀﾝﾄｳ | AC19: ㈱クボタ 茨城県営業担当 | AD19: 338-0832 | AE19: 埼玉県 さいたま市 桜区 西堀5-2-36 | AF19: 048-862-1125
C20: 便名： | D20: 福山便 西濃便 JPロジ | AA20: 61122 | AB20: ﾅﾘﾀｶﾄｳﾉｳｷ | AC20: 成田加藤農機（有） | AD20: 286-0021 | AE20: 千葉県 成田市 土屋1375-1 | AF20: 0476-22-0579
AA21: 61123 | AB21: ｸﾎﾞﾀﾄﾁｷﾞｹﾝｴｲｷﾞｮｳﾀﾝﾄｳ | AC21: ㈱クボタ 栃木県営業担当 | AD21: 338-0832 | AE21: 埼玉県 さいたま市 桜区 西堀5-2-36 | AF21: 048-862-1125
AA22: 61124 | AB22: ﾈﾓﾄｼｮｳｶｲ | AC22: ㈲根本商会 | AD22: 286-0801 | AE22: 千葉県 成田市 竜台468 | AF22: 0476-37-1211
A23: （様式：EL-97A03） | D23: 【 値引 】 | AA23: 61125 | AB23: ﾏﾙﾃﾝｻﾝｷﾞｮｳｷｶｲ | AC23: マルテン産業機械㈱ | AD23: 293-0001 | AE23: 千葉県 富津市 大堀1434 | AF23: 0439-87-0052
A24: 引き合い内容連絡書 | J24: 株式会社オーレック | AA24: 61126 | AB24: ﾐﾂﾋﾞｼﾉｳｷﾊﾝﾊﾞｲﾁﾊﾞｼﾃﾝ | AC24: 三菱農機販売㈱ 千葉支店 | AD24: 300-1312 | AE24: 茨城県 稲敷郡 河内町 長竿字西の町1596-2 | AF24: 0297-63-4633
A25: 得意先NO： | B25: 得意先名 及び 担当者名： | I25: 受注日： | AA25: 61127 | AB25: ｸﾎﾞﾀｸﾞﾝﾏｹﾝｴｲｷﾞｮｳﾀﾝﾄｳ | AC25: ㈱クボタ 群馬県営業担当 | AD25: 338-0832 | AE25: 埼玉県 さいたま市 桜区 西堀5-2-36 | AF25: 048-862-1125
A26: =A4 -> 0 | C26: =C4 | I26: =I4 -> 45957 | AA26: 61133 | AB26: ﾏｷﾀﾇﾏﾂﾞﾋｶﾞｼﾆﾎﾝ | AC26: ㈱マキタ沼津 東日本支店 | AD26: 362-0031 | AE26: 埼玉県 上尾市 東町2-8-4 | AF26: 048-779-2262
A27: 納入先NO： | B27: 納入先名及び 担当者名： | I27: 出荷希望日： | AA27: 61134 | AB27: ｸﾎﾞﾀｹﾝｷｼﾞｬﾊﾟﾝﾁﾊﾞｴｲｷﾞｮｳｼｮ | AC27: ㈱クボタ建機ジャパン千葉営業所 | AD27: 283-0823 | AE27: 千葉県 東金市 山田 字新田1201-10 | AF27: 茨城菱農
A28: =A6 -> 61344 | C28: =C6 -> ㈲土子機械店 | I28: =I6 -> 45986 | AA28: 61135 | AB28: ｵｵｻﾜｷｶｲ | AC28: 大沢機械 | AD28: 191-0043 | AE28: 東京都 日野市 平山6-2-1 | AF28: 042-591-1588
B29: 住所： | I29: TEL | AA29: 61136 | AB29: ｼﾊﾞﾀ | AC29: ㈱シバタ | AD29: 104-0032 | AE29: 東京都 中央区 八丁堀4-3-1 | AF29: 03-3552-0381
AA30: 61140 | AB30: ﾏｷﾀﾇﾏﾂﾞｷﾞｮｳﾑﾌﾞｼｮｳﾋﾝｶ | AC30: ㈱マキタ沼津 業務部商品課 | AD30: 410-0022 | AE30: 静岡県 沼津市 大岡35 | AF30: 055-963-1112
AA31: 61301 | AB31: ｶﾅｴｻﾝｷﾞｮｳ | AC31: カナエ産業㈱ | AD31: 194-0215 | AE31: 東京都 町田市 小山ケ丘3-7-10 | AF31: 042-798-7181
A32: 商品番号 | B32: 商品名 | E32: 数量 | F32: 値引後(仕切) | H32: 単価 | J32: 合計 | AA32: 61302 | AB32: ﾖｼｻﾞﾜｹﾞﾝﾄﾞｳｷ | AC32: 吉澤原動機 | AD32: 114-0013 | AE32: 東京都 北区 東田端2-8-6 | AF32: 03-3810-2700
A33: =A11 -> 0353-0260 | B33: =B11 -> SP853A/Y | E33: =E11 -> 1 | F33: =S11 | H33: =IFERROR(Q11," ") | J33: =IFERROR(H33*E33," ") | AA33: 61303 | AB33: ﾐﾔｼﾞｷｶｲ | AC33: ㈱宮地機械（出荷停止） | AD33: 177-0033 | AE33: 東京都 練馬区 高野台4-11-28 | AF33: 03-3997-3155
A34: =A12 -> 0 | B34: =B12 | E34: =E12 -> 0 | F34: =S12 | H34: =IFERROR(Q12," ") | J34: =IFERROR(H34*E34," ") | AA34: 61304 | AB34: ﾊﾁｷﾞｮｳｼｮｳｼﾞ | AC34: 八丈商事 | AD34: 100-1401 | AE34: 東京都 八丈島 八丈町 大賀郷1098-2 | AF34: 04996-2-2189
A35: =A13 -> 0 | B35: =B13 | E35: =E13 -> 0 | F35: =S13 | H35: =IFERROR(Q13," ") | J35: =IFERROR(H35*E35," ") | AA35: 61305 | AB35: ｲｼｲﾃﾞﾝｷｼｮｳﾃﾝ | AC35: ㈱石井電気商店 | AD35: 294-0042 | AE35: 千葉県 館山市 上野原294-5 | AF35: 0470-22-0542
A36: =A14 -> 0 | B36: =B14 | E36: =E14 -> 0 | F36: =S14 | H36: =IFERROR(Q14," ") | J36: =IFERROR(H36*E36," ") | AA36: 61306 | AB36: ｲｺﾞｳﾉｳｷ | AC36: ㈲井合農機店 | AD36: 273-0047 | AE36: 千葉県 船橋市 藤原5-22-31 | AF36: 047-439-5477
A37: =A15 -> 0 | B37: =B15 | E37: =E15 -> 0 | F37: =S15 -> 0 | H37: =IFERROR(-(S17)," ") -> 0 | J37: =IFERROR(H37*E37," ") -> 0 | AA37: 61307 | AB37: ｲｼｲﾃｯｺｳ | AC37: 石井鉄工㈱ | AD37: 299-4218 | AE37: 千葉県 長生郡 白子町 関4549-2 | AF37: 0475-33-3528
A38: =A16 -> 0 | B38: =B16 | E38: =E16 -> 0 | F38: =Q18 -> 0 | H38: =IFERROR(-(S18)," ") -> 0 | J38: =IFERROR(H38*E38," ") -> 0 | AA38: 61308 | AB38: ｲﾉｳｴﾉｳｷｼｮｳｶｲ | AC38: ㈲井上農機商会 | AD38: 299-4501 | AE38: 千葉県 いすみ市 岬町椎木1793 | AF38: 0470-87-2823
A39: 税抜小売 | B39: 掛率 | C39: 単価 | D39: OBIC照合 | F39: 伝票NO： | H39: 合計 | J39: =SUM(J33:J36) -> 0 | AA39: 61309 | AB39: ｵｵﾏﾁﾉｳｷ | AC39: ㈲大町農機 | AD39: 272-0801 | AE39: 千葉県 市川市 大町453 | AF39: 047-338-1210
A40: =L11 -> 308000 | B40: =T10 -> #VALUE! | C40: =F33 | D40: =IFERROR((E33*C40)," ") | F40: 出荷確認 | H40: 受注可否検討 | J40: 連絡書作成 | AA40: 61310 | AB40: ｲｼﾞﾏｼｮｳﾃﾝ | AC40: ㈲木嶋商店 | AD40: 289-1115 | AE40: 千葉県 八街市 八街ほ377 | AF40: 0434-44-2481
A41: =L12 | B41: =T10 -> #VALUE! | C41: =F34 | D41: =IFERROR((E34*C41)," ") | F41: 承認 | H41: 承認 | J41: 作成者 | AA41: 61311 | AB41: ｻｻｿﾈﾉｳｷ | AC41: 笹曽根農機 | AD41: 289-2135 | AE41: 千葉県 匝瑳市 高野898 | AF41: 0479-72-0781
A42: =L13 | B42: =T10 -> #VALUE! | C42: =F35 | D42: =IFERROR((E35*C42)," ") | E42: OBIC計 | AA42: 61312 | AB42: ﾌｶｻﾜﾉｳｷｼｮｳｶｲ | AC42: 深沢農機商会 | AD42: 196-0004 | AE42: 東京都 昭島市 緑町3-6-26 | AF42: 042-543-2759
A43: =L14 | B43: =T10 -> #VALUE! | C43: =F36 | D43: =IFERROR((E36*C43)," ") | E43: =SUM(D40:D43) -> 0 | AA43: 61313 | AB43: ｽｽﾞｷﾉｳｷ | AC43: ㈲鈴木農機 | AD43: 283-0046 | AE43: 千葉県 東金市 上谷956 | AF43: 0475-52-4511
A44: 値引理由； | B44: =L7 -> 不需要期値引 | C44: =N8/100 -> 0.05 | D44: 通常仕切； | E44: =IFERROR(VLOOKUP(A4,請求先!A:D,4,FALSE)," ") | AA44: 61314 | AB44: ｽﾐﾉﾃｯｺｳｼｮ | AC44: 住野鉄工所 | AD44: 289-1107 | AE44: 千葉県 八街市 八街は15 | AF44: 0434-44-1904
AA45: 61315 | AB45: ﾀｶﾊｼｷｶｲ | AC45: ㈲高橋機械 | AD45: 271-0092 | AE45: 千葉県 松戸市 松戸1877-1 | AF45: 0473-62-0101
AA46: 61317 | AB46: ﾋｶﾘﾐﾅﾄﾔｼｮｳｶｲ | AC46: ㈲光港屋商会 | AD46: 289-1727 | AE46: 千葉県 山武郡 横芝光町 宮川5460-1 | AF46: 0479-84-0611
AA47: 61319 | AB47: ﾐﾔｳﾁｷｺｳ | AC47: 宮内機工 | AD47: 286-0211 | AE47: 千葉県 富里市 御料69-8 | AF47: 0476-93-5793
AA48: 61320 | AB48: ﾐﾅﾄﾔﾉｳｷｼｮｳｶｲ | AC48: ㈲港屋農機商会 | AD48: 283-0005 | AE48: 千葉県 東金市 田間2132 | AF48: 0475-52-2246
AA49: 61321 | AB49: ﾔﾏｷﾉｳｷﾃﾝ | AC49: ㈲山木農機店 | AD49: 294-0052 | AE49: 千葉県 館山市 亀ヶ原835 | AF49: 0470-36-2021
AA50: 61322 | AB50: ﾖｳｶｲﾁﾊﾞﾉｳｷ | AC50: ㈲八日市場農機 | AD50: 289-2144 | AE50: 千葉県 匝瑳市 八日市場イ780-1 | AF50: 0479-72-1287
AA51: 61323 | AB51: ｵｵﾀｹｻﾝｷﾞｮｳ | AC51: ㈱大竹産業 | AD51: 286-0041 | AE51: 千葉県 成田市 飯田町1-6 | AF51: 0476-22-2333
AA52: 61324 | AB52: ﾀｹﾂﾞｶｷｶｲﾃﾝ | AC52: ㈱竹塚機械店 | AD52: 278-0033 | AE52: 千葉県 野田市 上花輪849 | AF52: 04-7125-1711
AA53: 61325 | AB53: ｺﾝﾄﾞｳﾉｳｺｳｼｬ | AC53: ㈱近藤農工舎 | AD53: 290-0008 | AE53: 千葉県 市原市 古市場347 | AF53: 0436-41-3723
AA54: 61328 | AB54: ｲｼﾀﾞｷｶｲﾃﾝ | AC54: ㈱石田機械店 | AD54: 270-0176 | AE54: 千葉県 流山市 加6丁目1545 | AF54: 04-7158-1257
AA55: 61329 | AB55: ｶﾏﾘ | AC55: ㈱カマリ | AD55: 310-0836 | AE55: 茨城県 水戸市 元吉田町1267-4 | AF55: 029-304-3366
AA56: 61330 | AB56: ﾋﾗｶﾞｷｺｳ | AC56: 平賀機工 | AD56: 309-1703 | AE56: 茨城県 笠間市 鯉淵6520-67 | AF56: 0296-77-0183
... AA95: 61376 | AB95: ﾘｮｳｴｲｼｬ | AC95: ㈲良栄社商会 | AD95: 299-1151 | AE95: 千葉県 君津市 中野4-15-18 | AF95: 0439-52-0035
AB96: ｺｼﾞﾝｷｬｸ | AC96: 個人客
AA97: 61400 | AB97: ｺﾐﾔﾉｳｻﾝｷｼｮｳｶｲ | AC97: ㈲古宮農蚕機商会 | AD97: 192-0051 | AE97: 東京都 八王子市 元本郷町1-5-5 | AF97: 042-625-2328
AA98: 63102 | AB98: ﾐﾂﾋﾞｼﾉｳｷﾊﾝﾊﾞｲｶﾝﾄｳｺｳｼﾝｴﾂ | AC98: 三菱農機販売㈱ 関東甲信越支店 | AD98: 340-0203 | AE98: 埼玉県 久喜市 桜田2-133-4 | AF98: 0480-58-9521
AA99: 63103 | AB99: ｶﾝﾄｳｺｳｼﾝｸﾎﾞﾀｸﾎﾞﾀﾄﾁｷﾞｼﾞﾑｼｮ | AC99: ㈱関東甲信クボタ 北関東事業所 （栃木） | AD99: 321-0905 | AE99: 栃木県 宇都宮市 平出工業団地28-2 | AF99: 0286-89-2341
AA100: 63105 | AB100: ﾐﾂﾋﾞｼﾉｳｷﾊﾝﾊﾞｲﾄﾁｷﾞｼﾃﾝ | AC100: 三菱農機販売㈱ 栃木支店 | AD100: 329-1233 | AE100: 栃木県 塩谷郡 高根沢町 宝積寺 中2248-60 | AF100: 0286-75-7321
AA101: 63112 | AB101: ﾀｶﾀﾞﾗｸﾉｳｷ | AC101: 高田酪農機㈱ | AD101: 321-3236 | AE101: 栃木県 宇都宮市 竹下町1101-11 | AF101: 028-667-2825
AA102: 63301 | AB102: ｺﾋﾞｷﾉｳｷｸﾞﾃﾝ | AC102: 小比企農機具店 | AD102: 326-0845 | AE102: 栃木県 足利市 大前町207 | AF102: 0284-62-2065
AA103: 63302 | AB103: ﾇﾉｶﾜﾉｳｷｸﾞﾃﾝ | AC103: 布川農機具店 | AD103: 329-4404 | AE103: 栃木県 栃木市 大平町富田1430 | AF103: 0282-43-2013
AA104: 63303 | AB104: ｽﾅｶﾉｳｷｸﾞﾃﾝ | AC104: 砂川農機具店 | AD104: 326-0323 | AE104: 栃木県 足利市 瑞穂野町495 | AF104: 0284-71-9033
AA105: 63304 | AB105: ｽｽﾞｷﾔ | AC105: ㈱鈴木屋 | AD105: 329-0205 | AE105: 栃木県 小山市 間々田1290 | AF105: 0285-45-0070
AA106: 63305 | AB106: ｶﾜﾀ | AC106: ㈱川田 | AD106: 322-0002 | AE106: 栃木県 鹿沼市 千渡2315-66 | AF106: 0289-65-3366
AA107: 63306 | AB107: ｺﾀﾞｲﾗﾉｳｷｼｮｳｶｲ | AC107: 小平農機商会 | AD107: 321-1261 | AE107: 栃木県 日光市 今市107-22 | AF107: 0288-21-0845
AA108: 63307 | AB108: ｻｲﾄｳﾉｳｷｼｮｳｶｲ | AC108: ㈲斉藤農機商会 | AD108: 329-2161 | AE108: 栃木県 矢板市 扇町1-11-19 | AF108: 0287-43-0475
... AA206: 64391 | AB206: ｶﾝﾄｳｺｳｼﾝｸﾎﾞﾀｸﾞﾝﾏｼﾞﾑｼｮ | AC206: ㈱関東甲信クボタ 群馬事務所 | AD206: 379-2154 | AE206: 群馬県 前橋市 天川大島町1364-1 | AF206: 027-261-6010
AA207: 64398 | AB207: ｶﾝﾄｳｹﾞﾝｷﾝｷｬｸ | AC207: 関東現金客
AA208: 64399 | AB208: ｺｼﾞﾝｷｬｸ | AC208: 個人客
AA209: 64444 | AB209: ﾐﾂﾋﾞｼﾉｳｷﾋｶﾞｼﾆﾎﾝﾌﾞﾋﾝｷｶﾝｾﾝﾀｰ | AC209: 三菱農機㈱ 東日本部品基幹センター | AD209: 340-0203 | AE209: 埼玉県 久喜市 桜田2-133-4 | AF209: 0480-58-9515
AA210: 64445 | AB210: ﾐﾂﾋﾞｼﾉｳｷ | AC210: 三菱ﾏﾋﾝﾄﾞﾗ農機㈱ 島根県 | AD210: 699-0101 | AE210: 島根県 松江市 東出雲町 揖屋667-1 | AF210: 0852-52-2111
AA211: 65130 | AB211: ｿｳﾌﾞｷｶｲ | AC211: ㈱相武機械 | AD211: 215-0003 | AE211: 神奈川県 川崎市 麻生区 高石3-31-27 | AF211: 044-966-4161
AA212: 65131 | AB212: ﾓﾘﾁｮｳ | AC212: 森長 | AD212: 254-0041 | AE212: 神奈川県 平塚市 浅間町5-27 | AF212: 0463-31-2195
AA213: 65132 | AB213: ｶﾝﾄｳｺｼﾝｸﾎﾞﾀｾｲｼﾝｼﾞｷﾞｮｳﾌﾞ | AC213: ㈱関東甲信クボタ 静神事業部 | AD213: 411-0817 | AE213: 静岡県 三島市 八反畑 字鶴田100 | AF213: 055-972-0800
AA214: 65137 | AB214: ｴﾙﾀ | AC214: ㈱エルタ | AD214: 190-1221 | AE214: 東京都 西多摩郡 瑞穂町 箱根ケ崎 東松原20-1 | AF214: 0425-56-0184
AA215: 65323 | AB215: ｵｵﾀｹﾉｳｷ | AC215: 大竹農機㈱ | AD215: 289-1115 | AE215: 千葉県 八街市 八街ほ244 | AF215: 043-444-0225
AA216: 65347 | AB216: ｶﾓｼﾀﾞｼｮｳｶｲ | AC216: 鴨志田商会 | AD216: 226-0000 | AE216: 神奈川県 横浜市 緑区 川和町1437 | AF216: 045-931-1038
AA217: 65348 | AB217: ｷｼﾀﾞﾉｳｷｼｮｳｶｲ | AC217: ㈱岸田農機商会 | AD217: 259-1131 | AE217: 神奈川県 伊勢原市 伊勢原1-7-18 | AF217: 0463-95-0121
AA218: 65350 | AB218: ｻｶﾞﾐﾉｳｷ | AC218: さがみ農機 | AD218: 258-0001 | AE218: 神奈川県 足柄上郡 松田町 寄5501 | AF218: 0465-89-2329
AA219: 65351 | AB219: ｽｽﾞﾉﾉｳｷ | AC219: ㈲鈴野農機 | AD219: 252-0826 | AE219: 神奈川県 藤沢市 宮原1348 | AF219: 0466-48-1048
AA220: 65352 | AB220: ﾀﾅｶﾉｳｷｼｮｳｶｲ | AC220: 田中農機商会 | AD220: 252-0807 | AE220: 神奈川県 藤沢市 下土棚444 | AF220: 0466-44-2005
... AA244: 2133075 | AB244: ﾂｸﾊﾞｼｻｸﾗﾉｳｷｾﾝﾀｰ | AC244: JAつくば市 桜農機センター | AD244: 305-0027 | AE244: 茨城県 つくば市 東岡335 | AF244: 029-857-3116
AA245: 2133107 | AC245: JA常陸 みなみ農機センター | AD245: 319-1234 | AE245: 茨城県 日立市 大和田町1992 | AF245: 0294-53-2121
AA246: 2133110 | AB246: ﾏｼｰﾈｵﾐﾀﾏ | AC246: JAマシーネ 小美玉 | AD246: 311-3412 | AE246: 茨城県 小美玉市 川戸1450-58 | AF246: 0299-58-5644
AA247: 2133115 | AB247: ﾐﾄﾉｳｷｮｳﾐﾄﾉｳｷｾﾝﾀｰ | AC247: JA水戸農協 水戸農機センター | AD247: 311-4141 | AE247: 茨城県 水戸市 赤塚2-27 | AF247: 029-252-2076
AA248: 2133147 | AB248: ﾅﾒｶﾞﾀﾉｳｷﾈﾝﾘｮｳ | AC248: JAなめがた農機燃料㈱ 南部農機センター | AD248: 311-3835 | AE248: 茨城県 行方市 島並857-16 | AF248: 0299-72-1651
AA249: 2134054 | AB249: ｸﾏｶﾞﾔｸﾏｶﾞﾔﾉｳｷｾﾝﾀｰ | AC249: JAくまがや 熊谷農機センター | AD249: 360-0805 | AE249: 埼玉県 熊谷市 上奈良1079-1 | AF249: 048-523-9291
AA250: 2134057 | AB250: ｸﾏｶﾞﾔｺｳﾅﾝﾉｳｷｾﾝﾀｰ | AC250: JAくまがや 江南農機センター | AD250: 360-0115 | AE250: 埼玉県 熊谷市 成沢490-1 | AF250: 048-536-1404
AA251: 2134071 | AB251: ｲﾙﾏﾉﾎｸﾌﾞﾉｳｷｾﾝﾀｰ | AC251: JAいるま野 北部農機センター | AD251: 350-0212 | AE251: 埼玉県 坂戸市 石井1880 | AF251: 049-289-2172
AA252: 2134072 | AB252: ｻｲﾀﾏｻｼｵｳｷﾞｼﾃﾝ | AC252: JAさいたま 指扇支店 | AD252: 331-0071 | AE252: 埼玉県 さいたま市 西区 高木337-3 | AF252: 048-623-5011
AA253: 2134091 | AB253: ｲﾙﾏﾉﾄｺﾛｻﾞﾜﾉｳｷｾﾝﾀｰ | AC253: JAいるま野 所沢農機センター | AD253: 359-0001 | AE253: 埼玉県 所沢市 下富627-10 | AF253: 042-942-3467
AA254: 2134092 | AC254: JAちちぶ農協秩父自動車センター | AD254: 368-0056 | AE254: 埼玉県 秩父市 寺尾3218-1 | AF254: 0494-25-2555
AA255: 2134107 | AB255: ｻｲﾀﾏﾁｭｳｵｳﾋｶﾞｼﾏﾂﾔﾏﾉｳｷｾﾝﾀｰ | AC255: JA埼玉中央 東松山農機センター | AD255: 355-0073 | AE255: 埼玉県 東松山市 上野本1405-1 | AF255: 0493-24-3159
AA256: 2135169 | AB256: ｷﾐﾂ | AC256: JAきみつ 平川農機整備工場 | AD256: 299-0205 | AE256: 千葉県 袖ヶ浦市 上泉366 | AF256: 0438-75-4007
AA257: 2135181 | AB257: ﾁｮｳｾｲﾉｳｷｮｳ | AC257: JA長生農協 睦沢農機センター | AD257: 299-4403 | AE257: 千葉県 長生郡 睦沢町 上市場914 | AF257: 0475-44-1236
AA258: 2135187 | AB258: ｷﾐﾂ | AC258: JAきみつ 天羽農機整備工場 | AD258: 299-1618 | AE258: 千葉県 富津市 花輪150 | AF258: 0439-80-7650
...

Sheet 部品値引
A1: （様式：EL-97A03）
A2: 引き合い内容連絡書 | J2: 株式会社オーレック
A3: 得意先NO： | B3: 得意先名 及び 担当者名： | I3: 受注日：
A4: 63322 | C4: =IFERROR(VLOOKUP(A4,請求先!A:D,2,FALSE)," ") -> 栃木県農業機械商業協同組合 | I4: =TODAY() -> 46201 | L4: 製品コード検索
A5: 納入先NO： | B5: 納入先名及び 担当者名： | G5: 生産日 | I5: 出荷希望日： | L5: HR532X/M | Q5: → | R5: =IFERROR(VLOOKUP(L5,商品コード!B:F,5,FALSE)," ") -> 0256-0420
A6: 69009039 | C6: =IFERROR(VLOOKUP(A6,出荷先!A:F,3,FALSE)," ") -> 片柳農機具店 | I6: 45348
B7: 住所： | C7: 〒 | D7: =IFERROR(VLOOKUP(A6,出荷先!A:F,4,FALSE)," ") -> 324-0234 | I7: TEL | L7: 実演機対応値引 | Q7: =IF(Q6="","",VLOOKUP(Q6,#REF!,2,FALSE))
B8: =IFERROR(VLOOKUP(A6,出荷先!A:F,5,FALSE)," ") -> 栃木県 大田原市 前田142 | I8: =IFERROR(VLOOKUP(A6,出荷先!A:F,6,FALSE)," ") -> 0287-54-2115 | L8: =IF(L7="","",VLOOKUP(L7,商品コード!A:B,2,FALSE)) -> 外掛 | M8: =IF(I8="","",VLOOKUP(I8,商品コード!#REF!,2,FALSE)) -> #REF! | N8: 10 | P8: %
A10: 商品番号 | B10: 商品名 | E10: 数量 | F10: 単位 | G10: 単価 | I10: オーダーＮｏ 等 | L10: 税別小売 | N10: 通常 | P10: =IF(A4="","",VLOOKUP(A4,請求先!A:D,4,FALSE)) -> 0.65 | Q10: 値引 | R10: =$N$8/100 -> 0.1 | S10: 最終 | T10: =IF(L8="外掛",P10-R10,IF(L8="内掛",ROUNDDOWN(P10*(100-100*R10)%,5))) -> 0.55
A11: 0327-74510 | B11: =IFERROR(VLOOKUP(A11,商品コード!A:C,2,FALSE)," ") -> キャブ調整工具 | E11: 3 | G11: =O13 -> 0 | I11: 即売会注文分 | K11: → | L11: =IF(A11="","",VLOOKUP(A11,商品コード!A:C,3,FALSE)) -> 2500 | N11: =L11*P10 -> 1625 | Q11: =IFERROR(S11-N11," ") -> -250 | S11: =ROUNDDOWN(L11*T10,0) -> 1375
B12: =IFERROR(VLOOKUP(A12,商品コード!A:C,2,FALSE)," ") | G12: =O14 -> 0 | K12: → | L12: =IF(A12="","",VLOOKUP(A12,商品コード!A:C,3,FALSE)) | N12: =IFERROR(IF(A4=61121,ROUNDDOWN((L12*P10),-1),IF(A4=61123,ROUNDDOWN((L12*P10),-1),IF(A4=64445001,ROUNDDOWN((L12*P10),-1),IF(A4=64445002,ROUNDDOWN((L12*P10),-1),ROUNDDOWN(L12*P10,-2)))))," ") | Q12: =IFERROR(S12-N12," ") | S12: =IFERROR(IF(OR(A4=61121,A4=61123,A4=64445001,A4=64445002),IF(L8="内掛",ROUNDDOWN(N12*(1-R10),-1),ROUNDDOWN(L12*T10,-1)),IF(L9="内掛",ROUNDDOWN(N12*(1-R10),-2),ROUNDDOWN(L12*T10,-2)))," ")
B13: =IFERROR(VLOOKUP(A13,商品コード!A:C,2,FALSE)," ") | G13: =O15 -> 0 | K13: → | L13: =IF(A13="","",VLOOKUP(A13,商品コード!A:C,3,FALSE)) | N13: =IFERROR(IF(A4=61121,ROUNDDOWN((L13*P10),-1),IF(A4=61123,ROUNDDOWN((L13*P10),-1),IF(A4=64445001,ROUNDDOWN((L13*P10),-1),IF(A4=64445002,ROUNDDOWN((L13*P10),-1),ROUNDDOWN(L13*P10,-2)))))," ") | Q13: =IFERROR(S13-N13," ") | S13: =IFERROR(IF(OR(A4=61121,A4=61123,A4=64445001,A4=64445002),IF(L8="内掛",ROUNDDOWN(N13*(1-R10),-1),ROUNDDOWN(L13*T10,-1)),IF(L10="内掛",ROUNDDOWN(N13*(1-R10),-2),ROUNDDOWN(L13*T10,-2)))," ")
B14: =IFERROR(VLOOKUP(A14,商品コード!A:C,2,FALSE)," ") | G14: =O16 -> 0 | K14: → | L14: =IF(A14="","",VLOOKUP(A14,商品コード!A:C,3,FALSE)) | N14: =IFERROR(IF(A4=61121,ROUNDDOWN((L14*P10),-1),IF(A4=61123,ROUNDDOWN((L14*P10),-1),IF(A4=64445001,ROUNDDOWN((L14*P10),-1),IF(A4=64445002,ROUNDDOWN((L14*P10),-1),ROUNDDOWN(L14*P10,-2)))))," ") | Q14: =IFERROR(S14-N14," ") | S14: =IFERROR(IF(OR(A4=61121,A4=61123,A4=64445001,A4=64445002),IF(L8="内掛",ROUNDDOWN(N14*(1-R10),-1),ROUNDDOWN(L14*T10,-1)),IF(L10="内掛",ROUNDDOWN(N14*(1-R10),-2),ROUNDDOWN(L14*T10,-2)))," ")
B15: =IFERROR(VLOOKUP(A15,商品コード!A:C,2,FALSE)," ") | G15: =O17 -> 0
B16: =IFERROR(VLOOKUP(A16,商品コード!A:C,2,FALSE)," ") | G16: =O18 -> 0
A17: 倉庫（ | B17: 031 | C17: ） | D17: 運賃 | E17: 元払い | F17: 伝票NO：
E18: 立 元 | F18: 出荷確認 | H18: 受注可否検討 | J18: 連絡書作成
A19: 機番 | E19: 着払い | F19: 承認 | H19: 承認 | J19: 作成者
C20: 便名： | D20: 福山便 西濃便 JPロジ
A23: （様式：EL-97A03） | D23: 【 値引 】
A24: 引き合い内容連絡書 | J24: 株式会社オーレック
A25: 得意先NO： | B25: 得意先名 及び 担当者名： | I25: 受注日：
A26: =A4 -> 63322 | C26: =C4 -> 栃木県農業機械商業協同組合 | I26: =I4 -> 46201
A27: 納入先NO： | B27: 納入先名及び 担当者名： | I27: 出荷希望日：
A28: =A6 -> 69009039 | C28: =C6 -> 片柳農機具店 | I28: =I6 -> 45348
B29: 住所： | I29: TEL
A32: 商品番号 | B32: 商品名 | E32: 数量 | F32: 値引後(仕切) | H32: 単価 | J32: 合計
A33: =A11 -> 0327-74510 | B33: =B11 -> キャブ調整工具 | E33: =E11 -> 3 | F33: =S11 -> 1375 | H33: =IFERROR(Q11," ") -> -250 | J33: =IFERROR(H33*E33," ") -> -750
A34: =A12 -> 0 | E34: =E12 -> 0 | F34: =S12 | H34: =IFERROR(Q12," ") | J34: =IFERROR(H34*E34," ")
A35: =A13 -> 0 | E35: =E13 -> 0 | F35: =S13 | H35: =IFERROR(Q13," ") | J35: =IFERROR(H35*E35," ")
A36: =A14 -> 0 | B36: =B14 | E36: =E14 -> 0 | F36: =S14 | H36: =IFERROR(Q14," ") | J36: =IFERROR(H36*E36," ")
A37: =A15 -> 0 | B37: =B15 | E37: =E15 -> 0 | F37: =S15 -> 0 | H37: =IFERROR(-(S17)," ") -> 0 | J37: =IFERROR(H37*E37," ") -> 0
A38: =A16 -> 0 | B38: =B16 | E38: =E16 -> 0 | F38: =Q18 -> 0 | H38: =IFERROR(-(S18)," ") -> 0 | J38: =IFERROR(H38*E38," ") -> 0
A39: 税抜小売 | B39: 掛率 | C39: 単価 | D39: OBIC照合 | F39: 伝票NO： | H39: 合計 | J39: =SUM(J33:J36) -> -750
A40: =L11 -> 2500 | B40: =T10 -> 0.55 | C40: =F33 -> 1375 | D40: =IFERROR((E33*C40)," ") -> 4125 | F40: 出荷確認 | H40: 受注可否検討 | J40: 連絡書作成
A41: =L12 | B41: =T10 -> 0.55 | C41: =F34 | D41: =IFERROR((E34*C41)," ") | F41: 承認 | H41: 承認 | J41: 作成者
A42: =L13 | B42: =T10 -> 0.55 | C42: =F35 | D42: =IFERROR((E35*C42)," ") | E42: OBIC計
A43: =L14 | B43: =T10 -> 0.55 | C43: =F36 | D43: =IFERROR((E36*C43)," ") | E43: =SUM(D40:D43) -> 4125
A44: 値引理由； | B44: =L7 -> 実演機対応値引 | C44: =N8/100 -> 0.1 | D44: 通常仕切； | E44: =IFERROR(VLOOKUP(A4,請求先!A:D,4,FALSE)," ") -> 0.65

Sheet 引合書
A1: （様式：EL-97A03） | S1: 納入先コード | T1: 納入先カナ名 | U1: 納入先正式名 | V1: 郵便番号1 | W1: 住所1 | X1: 電話番号1-1
A2: 引き合い内容連絡書 | J2: 株式会社オーレック | S2: 61102 | T2: ﾆﾎﾝｸﾘﾝﾄﾝ | U2: 日本クリントン㈱ | V2: 121-0836 | W2: 東京都 足立区 入谷5-7-8 | X2: 03-3854-8221
A3: 得意先NO： | B3: 得意先名 及び 担当者名： | I3: 受注日： | S3: 61103 | T3: ﾄｳｺｳｻﾝｷﾞｮｳ | U3: 東興産業㈱ | V3: 350-0821 | W3: 埼玉県 川越市 福田239 | X3: 0492-23-1217
A4: 61110011 | C4: =IFERROR(VLOOKUP(A4,請求先!A:D,2,FALSE)," ") -> （株）関東甲信クボタ 君津営業所 | I4: 45873 | S4: 61105 | T4: ｲﾄｳｻﾝｷﾞｮｳｷｶｲ | U4: 伊藤産業機械㈱ | V4: 290-0034 | W4: 千葉県 市原市 島野1978 | X4: 0436-22-1743
A5: 納入先NO： | B5: 納入先名及び 担当者名： | G5: 生産日 | I5: 出荷希望日： | S5: 61106 | T5: ｴﾑｴｽｹｰﾉｳｷﾞｮｳｷｶｲﾁﾊﾞｼﾞｷﾞｮｳｼｮ | U5: MSK東急機械㈱ 千葉事業所 | V5: 290-0012 | W5: 千葉県 市原市 藤井3-310 | X5: 0436-41-1069
A6: 61110011 | C6: =IFERROR(VLOOKUP(A6,出荷先!A:F,3,FALSE)," ") -> ㈱関東甲信クボタ 君津営業所 | I6: 45873 | S6: 61107 | T6: ｻｻｷｼｮｳｶｲ | U6: ㈱佐々木商会 | V6: 294-0037 | W6: 千葉県 館山市 長須賀123 | X6: 0470-22-1166
B7: 住所： | C7: 〒 | D7: =IFERROR(VLOOKUP(A6,出荷先!A:F,4,FALSE)," ") -> 292-0403 | I7: TEL | S7: 61108 | T7: ｽｷﾞｷﾃｯｺｳ | U7: 杉木鉄工㈱ | V7: 297-0029 | W7: 千葉県 茂原市 高師1536 | X7: 0475-22-4587
B8: =IFERROR(VLOOKUP(A6,出荷先!A:F,5,FALSE)," ") -> 千葉県 君津市 三田123-6 | I8: =IFERROR(VLOOKUP(A6,出荷先!A:F,6,FALSE)," ") -> 0439-29-6301 | S8: 61109 | T8: ﾀｶﾉｻﾝｷﾞｮｳ | U8: 高野産業㈱ | V8: 292-0054 | W8: 千葉県 木更津市 長須賀924-1 | X8: 0438-22-6251
S9: 61110 | T9: ｶﾝﾄｳｺｼﾝｸﾎﾞﾀﾁﾊﾞｼﾞｷﾞｮｳﾌﾞ | U9: ㈱関東甲信クボタ 南関東事業所 | V9: 260-0808 | W9: 千葉県 千葉市 中央区 星久喜町176-4 | X9: 043-261-3131
A10: 商品番号 | B10: 商品名 | E10: 数量 | F10: 単位 | G10: 単価 | I10: オーダーＮｏ 等 | S10: 61111 | T10: ﾅｶﾔｼｮｳｶｲ | U10: ㈱中屋商会 | V10: 289-2146 | W10: 千葉県 匝瑳市 八日市場ホ452 | X10: 0479-72-1161
A11: 89-1113-060182 | B11: =IFERROR(VLOOKUP(A11,商品コード!A:C,2,FALSE)," ") -> 六角ﾎﾞﾙﾄ(8T) M6*18 | E11: 1 | S11: 61112 | T11: ﾅｶﾑﾗｻﾝｷﾞｮｳ | U11: ㈱中村産業 | V11: 283-0811 | W11: 千葉県 東金市 台方246 | X11: 0475-52-2615
A12: 0353-71210 | B12: =IFERROR(VLOOKUP(A12,商品コード!A:C,2,FALSE)," ") -> 変速ワイヤー | E12: 1 | S12: 61113 | T12: ﾌﾀﾊﾞｺｳｷ | U12: ㈲双葉工機 | V12: 270-2222 | W12: 千葉県 松戸市 高塚新田340-11 | X12: 0473-92-7256
A13: 0353-2051H | B13: =IFERROR(VLOOKUP(A13,商品コード!A:C,2,FALSE)," ") -> 刈高さ調整フレーム | E13: 1 | S13: 61114 | T13: ﾓﾊﾞﾗﾌｺｸｼｬ | U13: ㈱茂原富国社 | V13: 297-0029 | W13: 千葉県 茂原市 高師1671 | X13: 0475-25-0325
A14: 0353-01800 | B14: =IFERROR(VLOOKUP(A14,商品コード!A:C,2,FALSE)," ") -> 変速ｱｰﾑ | E14: 1 | S14: 61115 | T14: ｲﾊﾞﾗｷﾘｮｳﾉｳ | U14: 茨城菱農㈱ | V14: 300-4201 | W14: 茨城県 つくば市 寺具1332-9 | X14: 0298-69-1045
A15: 89-1511-060042 | B15: =IFERROR(VLOOKUP(A15,商品コード!A:C,2,FALSE)," ") -> 六角ﾅｯﾄ M6 | E15: 1 | S15: 61116 | T15: ｶﾝﾄｳｺｳｼﾝｸﾎﾞﾀｲﾊﾞﾗｷｼﾞﾑｼｮ | U15: ㈱関東甲信クボタ 茨城事務所 | V15: 300-2402 | W15: 茨城県 つくばみらい市 坂野新田12-42 | X15: 0297-52-1111
B16: =IFERROR(VLOOKUP(A16,商品コード!A:C,2,FALSE)," ") | S16: 61117 | T16: ｵｵｶﾜｷｶｲ | U16: 大川機械 | V16: 300-0024 | W16: 茨城県 土浦市 田村町988-2 | X16: 0298-28-0755
A17: 倉庫（ | B17: 001 | C17: ） | D17: 運賃 | E17: 元払い | F17: 伝票NO： | S17: 61118 | T17: ﾐﾂﾋﾞｼﾉｳｷﾊﾝﾊﾞｲｲﾊﾞﾗｷｼﾃﾝ | U17: 三菱農機販売㈱ 茨城支店 | V17: 311-0133 | W17: 茨城県 那珂市 鴻巣1135-1 | X17: 0293-53-2140
B18: 0 | E18: 立 元 | F18: 出荷確認 | H18: 受注可否検討 | J18: 連絡書作成 | S18: 61120 | T18: ｼﾏｻﾉｳｷ | U18: ㈱嶋田農機 | V18: 300-3544 | W18: 茨城県 結城郡 八千代町 若996 | X18: 0296-48-1025
A19: 鶴岡担当 SP853 不具合対応のため | E19: 着払い | F19: 承認 | H19: 承認 | J19: 作成者 | S19: 61121 | T19: ｸﾎﾞﾀｲﾊﾞﾗｷｹﾝｴｲｷﾞｮｳﾀﾝﾄｳ | U19: ㈱クボタ 茨城県営業担当 | V19: 338-0832 | W19: 埼玉県 さいたま市 桜区 西堀5-2-36 | X19: 048-862-1125
C20: 便名： | D20: 福山便 西濃便 JPロジ | S20: 61122 | T20: ﾅﾘﾀｶﾄｳﾉｳｷ | U20: 成田加藤農機（有） | V20: 286-0021 | W20: 千葉県 成田市 土屋1375-1 | X20: 0476-22-0579
S21: 61123 | T21: ｸﾎﾞﾀﾄﾁｷﾞｹﾝｴｲｷﾞｮｳﾀﾝﾄｳ | U21: ㈱クボタ 栃木県営業担当 | V21: 338-0832 | W21: 埼玉県 さいたま市 桜区 西堀5-2-36 | X21: 048-862-1125
S22: 61124 | T22: ﾈﾓﾄｼｮｳｶｲ | U22: ㈲根本商会 | V22: 286-0801 | W22: 千葉県 成田市 竜台468 | X22: 0476-37-1211
A23: 製品コード検索 | S23: 61125 | T23: ﾏﾙﾃﾝｻﾝｷﾞｮｳｷｶｲ | U23: マルテン産業機械㈱ | V23: 293-0001 | W23: 千葉県 富津市 大堀1434 | X23: 0439-87-0052
A24: RCSP530/Y | F24: → | G24: =IFERROR(VLOOKUP(A24,商品コード!B:F,5,FALSE)," ") | S24: 61126 | T24: ﾐﾂﾋﾞｼﾉｳｷﾊﾝﾊﾞｲﾁﾊﾞｼﾃﾝ | U24: 三菱農機販売㈱ 千葉支店 | V24: 300-1312 | W24: 茨城県 稲敷郡 河内町 長竿字西の町1596-2 | X24: 0297-63-4633
S25: 61127 | T25: ｸﾎﾞﾀｸﾞﾝﾏｹﾝｴｲｷﾞｮｳﾀﾝﾄｳ | U25: ㈱クボタ 群馬県営業担当 | V25: 338-0832 | W25: 埼玉県 さいたま市 桜区 西堀5-2-36 | X25: 048-862-1125
S26: 61133 | T26: ﾏｷﾀﾇﾏﾂﾞﾋｶﾞｼﾆﾎﾝ | U26: ㈱マキタ沼津 東日本支店 | V26: 362-0031 | W26: 埼玉県 上尾市 東町2-8-4 | X26: 048-779-2262
S27: 61134 | T27: ｸﾎﾞﾀｹﾝｷｼﾞｬﾊﾟﾝﾁﾊﾞｴｲｷﾞｮｳｼｮ | U27: ㈱クボタ建機ジャパン千葉営業所 | V27: 283-0823 | W27: 千葉県 東金市 山田 字新田1201-10 | X27: 茨城菱農
S28: 61135 | T28: ｵｵｻﾜｷｶｲ | U28: 大沢機械 | V28: 191-0043 | W28: 東京都 日野市 平山6-2-1 | X28: 042-591-1588
S29: 61136 | T29: ｼﾊﾞﾀ | U29: ㈱シバタ | V29: 104-0032 | W29: 東京都 中央区 八丁堀4-3-1 | X29: 03-3552-0381
S30: 61140 | T30: ﾏｷﾀﾇﾏﾂﾞｷﾞｮｳﾑﾌﾞｼｮｳﾋﾝｶ | U30: ㈱マキタ沼津 業務部商品課 | V30: 410-0022 | W30: 静岡県 沼津市 大岡35 | X30: 055-963-1112
S31: 61301 | T31: ｶﾅｴｻﾝｷﾞｮｳ | U31: カナエ産業㈱ | V31: 194-0215 | W31: 東京都 町田市 小山ケ丘3-7-10 | X31: 042-798-7181
S32: 61302 | T32: ﾖｼｻﾞﾜｹﾞﾝﾄﾞｳｷ | U32: 吉澤原動機 | V32: 114-0013 | W32: 東京都 北区 東田端2-8-6 | X32: 03-3810-2700
S33: 61303 | T33: ﾐﾔｼﾞｷｶｲ | U33: ㈱宮地機械（出荷停止） | V33: 177-0033 | W33: 東京都 練馬区 高野台4-11-28 | X33: 03-3997-3155
S34: 61304 | T34: ﾊﾁｷﾞｮｳｼｮｳｼﾞ | U34: 八丈商事 | V34: 100-1401 | W34: 東京都 八丈島 八丈町 大賀郷1098-2 | X34: 04996-2-2189
S35: 61305 | T35: ｲｼｲﾃﾞﾝｷｼｮｳﾃﾝ | U35: ㈱石井電気商店 | V35: 294-0042 | W35: 千葉県 館山市 上野原294-5 | X35: 0470-22-0542
S36: 61306 | T36: ｲｺﾞｳﾉｳｷ | U36: ㈲井合農機店 | V36: 273-0047 | W36: 千葉県 船橋市 藤原5-22-31 | X36: 047-439-5477
... S95: 61376 | T95: ﾘｮｳｴｲｼｬ | U95: ㈲良栄社商会 | V95: 299-1151 | W95: 千葉県 君津市 中野4-15-18 | X95: 0439-52-0035
T96: ｺｼﾞﾝｷｬｸ | U96: 個人客
S97: 61400 | T97: ｺﾐﾔﾉｳｻﾝｷｼｮｳｶｲ | U97: ㈲古宮農蚕機商会 | V97: 192-0051 | W97: 東京都 八王子市 元本郷町1-5-5 | X97: 042-625-2328
S98: 63102 | T98: ﾐﾂﾋﾞｼﾉｳｷﾊﾝﾊﾞｲｶﾝﾄｳｺｳｼﾝｴﾂ | U98: 三菱農機販売㈱ 関東甲信越支店 | V98: 340-0203 | W98: 埼玉県 久喜市 桜田2-133-4 | X98: 0480-58-9521
S99: 63103 | T99: ｶﾝﾄｳｺｳｼﾝｸﾎﾞﾀｸﾎﾞﾀﾄﾁｷﾞｼﾞﾑｼｮ | U99: ㈱関東甲信クボタ 北関東事業所 （栃木） | V99: 321-0905 | W99: 栃木県 宇都宮市 平出工業団地28-2 | X99: 0286-89-2341
S100: 63105 | T100: ﾐﾂﾋﾞｼﾉｳｷﾊﾝﾊﾞｲﾄﾁｷﾞｼﾃﾝ | U100: 三菱農機販売㈱ 栃木支店 | V100: 329-1233 | W100: 栃木県 塩谷郡 高根沢町 宝積寺 中2248-60 | X100: 0286-75-7321
S101: 63112 | T101: ﾀｶﾀﾞﾗｸﾉｳｷ | U101: 高田酪農機㈱ | V101: 321-3236 | W101: 栃木県 宇都宮市 竹下町1101-11 | X101: 028-667-2825
S102: 63301 | T102: ｺﾋﾞｷﾉｳｷｸﾞﾃﾝ | U102: 小比企農機具店 | V102: 326-0845 | W102: 栃木県 足利市 大前町207 | X102: 0284-62-2065
S103: 63302 | T103: ﾇﾉｶﾜﾉｳｷｸﾞﾃﾝ | U103: 布川農機具店 | V103: 329-4404 | W103: 栃木県 栃木市 大平町富田1430 | X103: 0282-43-2013
S104: 63303 | T104: ｽﾅｶﾉｳｷｸﾞﾃﾝ | U104: 砂川農機具店 | V104: 326-0323 | W104: 栃木県 足利市 瑞穂野町495 | X104: 0284-71-9033
S105: 63304 | T105: ｽｽﾞｷﾔ | U105: ㈱鈴木屋 | V105: 329-0205 | W105: 栃木県 小山市 間々田1290 | X105: 0285-45-0070
S106: 63305 | T106: ｶﾜﾀ | U106: ㈱川田 | V106: 322-0002 | W106: 栃木県 鹿沼市 千渡2315-66 | X106: 0289-65-3366
S107: 63306 | T107: ｺﾀﾞｲﾗﾉｳｷｼｮｳｶｲ | U107: 小平農機商会 | V107: 321-1261 | W107: 栃木県 日光市 今市107-22 | X107: 0288-21-0845
S108: 63307 | T108: ｻｲﾄｳﾉｳｷｼｮｳｶｲ | U108: ㈲斉藤農機商会 | V108: 329-2161 | W108: 栃木県 矢板市 扇町1-11-19 | X108: 0287-43-0475
... S206: 64391 | T206: ｶﾝﾄｳｺｳｼﾝｸﾎﾞﾀｸﾞﾝﾏｼﾞﾑｼｮ | U206: ㈱関東甲信クボタ 群馬事務所 | V206: 379-2154 | W206: 群馬県 前橋市 天川大島町1364-1 | X206: 027-261-6010
S207: 64398 | T207: ｶﾝﾄｳｹﾞﾝｷﾝｷｬｸ | U207: 関東現金客
S208: 64399 | T208: ｺｼﾞﾝｷｬｸ | U208: 個人客
S209: 64444 | T209: ﾐﾂﾋﾞｼﾉｳｷﾋｶﾞｼﾆﾎﾝﾌﾞﾋﾝｷｶﾝｾﾝﾀｰ | U209: 三菱農機㈱ 東日本部品基幹センター | V209: 340-0203 | W209: 埼玉県 久喜市 桜田2-133-4 | X209: 0480-58-9515
S210: 64445 | T210: ﾐﾂﾋﾞｼﾉｳｷ | U210: 三菱ﾏﾋﾝﾄﾞﾗ農機㈱ 島根県 | V210: 699-0101 | W210: 島根県 松江市 東出雲町 揖屋667-1 | X210: 0852-52-2111
S211: 65130 | T211: ｿｳﾌﾞｷｶｲ | U211: ㈱相武機械 | V211: 215-0003 | W211: 神奈川県 川崎市 麻生区 高石3-31-27 | X211: 044-966-4161
S212: 65131 | T212: ﾓﾘﾁｮｳ | U212: 森長 | V212: 254-0041 | W212: 神奈川県 平塚市 浅間町5-27 | X212: 0463-31-2195
S213: 65132 | T213: ｶﾝﾄｳｺｼﾝｸﾎﾞﾀｾｲｼﾝｼﾞｷﾞｮｳﾌﾞ | U213: ㈱関東甲信クボタ 静神事業部 | V213: 411-0817 | W213: 静岡県 三島市 八反畑 字鶴田100 | X213: 055-972-0800
S214: 65137 | T214: ｴﾙﾀ | U214: ㈱エルタ | V214: 190-1221 | W214: 東京都 西多摩郡 瑞穂町 箱根ケ崎 東松原20-1 | X214: 0425-56-0184
S215: 65323 | T215: ｵｵﾀｹﾉｳｷ | U215: 大竹農機㈱ | V215: 289-1115 | W215: 千葉県 八街市 八街ほ244 | X215: 043-444-0225
S216: 65347 | T216: ｶﾓｼﾀﾞｼｮｳｶｲ | U216: 鴨志田商会 | V216: 226-0000 | W216: 神奈川県 横浜市 緑区 川和町1437 | X216: 045-931-1038
S217: 65348 | T217: ｷｼﾀﾞﾉｳｷｼｮｳｶｲ | U217: ㈱岸田農機商会 | V217: 259-1131 | W217: 神奈川県 伊勢原市 伊勢原1-7-18 | X217: 0463-95-0121
S218: 65350 | T218: ｻｶﾞﾐﾉｳｷ | U218: さがみ農機 | V218: 258-0001 | W218: 神奈川県 足柄上郡 松田町 寄5501 | X218: 0465-89-2329
S219: 65351 | T219: ｽｽﾞﾉﾉｳｷ | U219: ㈲鈴野農機 | V219: 252-0826 | W219: 神奈川県 藤沢市 宮原1348 | X219: 0466-48-1048
S220: 65352 | T220: ﾀﾅｶﾉｳｷｼｮｳｶｲ | U220: 田中農機商会 | V220: 252-0807 | W220: 神奈川県 藤沢市 下土棚444 | X220: 0466-44-2005
... S244: 2133075 | T244: ﾂｸﾊﾞｼｻｸﾗﾉｳｷｾﾝﾀｰ | U244: JAつくば市 桜農機センター | V244: 305-0027 | W244: 茨城県 つくば市 東岡335 | X244: 029-857-3116
S245: 2133107 | U245: JA常陸 みなみ農機センター | V245: 319-1234 | W245: 茨城県 日立市 大和田町1992 | X245: 0294-53-2121
S246: 2133110 | T246: ﾏｼｰﾈｵﾐﾀﾏ | U246: JAマシーネ 小美玉 | V246: 311-3412 | W246: 茨城県 小美玉市 川戸1450-58 | X246: 0299-58-5644
S247: 2133115 | T247: ﾐﾄﾉｳｷｮｳﾐﾄﾉｳｷｾﾝﾀｰ | U247: JA水戸農協 水戸農機センター | V247: 311-4141 | W247: 茨城県 水戸市 赤塚2-27 | X247: 029-252-2076
S248: 2133147 | T248: ﾅﾒｶﾞﾀﾉｳｷﾈﾝﾘｮｳ | U248: JAなめがた農機燃料㈱ 南部農機センター | V248: 311-3835 | W248: 茨城県 行方市 島並857-16 | X248: 0299-72-1651
S249: 2134054 | T249: ｸﾏｶﾞﾔｸﾏｶﾞﾔﾉｳｷｾﾝﾀｰ | U249: JAくまがや 熊谷農機センター | V249: 360-0805 | W249: 埼玉県 熊谷市 上奈良1079-1 | X249: 048-523-9291
S250: 2134057 | T250: ｸﾏｶﾞﾔｺｳﾅﾝﾉｳｷｾﾝﾀｰ | U250: JAくまがや 江南農機センター | V250: 360-0115 | W250: 埼玉県 熊谷市 成沢490-1 | X250: 048-536-1404
S251: 2134071 | T251: ｲﾙﾏﾉﾎｸﾌﾞﾉｳｷｾﾝﾀｰ | U251: JAいるま野 北部農機センター | V251: 350-0212 | W251: 埼玉県 坂戸市 石井1880 | X251: 049-289-2172
S252: 2134072 | T252: ｻｲﾀﾏｻｼｵｳｷﾞｼﾃﾝ | U252: JAさいたま 指扇支店 | V252: 331-0071 | W252: 埼玉県 さいたま市 西区 高木337-3 | X252: 048-623-5011
S253: 2134091 | T253: ｲﾙﾏﾉﾄｺﾛｻﾞﾜﾉｳｷｾﾝﾀｰ | U253: JAいるま野 所沢農機センター | V253: 359-0001 | W253: 埼玉県 所沢市 下富627-10 | X253: 042-942-3467
S254: 2134092 | U254: JAちちぶ農協秩父自動車センター | V254: 368-0056 | W254: 埼玉県 秩父市 寺尾3218-1 | X254: 0494-25-2555
S255: 2134107 | T255: ｻｲﾀﾏﾁｭｳｵｳﾋｶﾞｼﾏﾂﾔﾏﾉｳｷｾﾝﾀｰ | U255: JA埼玉中央 東松山農機センター | V255: 355-0073 | W255: 埼玉県 東松山市 上野本1405-1 | X255: 0493-24-3159
S256: 2135169 | T256: ｷﾐﾂ | U256: JAきみつ 平川農機整備工場 | V256: 299-0205 | W256: 千葉県 袖ヶ浦市 上泉366 | X256: 0438-75-4007
S257: 2135181 | T257: ﾁｮｳｾｲﾉｳｷｮｳ | U257: JA長生農協 睦沢農機センター | V257: 299-4403 | W257: 千葉県 長生郡 睦沢町 上市場914 | X257: 0475-44-1236
S258: 2135187 | T258: ｷﾐﾂ | U258: JAきみつ 天羽農機整備工場 | V258: 299-1618 | W258: 千葉県 富津市 花輪150 | X258: 0439-80-7650
S259: 2135190 | T259: ｲﾁﾊﾗｼﾉｳｷｾﾝﾀｰ | U259: JA市原市 農機センター | V259: 290-0225 | W259: 千葉県 市原市 牛久573-1 | X259: 0436-92-5650
S260: 2135192 | T260: ｱﾜﾉｳｷｮｳｳﾁﾎﾞｳﾉｳｷｾﾝﾀｰ | U260: JA安房農協 内房農機ｾﾝﾀｰ | V260: 294-0813 | W260: 千葉県 南房総市 谷向56 | X260: 0470-36-4070
S261: 2135198 | U261: JA君津市農業協同組合上総農機 SS | V261: 292-0503 | W261: 千葉県 君津市 広岡1771 | X261: 0439-29-2080
S262: 2135221 | T262: ﾆｼﾝﾊﾞﾉｳｷﾖｳｾｲｶﾂﾌﾞ | U262: JA西印旛農協 生活部 機械課 | V262: 270-1337 | W262: 千葉県 印西市 草深1230 | X262: 0476-47-3133
S263: 2135223 | T263: ｷｻﾗﾂﾞｼﾉｳｷﾞｮｳｷｮｳﾄﾞｳ | U263: JA木更津市農業協同組合 中郷農機事業 ｾﾝﾀｰ | V263: 292-0026 | W263: 千葉県 木更津市 井尻525-1 | X263: 0438-98-0279
S264: 2135424 | T264: ﾄﾐｻﾄｼﾉｳｷｾﾝﾀｰ | U264: JA富里市農機センター | V264: 286-0212 | W264: 千葉県 富里市 十倉431-1 | X264: 0476-93-8683
S265: 2135424 | T265: ﾄﾐｻﾄｼﾉｳｷﾞｮｳｷｮｳﾄﾞｳｾﾝﾀｰ | U265: JA富里市 農業共同センター | V265: 286-0212 | W265: 千葉県 富里市 十倉431-1 | X265: 0476-93-8683
S266: 2135424 | T266: ﾄﾐｻﾄｼﾉｳｷﾞｮｳｷｮｳﾄﾞｳｾﾝﾀｰ | U266: JA富里市 農機共同センター
S267: 2135428 | T267: ｷﾐﾂｿｳｺﾞｳｷｶｲｾﾝﾀｰ | U267: JA君津総合機械センター | V267: 299-1104 | W267: 千葉県 君津市 糠田169 | X267: 0439-32-5081
S268: 2135542 | T268: ﾁﾊﾞﾐﾄﾞﾘﾉｳｷｾﾝﾀｰ | U268: JAちばみどり 農機センター | V268: 289-2503 | W268: 千葉県 旭市 江ヶ崎661 | X268: 0479-63-7009
S269: 2136069 | T269: ﾄｳｷｮｳﾐﾗｲ | U269: JA東京みらい 農機センター | V269: 189-0014 | W269: 東京都 東村山市 本町1-16-5 | X269: 0423-93-5211
S270: 2136073 | T270: ﾏﾁﾀﾞｼﾉｳｷｮｳﾉｳｷｾﾝﾀｰ | U270: JA町田市農協 農機センター | V270: 194-0035 | W270: 東京都 町田市 忠生1-29-4 | X270: 042-792-2811
S271: 2137003 | T271: ｹﾝｵｳｱｲｶﾜｹｲｻﾞｲｾﾝﾀｰ | U271: JA県央愛川経済センター | V271: 243-0308 | W271: 神奈川県 愛甲郡 愛川町 三増891 | X271: 0462-81-5000
S272: 2137004 | T272: ｻｶﾞﾐﾉｳｷｮｳｱﾔｾｴｲﾉｳｹｲｻﾞｲ | U272: JAさがみ農協 綾瀬営農経済 | V272: 252-1103 | W272: 神奈川県 綾瀬市 深谷3333 | X272: 0467-78-0521
S273: 2137008 | T273: ｻｶﾞﾐﾉｳｷｮｳｴﾋﾞﾅ | U273: JAさがみ農協 海老名営農センター | V273: 243-0411 | W273: 神奈川県 海老名市 大谷240 | X273: 046-234-2514
S274: 2137010 | T274: ｶﾅｶﾞﾜｾｲﾌﾞﾉｳｷｮｳﾉｳｷｾﾝﾀｰ | U274: JAかながわ西部農協農機センター | V274: 258-0016 | W274: 神奈川県 足柄上郡 大井町 上大井238 | X274: 0465-83-4171
S275: 2137051 | T275: ｼｮｳﾅﾝﾉｳｷｮｳｼﾞｷﾞｮｳｾﾝﾀｰﾉｳｷ | U275: JA湘南農協 事業センター農機 | V275: 259-1213 | W275: 神奈川県 平塚市 片岡657 | X275: 0463-58-2125
S276: 2137063 | T276: ｾﾞﾝﾉｳｶﾅｶﾞﾜｹﾝﾎﾝﾌﾞﾄｳﾌﾞｷﾀﾉｳｷｾﾝﾀｰ | U276: JA全農神奈川県本部 東部きた 農機センター | V276: 224-0045 | W276: 神奈川県 横浜市 都筑区 東方町1401 | X276: 045-942-8666
S277: 69009226 | T277: ｳｴﾉ | U277: ㈱上野 | V277: 323-0012 | W277: 栃木県 小山市 羽川777-35 | X277: 0285-23-5212
S278: 69009166 | T278: ｵｵﾇｷｷｶｲﾃﾝ | U278: ㈲大貫機械店 | V278: 329-2161 | W278: 栃木県 矢板市 扇町1-16-22 | X278: 0287-43-0366
...

Sheet 商品コード
A1: 品番コード | B1: 品番名 | C1: 新小売単価(2023.1.1～) | D1: やまびこ運賃 | E1: ｲﾘﾉ値引 | F1: 品番コード | J1: データ引用2022/04/01
A2: 実演機値引 | B2: 外掛 | F2: 実演機値引
A3: 実演機対応値引 | B3: 外掛 | F3: 実演機対応値引
A4: 展示機値引 | B4: 内掛 | F4: 展示機値引
A5: 不需要期値引 | B5: 内掛 | F5: 不需要期値引
A6: 早期確注値引 | B6: 内掛 | F6: 早期確注値引
A7: 台数値引 | B7: 内掛 | F7: 台数値引
A8: 推進値引 | B8: 内掛 | F8: 推進値引
A9: 展示会値引 | B9: 内掛 | F9: 展示会値引
A10: 0353-0020 | B10: SP753B/M | C10: 328000
A11: 0331-0220 | B11: AM63AX/M | C11: 278000 | D11: 7660 | F11: 0331-0220
A12: 0332-0220 | B12: AM63BX/M | C12: 309000 | D12: 7660 | F12: 0332-0220
A13: 0332-0320 | B13: AM64B/M | C13: 396000 | D13: 7660 | F13: 0332-0320
A14: 0333-0220 | B14: AM73BX/M | C14: 367000 | D14: 9200 | F14: 0333-0220
A15: 0333-0320 | B15: AM74B/M | C15: 468000 | D15: 9200 | F15: 0333-0320
A16: 0311-0220 | B16: AM81X/M | C16: 388000 | D16: 14420 | F16: 0311-0220
A17: 0051-0020 | B17: AR301/M | C17: 217000 | D17: 5220 | F17: 0051-0020
A18: 0027-0020 | B18: AR400/M | C18: 228000 | D18: 5220 | F18: 0027-0020
A19: 0036-0220 | B19: AR660/M | C19: 280000 | D19: 4480 | F19: 0036-0220
A20: 0038-0020 | B20: AR604/M | C20: 327000 | D20: 7260 | F20: 0038-0020
A21: 0039-0020 | B21: AR704/M | C21: 366000 | D21: 9200 | F21: 0039-0020
A22: 0040-0020 | B22: AR607N/M | C22: 291000 | D22: 7260 | F22: 0040-0020
... A65: 0356-0110 | B65: RMK180X/K | C65: 1598000 | D65: 32000 | F65: 0356-0110
A66: 0361-0010 | B66: RMT110/K | C66: 1177000 | F66: 0361-0010
A67: 0031-0220 | B67: SF601/M | C67: 227000 | D67: 5220 | F67: 0031-0220
A68: 0032-0120 | B68: SF601D/M | C68: 264000 | D68: 5220 | F68: 0032-0120
A69: 0046-0120 | B69: SF601V/M | C69: 198000 | D69: 5920 | F69: 0046-0120
A70: 0052-0120 | B70: SF701/M | C70: 208000 | D70: 5920 | F70: 0052-0120
A71: 0265-0220 | B71: SH51X/M | C71: 197000 | D71: 5220 | F71: 0265-0220
A72: 0930-0220 | B72: SJ600X/M | C72: 4446000 | F72: 0930-0220
A73: 0930-0320 | B73: SJ600X-33/M | C73: 4481000 | F73: 0930-0320
A74: 0931-0220 | B74: SJ800X/M | C74: 4561000 | F74: 0931-0220
A75: 0931-0320 | B75: SJ800X-33/M | C75: 4620000 | F75: 0931-0320
A76: 0951-0020 | B76: SJ800A/M | C76: 5104000 | F76: 0951-0020
A77: 0306-0020 | B77: SP301A/M | C77: 185000 | D77: 2540 | F77: 0306-0020
A78: 0326-0220 | B78: SP431F/M | C78: 263000 | D78: 3780 | E78: 10900 | F78: 0326-0220
A79: 0353-0260 | B79: SP853A/Y | C79: 308000 | D79: 5220 | F79: 0353-0060
A80: 0359-0020 | B80: WM634/M | C80: 228000 | D80: 5920 | E80: 8600 | F80: 0359-0020
A81: 0321-0220 | B81: WM646F/M | C81: 279000 | D81: 7660 | E81: 12200 | F81: 0321-0220
A82: 0317-0320 | B82: WM746F/M | C82: 299000 | D82: 9200 | E82: 14000 | F82: 0317-0320
A83: 0328-0120 | B83: WM757P/M | C83: 349000 | D83: 9200 | E83: 14700 | F83: 0328-0120
A84: 0358-0020 | B84: WMC747P/M | C84: 399000 | D84: 7260 | F84: 0358-0020
A85: 0315-0320 | B85: WMC1317F/M | C85: 439000 | D85: 7260 | F85: 0315-0320
A86: 0343-80000 | B86: 剪定枝ﾌｫｰｸｾｯﾄ | C86: 96800 | F86: 0343-80000
A87: 0347-80300 | B87: 剪定枝ﾌｫｰｸｾｯﾄ 4WD | C87: 88000 | F87: 0347-80300
A88: 0312-89000 | B88: 牽引式ｽｲｰﾊﾟｰﾋｯﾁｾｯﾄ | C88: 167000 | D88: 3780 | F88: 0312-89000
A89: 0342-90000 | B89: HS100 | C89: 350000 | D89: 3780 | F89: 0342-90000
A90: 0371-0160 | B90: RCSP530A/Y | C90: 1320000 | F90: 0371-0160
A91: 0354-0020 | B91: HRS815/M | C91: 999000 | F91: 0354-0020
A92: 0342-81000 | B92: SW700 | C92: 279000 | F92: 0342-81000
A93: 0929-0220 | B93: SGW804/M | C93: 261000 | F93: 0929-0220
A94: 0929-0320 | B94: SGW804S/M | C94: 294000 | F94: 0929-0320
A95: 0342-86000 | B95: 落葉収集ﾚｰｷｾｯﾄ | C95: 44000 | F95: 0342-86000
A96: 0934-0020 | B96: BX800/M | C96: 484000 | F96: 0934-0020
A97: 0941-0000 | B97: MP750 | C97: 385000 | F97: 0941-0000
A98: 0372-0080 | B98: RCHR800 | C98: 3000000 | F98: 0372-0080
A99: 0365-0020 | B99: HR403 | C99: 318000
A100: 0317-0420 | B100: WM746AF/M | C100: 309000
A101: 0328-0220 | B101: WM757AP/M | C101: 359000
A102: 0374-0060 | B102: RCSP540/Y | C102: 1480000
A103: 0321-0320 | B103: WM646AF/M | C103: 299000
A104: 0358-0120 | B104: WMC747AP/M | C104: 409000
A105: 0315-0420 | B105: WMC1327F/M | C105: 449000
A106: 0372-0180 | B106: RCHR800A | C106: 3200000
A107: 0354-0120 | B107: HRS815A/M | C107: 1098000
A108: 0940-0170 | B108: ZHR800A/M | C108: 1550000
A109: 0310-0480 | B109: RM832A | C109: 800000
A110: 0333-0420 | B110: AM75B/M | C110: 468000
... A142: 0328-0220 | B142: WM757AP | C142: 359000
A143: 0353-71210 | B143: 変速ワイヤー
A144: 0353-2051H | B144: 刈高さ調整フレーム
A145: 0353-01800 | B145: 変速ｱｰﾑ
A146: 9001-0360 | B146: GEH802 | C146: 77000
A147: 9016-0620 | B147: GB300PN-406
A148: 0208-09910 | B148: 防振ｺﾞﾑ
A149: 88-A021-005400 | B149: ﾀﾞｲﾔﾌﾗﾑｷｬﾌﾞﾚﾀｰ
A150: 88-14075-0707 | B150: ｷｬｯﾌﾟｱｯｼ
A151: 89-6123-006102 | B151: Vﾍﾞﾙﾄ SB61W800
A152: 0208-3920G | B152: ﾄﾞﾗｲﾌﾞﾁｪｰﾝｹｰｽASY緑
A153: 0371-72000 | B153: ﾊﾞｯﾃﾘｰﾕﾆｯﾄ | C153: 84000
A154: 0212-71100 | B154: ｴﾝｼﾞﾝｽﾄｯﾌﾟｽｲｯﾁ
A155: 0315-75200 | B155: DUﾌﾞｯｼｭ 42.30
A156: 0201-51411 | B156: ｽｲﾝｸﾞｹｰｽA CMP 白
A157: 88-11065-7025 | B157: ｷｬｯﾌﾟ | C157: 4800
A158: 0347-39000 | B158: ｳﾚﾀﾝﾀｲﾔ 17*8.00-8(L)ﾎﾞ | C158: 55000
A159: 0347-38000 | B159: ｳﾚﾀﾝﾀｲﾔ 17*8.00-8(R)ﾎﾞ | C159: 55000
A160: 0346-32000 | B160: ｳﾚﾀﾝﾀｲﾔ 3.50-7(L)ﾎﾞｽ無し | C160: 31000
A161: 0346-31000 | B161: ｳﾚﾀﾝﾀｲﾔ 3.50-7(R)ﾎﾞｽ無し | C161: 31000
A162: 88-KA01032A002 | B162: ｸﾘｰﾅｰｴﾚﾒﾝﾄ
A163: 0353-3910H | B163: ｽﾊﾟｲｸ車輪ASSY ｶﾞﾝﾒﾀ
A164: 0353-3010H | B164: ｽﾊﾟｲｸ車輪CMP ｶﾞﾝﾒﾀ
A165: 0353-0020 | B165: SP753B/M
A166: 0342-85800 | B166: ﾛｰﾌﾟ取付ﾚﾊﾞｰ | F166: 0342-85800
A167: 0001-10200 | B167: ﾊﾝﾄﾞﾙﾎﾞﾝﾈｯﾄ | C167: 1550 | F167: 0001-10200
A168: 0001-10400 | B168: ﾉﾌﾞﾎﾞﾙﾄ M8*95 | C168: 1750 | F168: 0001-10400
A169: 0353-0020 | B169: SP753B/M | C169: 328000 | F169: 0001-20300
A170: 0372-0180 | B170: RCHR800A | C170: 3200000 | F170: 0001-20500
A171: 0001-20600 | B171: ﾄﾞﾗﾑ軸ｷﾞﾔ13T | C171: 2800 | F171: 0001-20600
A172: 0001-20700 | B172: 中間軸 | C172: 4300 | F172: 0001-20700
A173: 0001-20800 | B173: 中間軸ｷﾞﾔ27T | C173: 3300 | F173: 0001-20800
...

Sheet 請求先
A1: 請求先コード | B1: 請求先名（漢字） | C1: 請求先名（カナ） | D1: 掛け率 | E1: 掛け率 | F1: 掛け率 | I1: データ引用2021/9/8
A2: 61102 | B2: バロネス関東株式会社 | C2: ﾊﾞﾛﾈｽｶﾝﾄｳ | D2: 0.67 | E2: ％ | F2: ALL67%
A3: 61103 | B3: 東興産業（株） | C3: ﾄｳｺｳｻﾝｷﾞﾖｳ | D3: 0.63 | E3: ％ | F3: ALL63%
A4: 61105 | B4: 伊藤産業機械㈱ | C4: ｲﾄｳｻﾝｷﾞﾖｳｷｶｲ | D4: 0.67 | E4: ％ | F4: ALL67%
A5: 61106 | B5: ＭＳＫ東急機械㈱ 千葉事業所 | C5: ｴﾑｴｽｹｲﾄｳｷﾕｳｷｶｲ ﾁﾊﾞ | D5: 0.65 | E5: ％ | F5: ALL65%
A6: 61107 | B6: ㈱佐々木商会 | C6: ｻｻｷｼﾖｳｶｲ | D6: 0.67 | E6: ％ | F6: ALL67%
A7: 61108 | B7: 杉木鉄工㈱ | C7: ｽｷﾞｷﾃﾂｺｳ | D7: 0.67 | E7: ％ | F7: ALL67%
A8: 61110 | B8: ㈱関東甲信クボタ（千葉県） | C8: ｶﾝﾄｳｺｳｼﾝｸﾎﾞﾀ ﾁﾊﾞｹﾝ | D8: 0.65 | E8: ％ | F8: ALL65% | G8: 直扱い | H8: 実演機
A9: 61111 | B9: 株式会社 中屋商会 | C9: ﾅｶﾔｼﾖｳｶｲ | D9: 0.7 | E9: ％ | F9: ALL70%
A10: 61112 | B10: 株式会社 中村産業 | C10: ﾅｶﾑﾗｻﾝｷﾞﾖｳ | D10: 0.67 | E10: ％ | F10: ALL67%
A11: 61113 | B11: 有限会社 双葉工機 | C11: ﾌﾀﾊﾞｺｳｷ | D11: 0.67 | E11: ％ | F11: ALL67%
A12: 61115 | B12: 茨城菱農株式会社 | C12: ｲﾊﾞﾗｷﾘﾖｳﾉｳ | D12: 0.67 | E12: ％ | F12: ALL67%
A13: 61116 | B13: ㈱関東甲信クボタ（茨城県） | C13: ｶﾝﾄｳｺｳｼﾝｸﾎﾞﾀ ｲﾊﾞﾗｷｹﾝ | D13: 0.65 | E13: ％ | F13: ALL65%
A14: 61117 | B14: 大川機械 | C14: ｵｵｶﾜｷｶｲ | D14: 0.7 | E14: ％ | F14: ALL70%
A15: 61118 | B15: 三菱農機販売(株) 茨城支店 | C15: ﾐﾂﾋﾞｼﾉｳｷﾊﾝﾊﾞｲｲﾊﾞﾗｷｼﾃﾝ | D15: 0.65 | E15: ％ | F15: ALL65%
A16: 61121 | B16: ㈱クボタ 茨城県営業担当 | C16: ｸﾎﾞﾀ ｲﾊﾞﾗｷｹﾝｴｲｷﾞﾖｳﾀﾝﾄｳ | D16: 0.63 | E16: ％ | F16: ALL63%
A17: 61122 | B17: 成田加藤農機㈲ | C17: ﾅﾘﾀｶﾄｳﾉｳｷ | D17: 0.7 | E17: ％ | F17: ALL70%
A18: 61123 | B18: ㈱クボタ 栃木営業担当 | C18: ｸﾎﾞﾀ ﾄﾁｷﾞｴｲｷﾞﾖｳﾀﾝﾄｳ | D18: 0.63 | E18: ％ | F18: ALL63%
A19: 61124 | B19: ㈲根本商会 | C19: ﾈﾓﾄｼﾖｳｶｲ | D19: 0.7 | E19: ％ | F19: ALL70%
A20: 61125 | B20: マルテン産業機械㈱ | C20: ﾏﾙﾃﾝｻﾝｷﾞﾖｳｷｶｲ | D20: 0.7 | E20: ％ | F20: ALL70%
... A26: 61136 | B26: ㈱シバタ | C26: ｼﾊﾞﾀ | D26: 0.65 | E26: ％ | F26: ALL65%
A27: 61140 | B27: ㈱マキタＯＥＭ調達１Ｇ | C27: ﾏｷﾀ ｵｰｲｰｴﾑﾁﾖｳﾀﾂﾀﾞｲｲﾁｸﾞﾙｰﾌﾟ | E27: ％ | F27: 65-65-65-60-65
A28: 61301 | B28: カナエ産業 ㈱ | C28: ｶﾅｴｻﾝｷﾞﾖｳ | D28: 0.7 | E28: ％ | F28: ALL70%
A29: 61304 | B29: 八丈商事 | C29: ﾊﾁｼﾞﾖｳｼﾖｳｼﾞ | D29: 0.7 | E29: ％ | F29: ALL70%
A30: 61305 | B30: ㈱石井電機商店 | C30: ｲｼｲﾃﾞﾝｷｼﾖｳﾃﾝ | D30: 0.67 | E30: ％ | F30: ALL67%
A31: 61306 | B31: ㈲井合農機店 | C31: ｲｺﾞｳﾉｷﾃﾝ | D31: 0.7 | E31: ％ | F31: ALL70%
A32: 61307 | B32: 石井鉄工 株式会社 | C32: ｲｼｲﾃﾂｺｳ | D32: 0.7 | E32: ％ | F32: ALL70%
A33: 61308 | B33: ㈲井上農機商会 | C33: ｲﾉｳｴﾉｳｷｼﾖｳｶｲ | D33: 0.7 | E33: ％ | F33: ALL70%
A34: 61310 | B34: 有限会社 木嶋商店 | C34: ｷｼﾞﾏｼﾖｳﾃﾝ | D34: 0.7 | E34: ％ | F34: ALL70%
A35: 61311 | B35: 笹曽根農機 | C35: ｻｻｿﾈﾉｳｷ | D35: 0.7 | E35: ％ | F35: ALL70%
A36: 61312 | B36: 深沢農機商会 | C36: ﾌｶｻﾞﾜﾉｳｷｼﾖｳｶｲ | D36: 0.7 | E36: ％ | F36: ALL70%
A37: 61313 | B37: ㈲鈴木農機 | C37: ｽｽﾞｷﾉｳｷ | D37: 0.7 | E37: ％ | F37: ALL70%
A38: 61315 | B38: ㈲高橋機械 | C38: ﾀｶﾊｼｷｶｲ | D38: 0.7 | E38: ％ | F38: ALL70%
A39: 61317 | B39: ㈲光港屋商会 | C39: ﾋｶﾘﾐﾅﾄﾔｼﾖｳｶｲ | D39: 0.67 | E39: ％ | F39: ALL67%
... A73: 61360 | B73: ㈲染井金物店 | C73: ｿﾒｲｶﾅﾓﾉﾃﾝ | D73: 0.7 | E73: ％ | F73: ALL70%
A74: 61361 | B74: ㈱クボタ 神奈川県営業担当 | C74: ｸﾎﾞﾀ ｶﾅｶﾞﾜｹﾈｲｷﾞﾖｳﾀﾝﾄｳ | E74: ％ | F74: ALL63%十円未満四捨五入
A75: 61362 | B75: ㈲秋山農機 | C75: ｱｷﾔﾏﾉｳｷ | D75: 0.7 | E75: ％ | F75: ALL70%
A76: 61368 | B76: ㈲三和商会 | C76: ﾐﾂﾜｼﾖｳｶｲ | D76: 0.7 | E76: ％ | F76: ALL70%
A77: 61371 | B77: 山利産業㈱ | C77: ﾔﾏﾘｻﾝｷﾞﾖｳ | D77: 0.7 | E77: ％ | F77: ALL70%
A78: 61373 | B78: ㈱クボタ 千葉県営業担当 | C78: ｸﾎﾞﾀ ﾁﾊﾞｹﾝｴｲｷﾞﾖｳﾀﾝﾄｳ | D78: 0.63 | E78: ％ | F78: ALL63%十円未満四捨五入
A79: 61374 | B79: ㈲アダチ | C79: ｱﾀﾞﾁ | D79: 0.7 | E79: ％ | F79: ALL70%
A80: 61375 | B80: ㈲カツヤマ | C80: ｶﾂﾔﾏ | E80: ％ | F80: 68-68-//-//-//
A81: 61376 | B81: 有限会社 良栄社商会 | C81: ﾘﾖｳｴｲｼﾔｼﾖｳｶｲ | D81: 0.68 | E81: ％ | F81: ALL68%
A82: 61377 | B82: 千葉県農業機械商業協同組合 | C82: ｺﾐﾔﾉｳｻﾝｷｼﾖｳｶｲ | D82: 0.67 | E82: ％ | F82: ALL67%
A83: 63102 | B83: 三菱農機販売（株）関東甲信越支社 | C83: ﾐﾂﾋﾞｼﾉｳｷﾊﾝﾊﾞｲｶﾝﾄｳｺｳｼﾝｴﾂｼｼｬ | D83: 0.65 | E83: ％ | F83: ALL65%
A84: 63103 | B84: ㈱関東甲信クボタ（栃木県） | C84: ｶﾝﾄｳｺｳｼﾝｸﾎﾞﾀ ﾄﾁｷﾞｹﾝ | D84: 0.65 | E84: ％ | F84: ALL65%
A85: 63105 | B85: 三菱農機販売(株) 栃木支店 | C85: ﾐﾂﾋﾞｼﾉｳｷ | D85: 0.65 | E85: ％ | F85: ALL65%
A86: 63112 | B86: 高田酪農機株式会社 | C86: ﾀｶﾀﾞﾗｸﾉｳ | D86: 0.7 | E86: ％ | F86: ALL70%
A87: 63304 | B87: 株式会社鈴木屋商店 | C87: ｽｽﾞｷﾔｼｮｳﾃﾝ | D87: 0.7 | E87: ％ | F87: ALL70%
A88: 63307 | B88: 有限会社 斎藤農機商会 | C88: ｻｲﾄｳﾉｳｷｼﾖｳｶｲ | D88: 0.7 | E88: ％ | F88: ALL70%
A89: 63308 | B89: 有限会社 川又商会 | C89: ｶﾜﾏﾀｼﾖｳｶｲ | D89: 0.7 | E89: ％ | F89: ALL70%
A90: 63318 | B90: 渡辺機械サービス | C90: ﾜﾀﾅﾍﾞｷｶｲｻｰﾋﾞｽ | D90: 0.7 | E90: ％ | F90: ALL70%
A91: 63319 | B91: ㈲佐瀬農機具店 | C91: ｻｾﾉｳｷｸﾞﾃﾝ | D91: 0.7 | E91: ％ | F91: ALL70%
A92: 63320 | B92: 有限会社 植木農機商会 | C92: ｳｴｷﾉｳｷｼﾖｳｶｲ | D92: 0.7 | E92: ％ | F92: ALL70%
... A116: 64120 | B116: （株）関東甲信クボタ 埼玉県 | C116: ｶﾝﾄｳｺｳｼﾝｸﾎﾞﾀ ｻｲﾀﾏｹﾝ | D116: 0.65 | E116: ％ | F116: ALL65%
A117: 64121 | B117: 丸山物流㈱東北センター | C117: ﾏﾙﾔﾏﾌﾞﾂﾘｭｳ ﾄｳﾎｸｾﾝﾀｰ | E117: ％ | F117: 75-75-75-60-75
A118: 64122 | B118: ㈱グラケン | C118: ｸﾞﾗｹﾝ | D118: 0.67 | E118: ％ | F118: ALL67%
A119: 64123 | B119: ㈱岡山農栄社 関東営業所 | C119: ｵｶﾔﾏﾉｳｴｲｼﾔ ｶﾝﾄｳｴｲｷﾞﾖｳｼ | E119: ％ | F119: 65-65-65-60-65
A120: 64125 | B120: エム・エス・ケー農業機械㈱東日本支店 | C120: ｴﾑ･ｴｽ･ｹｰﾉｳｷﾞﾖｳｷｶｲ | D120: 0.67 | E120: ％ | F120: ALL67%
A121: 64131 | B121: （株）ササクボ農機店 | C121: ｻｻｸﾎﾞﾉｳｷﾃﾝ | D121: 0.7 | E121: ％ | F121: ALL70%
A122: 64132 | B122: コマツカスタマーサポート株式会社 東京関越カンパニー北本支店 | C122: ｺﾏﾂｶｽﾀﾏｰｻﾎﾟｰﾄ ﾄｳｷｮｳｶﾝｴﾂｶﾝﾊﾟﾆｰｷﾀﾓﾄｼﾃﾝ | D122: 0.67 | E122: ％ | F122: ALL67%
A123: 64133 | B123: 三幸フォークリフト㈱ | C123: ｻﾝｺｳﾌｵｰｸﾘﾌﾄ | D123: 0.7 | E123: ％ | F123: ALL70%
A124: 64134 | B124: コマツカスタマーサポート株式会社 東京関越カンパニー群馬支店 | C124: ｺﾏﾂｶｽﾀﾏｰｻﾎﾟｰﾄ ﾄｳｷｮｳｶﾝｴﾂｶﾝﾊﾟﾆｰｸﾞﾝﾏｼﾃﾝ | D124: 0.67 | E124: ％ | F124: ALL67%
A125: 64200 | B125: ㈱クボタ 部品営業推進部 営業推進ｸﾞﾙｰﾌﾟ | C125: ｸﾎﾞﾀ ﾌﾞﾋﾝｴｲｷﾞﾖｳｽｲｼﾝﾌﾞｴｲｷﾞｮｳｽｲｼﾝｸﾞﾙｰﾌﾟ | E125: ％ | F125: ALL65%十円未満四捨五入
A126: 64201 | B126: ㈱中農機商会 | C126: ﾅｶﾉｳｷｼﾖｳｶｲ | D126: 0.68 | E126: ％ | F126: ALL68%
A127: 64202 | B127: 群馬県農業機械商業協同組合 | C127: ｸﾞﾝﾏｹﾝﾉｳｷﾞﾖｳｷｶｲｼﾖｳｷﾞﾖｳｷﾖｳﾄﾞｳｸﾐｱｲ | D127: 0.67 | E127: ％ | F127: ALL67%
A128: 64303 | B128: 関東農機商会 | C128: ｶﾝﾄｳﾉｳｷｼﾖｳｶｲ | D128: 0.67 | E128: ％ | F128: ALL67%
A129: 64304 | B129: （有）群馬農機商会 | C129: ｸﾞﾝﾏﾉｳｷｼﾖｳｶｲ | D129: 0.7 | E129: ％ | F129: ALL70%
A130: 64305 | B130: 群馬ヰセキ販売㈱ | C130: ｸﾞﾝﾏｲｾｷﾊﾝﾊﾞｲ | D130: 0.7 | E130: ％ | F130: ALL70%
A131: 64306 | B131: ㈲群商農機 | C131: ｸﾞﾝｼﾖｳﾉｳｷ | D131: 0.7 | E131: ％ | F131: ALL70%
A132: 64307 | B132: ㈲ケーオー商会 | C132: ｹｰｵｰﾉｳｷｼﾖｳｶｲ ｶﾝﾄｳ | D132: 0.7 | E132: ％ | F132: ALL70%
A133: 64308 | B133: （有）館林農機パレス | C133: ﾀﾃﾊﾞﾔｼﾉｳｷﾊﾟﾚｽ | D133: 0.7 | E133: ％ | F133: ALL70%
A134: 64309 | B134: ㈲トーショウ機械販売 | C134: ﾄｰｼﾖｳｷｶｲﾊﾝﾊﾞｲ | D134: 0.67 | E134: ％ | F134: ALL67%
A135: 64310 | B135: 中沢商事（株） | C135: ﾅｶｻﾞﾜｼﾖｳｼﾞ | D135: 0.7 | E135: ％ | F135: ALL70%
A136: 64311 | B136: 山本農機販売㈱ | C136: ﾔﾏﾓﾄﾉｳｷﾊﾝﾊﾞｲ | D136: 0.7 | E136: ％ | F136: ALL70%
A137: 64312 | B137: 吉田農機商会 | C137: ﾖｼﾀﾞﾉｳｷｼﾖｳｶｲ | D137: 0.7 | E137: ％ | F137: ALL70%
... A166: 64359 | B166: 細田農機（株） | C166: ﾎｿﾀﾞﾉｳｷ | D166: 0.7 | E166: ％ | F166: ALL70%
A167: 64360 | B167: （有）シミズ | C167: ｼﾐｽﾞ | E167: ％ | F167: 70-70-70-65-65
A168: 64362 | B168: 野口機械 | C168: ﾉｸﾞﾁｷｶｲ | D168: 0.7 | E168: ％ | F168: ALL70%
A169: 64366 | B169: アオキ種苗㈱ | C169: ｱｵｷｼﾕﾋﾞﾖｳ | D169: 0.7 | E169: ％ | F169: ALL70%
A170: 64368 | B170: ㈲吉田農機 | C170: ﾖｼﾀﾞﾉｳｷ | D170: 0.7 | E170: ％ | F170: ALL70%
A171: 64369 | B171: ㈱ホソダ | C171: ﾎｿﾀﾞ | D171: 0.67 | E171: ％ | F171: ALL67%
A172: 64370 | B172: サクラ産業㈱ | C172: ｻｸﾗｻﾝｷﾞﾖｳ | D172: 0.67 | E172: ％ | F172: ALL67%
A173: 64371 | B173: 和光貿易㈱ | C173: ﾜｺｳﾎﾞｳｴｷ | D173: 0.67 | E173: ％ | F173: ALL67%
A174: 64372 | B174: たじま農機 | C174: ﾀｼﾞﾏﾉｳｷ | D174: 0.7 | E174: ％ | F174: ALL70%
A175: 64375 | B175: 生研機構 | C175: ｾｲｹﾝｷｺｳ | D175: 0.8 | E175: ％ | F175: ALL80%
A176: 64376 | B176: ㈱シバタ 幸手工場 | C176: ｼﾊﾞﾀ ｻﾂﾃｺｳｼﾞﾖｳ | D176: 0.65 | E176: ％ | F176: ALL65%
A177: 64377 | B177: 中川機工（株） | C177: ﾅｶｶﾞﾜｷｺｳ | D177: 0.67 | E177: ％ | F177: ALL67%
A178: 64379 | B178: （株）広洋エンジニアリング | C178: ｺｳﾖｳｴﾝｼﾞﾆｱﾘﾝｸﾞ | D178: 0.67 | E178: ％ | F178: ALL67%
A179: 64380 | B179: ㈱クボタ 埼玉県営業担当 | C179: ｸﾎﾞﾀ ｻｲﾀﾏｹﾝｴｲｷﾞﾖｳﾀﾝﾄｳ | E179: ％ | F179: ALL63%十円未満四捨五入
A180: 64381 | B180: ㈲明升堂 | C180: ﾒｲｼﾖｳﾄﾞｳ | D180: 0.7 | E180: ％ | F180: ALL70%
A181: 64382 | B181: 佐藤農機 | C181: ｻﾄｳﾉｳｷ | D181: 0.7 | E181: ％ | F181: ALL70%
A182: 64383 | B182: ㈱ＩＨＩシバウラ | C182: ｱｲｴﾂﾁｱｲｼﾊﾞｳﾗ | E182: ％ | F182: 65-65-//-//-//
A183: 64384 | B183: （株）シバタ Ｈ・Ｃ事業部 | C183: ｼﾊﾞﾀ ﾎｰﾑｾﾝﾀｰｼﾞｷﾞﾖｳﾌﾞ | D183: 0.65 | E183: ％ | F183: ALL65%
A184: 64391 | B184: （株）関東甲信クボタ（群馬県） | C184: ｶﾝﾄｳｺｳｼﾝｸﾎﾞﾀ ｸﾞﾝﾏｹﾝ | D184: 0.65 | E184: ％ | F184: ALL65%
A185: 64444 | B185: 三菱ﾏﾋﾝﾄﾞﾗ農機㈱国内営業統括部A/Sｾﾝﾀｰ | C185: ﾐﾂﾋﾞｼﾏﾋﾝﾄﾞﾗﾉｳｷ ｺｸﾅｲｴｲｷﾞﾖｳ | D185: 0.65 | E185: ％ | F185: ALL65%
A186: 64445 | B186: 三菱マヒンドラ農機㈱ 提携作業機グループ | C186: ﾐﾂﾋﾞｼﾏﾋﾝﾄﾞﾗﾉｳｷ | E186: ％
A187: 65130 | B187: （株）相武機械 | C187: ｿｳﾌﾞｷｶｲ | D187: 0.72 | E187: ％ | F187: ALL72%
A188: 65131 | B188: ㈲森長 | C188: ﾓﾘﾁﾖｳ | D188: 0.7 | E188: ％ | F188: ALL70%
A189: 65132 | B189: （株）関東甲信クボタ（神奈川県） | C189: ｶﾝﾄｳｺｳｼﾝｸﾎﾞﾀ ｶﾅｶﾞﾜｹﾝ | D189: 0.65 | E189: ％ | F189: ALL65%
...

Sheet 出荷先
A1: 納入先コード | B1: 納入先カナ名 | C1: 納入先正式名 | D1: 郵便番号1 | E1: 住所1 | F1: 電話番号1-1 | I1: データ引用2022/04/25
A2: 61102 | B2: ﾆﾎﾝｸﾘﾝﾄﾝ | C2: 日本クリントン㈱ | D2: 121-0836 | E2: 東京都 足立区 入谷5-7-8 | F2: 03-3854-8221
A3: 61103 | B3: ﾄｳｺｳｻﾝｷﾞｮｳ | C3: 東興産業㈱ | D3: 350-0821 | E3: 埼玉県 川越市 福田239 | F3: 0492-23-1217
A4: 61105 | B4: ｲﾄｳｻﾝｷﾞｮｳｷｶｲ | C4: 伊藤産業機械㈱ | D4: 290-0034 | E4: 千葉県 市原市 島野1978 | F4: 0436-22-1743
A5: 61106 | B5: ｴﾑｴｽｹｰﾉｳｷﾞｮｳｷｶｲﾁﾊﾞｼﾞｷﾞｮｳｼｮ | C5: MSK東急機械㈱ 千葉事業所 | D5: 290-0012 | E5: 千葉県 市原市 藤井3-310 | F5: 0436-41-1069
A6: 61107 | B6: ｻｻｷｼｮｳｶｲ | C6: ㈱佐々木商会 | D6: 294-0037 | E6: 千葉県 館山市 長須賀123 | F6: 0470-22-1166
A7: 61108 | B7: ｽｷﾞｷﾃｯｺｳ | C7: 杉木鉄工㈱ | D7: 297-0029 | E7: 千葉県 茂原市 高師1536 | F7: 0475-22-4587
A8: 61109 | B8: ﾀｶﾉｻﾝｷﾞｮｳ | C8: 高野産業㈱ | D8: 292-0054 | E8: 千葉県 木更津市 長須賀924-1 | F8: 0438-22-6251
A9: 61110 | B9: ｶﾝﾄｳｺｼﾝｸﾎﾞﾀﾁﾊﾞｼﾞｷﾞｮｳﾌﾞ | C9: ㈱関東甲信クボタ 南関東事業所 | D9: 260-0808 | E9: 千葉県 千葉市 中央区 星久喜町176-4 | F9: 043-261-3131
A10: 61111 | B10: ﾅｶﾔｼｮｳｶｲ | C10: ㈱中屋商会 | D10: 289-2146 | E10: 千葉県 匝瑳市 八日市場ホ452 | F10: 0479-72-1161
A11: 61112 | B11: ﾅｶﾑﾗｻﾝｷﾞｮｳ | C11: ㈱中村産業 | D11: 283-0811 | E11: 千葉県 東金市 台方246 | F11: 0475-52-2615
A12: 61113 | B12: ﾌﾀﾊﾞｺｳｷ | C12: ㈲双葉工機 | D12: 270-2222 | E12: 千葉県 松戸市 高塚新田340-11 | F12: 0473-92-7256
A13: 61114 | B13: ﾓﾊﾞﾗﾌｺｸｼｬ | C13: ㈱茂原富国社 | D13: 297-0029 | E13: 千葉県 茂原市 高師1671 | F13: 0475-25-0325
... A95: 61376 | B95: ﾘｮｳｴｲｼｬ | C95: ㈲良栄社商会 | D95: 299-1151 | E95: 千葉県 君津市 中野4-15-18 | F95: 0439-52-0035
B96: ｺｼﾞﾝｷｬｸ | C96: 個人客
A97: 61400 | B97: ｺﾐﾔﾉｳｻﾝｷｼｮｳｶｲ | C97: ㈲古宮農蚕機商会 | D97: 192-0051 | E97: 東京都 八王子市 元本郷町1-5-5 | F97: 042-625-2328
A98: 63102 | B98: ﾐﾂﾋﾞｼﾉｳｷﾊﾝﾊﾞｲｶﾝﾄｳｺｳｼﾝｴﾂ | C98: 三菱農機販売㈱ 関東甲信越支店 | D98: 340-0203 | E98: 埼玉県 久喜市 桜田2-133-4 | F98: 0480-58-9521
A99: 63103 | B99: ｶﾝﾄｳｺｳｼﾝｸﾎﾞﾀｸﾎﾞﾀﾄﾁｷﾞｼﾞﾑｼｮ | C99: ㈱関東甲信クボタ 北関東事業所 （栃木） | D99: 321-0905 | E99: 栃木県 宇都宮市 平出工業団地28-2 | F99: 0286-89-2341
A100: 63105 | B100: ﾐﾂﾋﾞｼﾉｳｷﾊﾝﾊﾞｲﾄﾁｷﾞｼﾃﾝ | C100: 三菱農機販売㈱ 栃木支店 | D100: 329-1233 | E100: 栃木県 塩谷郡 高根沢町 宝積寺 中2248-60 | F100: 0286-75-7321
A101: 63112 | B101: ﾀｶﾀﾞﾗｸﾉｳｷ | C101: 高田酪農機㈱ | D101: 321-3236 | E101: 栃木県 宇都宮市 竹下町1101-11 | F101: 028-667-2825
A102: 63301 | B102: ｺﾋﾞｷﾉｳｷｸﾞﾃﾝ | C102: 小比企農機具店 | D102: 326-0845 | E102: 栃木県 足利市 大前町207 | F102: 0284-62-2065
A103: 63302 | B103: ﾇﾉｶﾜﾉｳｷｸﾞﾃﾝ | C103: 布川農機具店 | D103: 329-4404 | E103: 栃木県 栃木市 大平町富田1430 | F103: 0282-43-2013
A104: 63303 | B104: ｽﾅｶﾉｳｷｸﾞﾃﾝ | C104: 砂川農機具店 | D104: 326-0323 | E104: 栃木県 足利市 瑞穂野町495 | F104: 0284-71-9033
A105: 63304 | B105: ｽｽﾞｷﾔ | C105: ㈱鈴木屋 | D105: 329-0205 | E105: 栃木県 小山市 間々田1290 | F105: 0285-45-0070
A106: 63305 | B106: ｶﾜﾀ | C106: ㈱川田 | D106: 322-0002 | E106: 栃木県 鹿沼市 千渡2315-66 | F106: 0289-65-3366
A107: 63306 | B107: ｺﾀﾞｲﾗﾉｳｷｼｮｳｶｲ | C107: 小平農機商会 | D107: 321-1261 | E107: 栃木県 日光市 今市107-22 | F107: 0288-21-0845
A108: 63307 | B108: ｻｲﾄｳﾉｳｷｼｮｳｶｲ | C108: ㈲斉藤農機商会 | D108: 329-2161 | E108: 栃木県 矢板市 扇町1-11-19 | F108: 0287-43-0475
... A206: 64391 | B206: ｶﾝﾄｳｺｳｼﾝｸﾎﾞﾀｸﾞﾝﾏｼﾞﾑｼｮ | C206: ㈱関東甲信クボタ 群馬事務所 | D206: 379-2154 | E206: 群馬県 前橋市 天川大島町1364-1 | F206: 027-261-6010
A207: 64398 | B207: ｶﾝﾄｳｹﾞﾝｷﾝｷｬｸ | C207: 関東現金客
A208: 64399 | B208: ｺｼﾞﾝｷｬｸ | C208: 個人客
A209: 64444 | B209: ﾐﾂﾋﾞｼﾉｳｷﾋｶﾞｼﾆﾎﾝﾌﾞﾋﾝｷｶﾝｾﾝﾀｰ | C209: 三菱農機㈱ 東日本部品基幹センター | D209: 340-0203 | E209: 埼玉県 久喜市 桜田2-133-4 | F209: 0480-58-9515
A210: 64445 | B210: ﾐﾂﾋﾞｼﾉｳｷ | C210: 三菱ﾏﾋﾝﾄﾞﾗ農機㈱ 島根県 | D210: 699-0101 | E210: 島根県 松江市 東出雲町 揖屋667-1 | F210: 0852-52-2111
A211: 65130 | B211: ｿｳﾌﾞｷｶｲ | C211: ㈱相武機械 | D211: 215-0003 | E211: 神奈川県 川崎市 麻生区 高石3-31-27 | F211: 044-966-4161
A212: 65131 | B212: ﾓﾘﾁｮｳ | C212: 森長 | D212: 254-0041 | E212: 神奈川県 平塚市 浅間町5-27 | F212: 0463-31-2195
A213: 65132 | B213: ｶﾝﾄｳｺｼﾝｸﾎﾞﾀｾｲｼﾝｼﾞｷﾞｮｳﾌﾞ | C213: ㈱関東甲信クボタ 静神事業部 | D213: 411-0817 | E213: 静岡県 三島市 八反畑 字鶴田100 | F213: 055-972-0800
A214: 65137 | B214: ｴﾙﾀ | C214: ㈱エルタ | D214: 190-1221 | E214: 東京都 西多摩郡 瑞穂町 箱根ケ崎 東松原20-1 | F214: 0425-56-0184
A215: 65323 | B215: ｵｵﾀｹﾉｳｷ | C215: 大竹農機㈱ | D215: 289-1115 | E215: 千葉県 八街市 八街ほ244 | F215: 043-444-0225
A216: 65347 | B216: ｶﾓｼﾀﾞｼｮｳｶｲ | C216: 鴨志田商会 | D216: 226-0000 | E216: 神奈川県 横浜市 緑区 川和町1437 | F216: 045-931-1038
A217: 65348 | B217: ｷｼﾀﾞﾉｳｷｼｮｳｶｲ | C217: ㈱岸田農機商会 | D217: 259-1131 | E217: 神奈川県 伊勢原市 伊勢原1-7-18 | F217: 0463-95-0121
A218: 65350 | B218: ｻｶﾞﾐﾉｳｷ | C218: さがみ農機 | D218: 258-0001 | E218: 神奈川県 足柄上郡 松田町 寄5501 | F218: 0465-89-2329
A219: 65351 | B219: ｽｽﾞﾉﾉｳｷ | C219: ㈲鈴野農機 | D219: 252-0826 | E219: 神奈川県 藤沢市 宮原1348 | F219: 0466-48-1048
A220: 65352 | B220: ﾀﾅｶﾉｳｷｼｮｳｶｲ | C220: 田中農機商会 | D220: 252-0807 | E220: 神奈川県 藤沢市 下土棚444 | F220: 0466-44-2005
... A244: 2133075 | B244: ﾂｸﾊﾞｼｻｸﾗﾉｳｷｾﾝﾀｰ | C244: JAつくば市 桜農機センター | D244: 305-0027 | E244: 茨城県 つくば市 東岡335 | F244: 029-857-3116
A245: 2133107 | C245: JA常陸 みなみ農機センター | D245: 319-1234 | E245: 茨城県 日立市 大和田町1992 | F245: 0294-53-2121
A246: 2133110 | B246: ﾏｼｰﾈｵﾐﾀﾏ | C246: JAマシーネ 小美玉 | D246: 311-3412 | E246: 茨城県 小美玉市 川戸1450-58 | F246: 0299-58-5644
A247: 2133115 | B247: ﾐﾄﾉｳｷｮｳﾐﾄﾉｳｷｾﾝﾀｰ | C247: JA水戸農協 水戸農機センター | D247: 311-4141 | E247: 茨城県 水戸市 赤塚2-27 | F247: 029-252-2076
A248: 2133147 | B248: ﾅﾒｶﾞﾀﾉｳｷﾈﾝﾘｮｳ | C248: JAなめがた農機燃料㈱ 南部農機センター | D248: 311-3835 | E248: 茨城県 行方市 島並857-16 | F248: 0299-72-1651
A249: 2134054 | B249: ｸﾏｶﾞﾔｸﾏｶﾞﾔﾉｳｷｾﾝﾀｰ | C249: JAくまがや 熊谷農機センター | D249: 360-0805 | E249: 埼玉県 熊谷市 上奈良1079-1 | F249: 048-523-9291
A250: 2134057 | B250: ｸﾏｶﾞﾔｺｳﾅﾝﾉｳｷｾﾝﾀｰ | C250: JAくまがや 江南農機センター | D250: 360-0115 | E250: 埼玉県 熊谷市 成沢490-1 | F250: 048-536-1404
A251: 2134071 | B251: ｲﾙﾏﾉﾎｸﾌﾞﾉｳｷｾﾝﾀｰ | C251: JAいるま野 北部農機センター | D251: 350-0212 | E251: 埼玉県 坂戸市 石井1880 | F251: 049-289-2172
A252: 2134072 | B252: ｻｲﾀﾏｻｼｵｳｷﾞｼﾃﾝ | C252: JAさいたま 指扇支店 | D252: 331-0071 | E252: 埼玉県 さいたま市 西区 高木337-3 | F252: 048-623-5011
A253: 2134091 | B253: ｲﾙﾏﾉﾄｺﾛｻﾞﾜﾉｳｷｾﾝﾀｰ | C253: JAいるま野 所沢農機センター | D253: 359-0001 | E253: 埼玉県 所沢市 下富627-10 | F253: 042-942-3467
A254: 2134092 | C254: JAちちぶ農協秩父自動車センター | D254: 368-0056 | E254: 埼玉県 秩父市 寺尾3218-1 | F254: 0494-25-2555
A255: 2134107 | B255: ｻｲﾀﾏﾁｭｳｵｳﾋｶﾞｼﾏﾂﾔﾏﾉｳｷｾﾝﾀｰ | C255: JA埼玉中央 東松山農機センター | D255: 355-0073 | E255: 埼玉県 東松山市 上野本1405-1 | F255: 0493-24-3159
A256: 2135169 | B256: ｷﾐﾂ | C256: JAきみつ 平川農機整備工場 | D256: 299-0205 | E256: 千葉県 袖ヶ浦市 上泉366 | F256: 0438-75-4007
A257: 2135181 | B257: ﾁｮｳｾｲﾉｳｷｮｳ | C257: JA長生農協 睦沢農機センター | D257: 299-4403 | E257: 千葉県 長生郡 睦沢町 上市場914 | F257: 0475-44-1236
A258: 2135187 | B258: ｷﾐﾂ | C258: JAきみつ 天羽農機整備工場 | D258: 299-1618 | E258: 千葉県 富津市 花輪150 | F258: 0439-80-7650
A259: 2135190 | B259: ｲﾁﾊﾗｼﾉｳｷｾﾝﾀｰ | C259: JA市原市 農機センター | D259: 290-0225 | E259: 千葉県 市原市 牛久573-1 | F259: 0436-92-5650
A260: 2135192 | B260: ｱﾜﾉｳｷｮｳｳﾁﾎﾞｳﾉｳｷｾﾝﾀｰ | C260: JA安房農協 内房農機ｾﾝﾀｰ | D260: 294-0813 | E260: 千葉県 南房総市 谷向56 | F260: 0470-36-4070
A261: 2135198 | C261: JA君津市農業協同組合上総農機 SS | D261: 292-0503 | E261: 千葉県 君津市 広岡1771 | F261: 0439-29-2080
A262: 2135221 | B262: ﾆｼﾝﾊﾞﾉｳｷﾖｳｾｲｶﾂﾌﾞ | C262: JA西印旛農協 生活部 機械課 | D262: 270-1337 | E262: 千葉県 印西市 草深1230 | F262: 0476-47-3133
A263: 2135223 | B263: ｷｻﾗﾂﾞｼﾉｳｷﾞｮｳｷｮｳﾄﾞｳ | C263: JA木更津市農業協同組合 中郷農機事業 ｾﾝﾀｰ | D263: 292-0026 | E263: 千葉県 木更津市 井尻525-1 | F263: 0438-98-0279
A264: 2135424 | B264: ﾄﾐｻﾄｼﾉｳｷｾﾝﾀｰ | C264: JA富里市農機センター | D264: 286-0212 | E264: 千葉県 富里市 十倉431-1 | F264: 0476-93-8683
A265: 2135424 | B265: ﾄﾐｻﾄｼﾉｳｷﾞｮｳｷｮｳﾄﾞｳｾﾝﾀｰ | C265: JA富里市 農業共同センター | D265: 286-0212 | E265: 千葉県 富里市 十倉431-1 | F265: 0476-93-8683
A266: 2135424 | B266: ﾄﾐｻﾄｼﾉｳｷﾞｮｳｷｮｳﾄﾞｳｾﾝﾀｰ | C266: JA富里市 農機共同センター
A267: 2135428 | B267: ｷﾐﾂｿｳｺﾞｳｷｶｲｾﾝﾀｰ | C267: JA君津総合機械センター | D267: 299-1104 | E267: 千葉県 君津市 糠田169 | F267: 0439-32-5081
A268: 2135542 | B268: ﾁﾊﾞﾐﾄﾞﾘﾉｳｷｾﾝﾀｰ | C268: JAちばみどり 農機センター | D268: 289-2503 | E268: 千葉県 旭市 江ヶ崎661 | F268: 0479-63-7009
A269: 2136069 | B269: ﾄｳｷｮｳﾐﾗｲ | C269: JA東京みらい 農機センター | D269: 189-0014 | E269: 東京都 東村山市 本町1-16-5 | F269: 0423-93-5211
A270: 2136073 | B270: ﾏﾁﾀﾞｼﾉｳｷｮｳﾉｳｷｾﾝﾀｰ | C270: JA町田市農協 農機センター | D270: 194-0035 | E270: 東京都 町田市 忠生1-29-4 | F270: 042-792-2811
A271: 2137003 | B271: ｹﾝｵｳｱｲｶﾜｹｲｻﾞｲｾﾝﾀｰ | C271: JA県央愛川経済センター | D271: 243-0308 | E271: 神奈川県 愛甲郡 愛川町 三増891 | F271: 0462-81-5000
A272: 2137004 | B272: ｻｶﾞﾐﾉｳｷｮｳｱﾔｾｴｲﾉｳｹｲｻﾞｲ | C272: JAさがみ農協 綾瀬営農経済 | D272: 252-1103 | E272: 神奈川県 綾瀬市 深谷3333 | F272: 0467-78-0521
A273: 2137008 | B273: ｻｶﾞﾐﾉｳｷｮｳｴﾋﾞﾅ | C273: JAさがみ農協 海老名営農センター | D273: 243-0411 | E273: 神奈川県 海老名市 大谷240 | F273: 046-234-2514
A274: 2137010 | B274: ｶﾅｶﾞﾜｾｲﾌﾞﾉｳｷｮｳﾉｳｷｾﾝﾀｰ | C274: JAかながわ西部農協農機センター | D274: 258-0016 | E274: 神奈川県 足柄上郡 大井町 上大井238 | F274: 0465-83-4171
A275: 2137051 | B275: ｼｮｳﾅﾝﾉｳｷｮｳｼﾞｷﾞｮｳｾﾝﾀｰﾉｳｷ | C275: JA湘南農協 事業センター農機 | D275: 259-1213 | E275: 神奈川県 平塚市 片岡657 | F275: 0463-58-2125
A276: 2137063 | B276: ｾﾞﾝﾉｳｶﾅｶﾞﾜｹﾝﾎﾝﾌﾞﾄｳﾌﾞｷﾀﾉｳｷｾﾝﾀｰ | C276: JA全農神奈川県本部 東部きた 農機センター | D276: 224-0045 | E276: 神奈川県 横浜市 都筑区 東方町1401 | F276: 045-942-8666
A277: 69009226 | B277: ｳｴﾉ | C277: ㈱上野 | D277: 323-0012 | E277: 栃木県 小山市 羽川777-35 | F277: 0285-23-5212
A278: 69009166 | B278: ｵｵﾇｷｷｶｲﾃﾝ | C278: ㈲大貫機械店 | D278: 329-2161 | E278: 栃木県 矢板市 扇町1-16-22 | F278: 0287-43-0366
... A561: 64113903 | B561: ﾋｶﾞｼﾆﾎﾝﾐﾂﾋﾞｼｶﾝﾄｳｺｳｼﾝｴﾂｶﾜｼﾏｴｲｷﾞｮｳｼｮ | C561: 東日本三菱 関東甲信越支社 川島営業所 | D561: 350-0152 | E561: 埼玉県 比企郡 川島町 上伊草995-1 | F561: 0492-97-0274
A562: 64114001 | C562: ㈱ＩＳＥＫＩアグリ 茨城
A563: 64114002 | C563: ㈱ＩＳＥＫＩアグリ 栃木
A564: 64114003 | C564: ㈱ＩＳＥＫＩアグリ 群馬
A565: 64114004 | C565: ㈱ＩＳＥＫＩアグリ 埼玉
A566: 64114005 | C566: ㈱ＩＳＥＫＩアグリ 千葉
A567: 64114006 | C567: ㈱ＩＳＥＫＩアグリ 東京
A568: 64114007 | C568: ㈱ＩＳＥＫＩアグリ 神奈川
A569: 64114900 | B569: ｷﾀﾊﾀﾉｳｷｼｮｳｶｲ | C569: ㈱北畠農機商会 | D569: 309-1454 | E569: 茨城県 桜川市 上城248 | F569: 0296-75-2401
A570: 64116100 | B570: ﾔﾏﾋﾞｺﾄｳｷｮｳ | C570: やまびこ 東京
A571: 64116200 | B571: ﾔﾏﾋﾞｺｶﾅｶﾞﾜ | C571: やまびこ 神奈川
A572: 64116300 | B572: ﾔﾏﾋﾞｺｲﾊﾞﾗｷ | C572: やまびこ 茨城
A573: 64116400 | B573: ﾔﾏﾋﾞｺﾄﾁｷﾞ | C573: やまびこ 栃木
A574: 64116500 | B574: ﾔﾏﾋﾞｺｻｲﾀﾏ | C574: やまびこ 埼玉
A575: 64116600 | B575: ﾔﾏﾋﾞｺｸﾞﾝﾏ | C575: やまびこ 群馬
A576: 64116700 | B576: ﾔﾏﾋﾞｺﾁﾊﾞ | C576: やまびこ 千葉
A577: 64117100 | B577: ﾔﾏﾋﾞｺｼﾞｬﾊﾟﾝﾄｳｷｮｳ | C577: やまびこジャパン㈱ 東京
A578: 64117200 | B578: ﾔﾏﾋﾞｺｼﾞｬﾊﾟﾝｶﾅｶﾞﾜ | C578: やまびこジャパン㈱ 神奈川
A579: 64117300 | B579: ﾔﾏﾋﾞｺｼﾞｬﾊﾟﾝｲﾊﾞﾗｷ | C579: やまびこジャパン㈱ 茨城
A580: 64117400 | B580: ﾔﾏﾋﾞｺｼﾞｬﾊﾟﾝﾄﾁｷﾞ | C580: やまびこジャパン㈱ 栃木
A581: 64117500 | B581: ﾔﾏﾋﾞｺｼﾞｬﾊﾟﾝｻｲﾀﾏ | C581: やまびこジャパン㈱ 埼玉
... A583: 64117700 | B583: ﾔﾏﾋﾞｺｼﾞｬﾊﾟﾝﾁﾊﾞ | C583: やまびこジャパン㈱ 千葉
A584: 64117738 | B584: ﾚﾝﾀﾙﾉﾆｯｹﾝﾊﾏﾏﾂｴｲｷﾞｮｳｼｮ | C584: ㈱レンタルのニッケン 浜松営業所 | D584: 435-0007 | E584: 静岡県 浜松市 東区 流通元町17-2 | F584: 053-421-1750
...

Sheet やまびこ
A1: （様式：EL-97A03）
A2: 引き合い内容連絡書 | J2: 株式会社オーレック
A3: 得意先NO： | B3: 得意先名 及び 担当者名： | I3: 受注日：
A4: 64116300 | C4: =IFERROR(VLOOKUP(A4,請求先!A:D,2,FALSE)," ") -> ㈱やまびこ（茨城） | I4: =TODAY() -> 46201
A5: 納入先NO： | B5: 納入先名及び 担当者名： | G5: 生産日 | I5: 出荷希望日：
A6: 69008232 | C6: =IFERROR(VLOOKUP(A6,出荷先!A:F,3,FALSE)," ") -> 大和田農機 整備センター | I6: 44691
B7: 住所： | C7: 〒 | D7: =IFERROR(VLOOKUP(A6,出荷先!A:F,4,FALSE)," ") -> 311-1517 | I7: TEL
B8: =IFERROR(VLOOKUP(A6,出荷先!A:F,5,FALSE)," ") -> 茨城県鉾田市鉾田595 | I8: =IFERROR(VLOOKUP(A6,出荷先!A:F,6,FALSE)," ") -> 0291-32-2969
A10: 商品番号 | B10: 商品名 | E10: 数量 | F10: 単位 | G10: 単価 | I10: オーダーＮｏ 等
A11: 0285-0620 | B11: =IFERROR(VLOOKUP(A11,商品コード!A:C,2,FALSE)," ") -> HR665/M(ｽﾃﾝﾚｽ仕様） | E11: 1 | F11: 台 | I11: OS | J11: 18346538
B12: =IFERROR(VLOOKUP(A12,商品コード!A:C,2,FALSE)," ") | I12: 0
A13: A003 | B13: =IFERROR(VLOOKUP(A13,商品コード!A:C,2,FALSE)," ") -> 立替運賃 | E13: =E11 -> 1 | G13: =IF(A11="","",VLOOKUP(A11,商品コード!$A:$E,4,FALSE)) -> 10940
B14: =IFERROR(VLOOKUP(A14,商品コード!A:C,2,FALSE)," ")
B15: =IFERROR(VLOOKUP(A15,商品コード!A:C,2,FALSE)," ")
B16: =IFERROR(VLOOKUP(A16,商品コード!A:C,2,FALSE)," ")
A17: 倉庫（ | B17: 011 | C17: ） | D17: 運賃 | E17: 元払い | F17: 伝票NO：
B18: 0 | E18: 立 元 | F18: 出荷確認 | H18: 受注可否検討 | J18: 連絡書作成
E19: 着払い | F19: 承認 | H19: 承認 | J19: 作成者
C20: 便名： | D20: 西濃便 ＴＯＬＬ便
A23: （様式：EL-97A03）

Sheet ﾌﾞﾙｰ・ｸﾞﾘｰﾝﾅｲﾌ用
A1: （様式：EL-97A03） | D1: ﾌﾞﾙｰ･ｸﾞﾘｰﾝ ﾅｲﾌ | F1: ヘッダー
A2: 引き合い内容連絡書 | F2: ：売上区分1「売上」 | J2: 株式会社オーレック
A3: 得意先NO： | B3: 得意先名 及び 担当者名： | I3: 受注日：
C4: =IFERROR(VLOOKUP(A4,請求先!A:D,2,FALSE)," ") | I4: =TODAY() -> 46201
A5: 納入先NO： | B5: 納入先名及び 担当者名： | I5: 出荷希望日：
C6: =IFERROR(VLOOKUP(A6,出荷先!A:F,3,FALSE)," ")
B7: 住所： | C7: 〒 | D7: =IFERROR(VLOOKUP(A6,出荷先!A:F,4,FALSE)," ") | I7: TEL
B8: =IFERROR(VLOOKUP(A6,出荷先!A:F,5,FALSE)," ") | I8: =IFERROR(VLOOKUP(A6,出荷先!A:F,6,FALSE)," ") | M8: 特価値引対応
A10: 商品番号 | B10: 商品名 | E10: 数量 | F10: 単位 | G10: 単価 | I10: オーダーＮｏ 等 | O10: 通常掛率
B11: =IFERROR(VLOOKUP(A11,商品コード!A:C,2,FALSE)," ") | G11: =O13 | I11: =IFERROR(E11*G11," ") | J11: =IFERROR(F11-H11," ") -> 0 | O11: =IFERROR(VLOOKUP(A4,請求先!A:D,4,FALSE)," ") | U11: 商品コード
B12: =IFERROR(VLOOKUP(A12,商品コード!A:C,2,FALSE)," ") | G12: =O14 | I12: =IFERROR(E12*G12," ") | J12: =IFERROR(F12-H12," ") -> 0 | M12: 小売単価 | O12: 仕切単価 | Q12: 特価 | S12: 値引 | U12: 品名 | W12: 品番 | Y12: 販売価格
B13: =IFERROR(VLOOKUP(A13,商品コード!A:C,2,FALSE)," ") | G13: =O15 | I13: =IFERROR(E13*G13," ") | J13: =IFERROR(F13-H13," ") -> 0 | M13: =IFERROR(VLOOKUP(A11,商品コード!A:C,3,FALSE)," ") | N13: ＠ | O13: =IFERROR(ROUNDDOWN(M13*$O$11,0)," ") | S13: =IFERROR(O13-Q13," ") | U13: ｸﾞﾘｰﾝﾅｲﾌｾｯﾄ(SP50) | W13: 0208-85000 | Y13: 1980
B14: =IFERROR(VLOOKUP(A14,商品コード!A:C,2,FALSE)," ") | G14: =O16 | I14: =IFERROR(E14*G14," ") | J14: =IFERROR(F14-H14," ") -> 0 | M14: =IFERROR(VLOOKUP(A12,商品コード!A:C,3,FALSE)," ") | N14: ＠ | O14: =IFERROR(ROUNDDOWN(M14*$O$11,0)," ") | S14: =IFERROR(O14-Q14," ") | U14: ﾌﾞﾙｰﾅｲﾌ(WM716) | W14: 0245-77200 | Y14: 850
B15: =IFERROR(VLOOKUP(A15,商品コード!A:C,2,FALSE)," ") | G15: =O17 | I15: =IFERROR(E15*G15," ") | J15: =IFERROR(F15-H15," ") -> 0 | M15: =IFERROR(VLOOKUP(A13,商品コード!A:C,3,FALSE)," ") | N15: ＠ | O15: =IFERROR(ROUNDDOWN(M15*$O$11,0)," ") | S15: =IFERROR(O15-Q15," ") | U15: ﾌﾞﾙｰﾅｲﾌ(WM60) | W15: 80-1516-822-00 | Y15: 750
B16: =IFERROR(VLOOKUP(A16,商品コード!A:C,2,FALSE)," ") | G16: =O18 | I16: =IFERROR(E16*G16," ") | J16: =IFERROR(F16-H16," ") -> 0 | M16: =IFERROR(VLOOKUP(A14,商品コード!A:C,3,FALSE)," ") | N16: ＠ | O16: =IFERROR(ROUNDDOWN(M16*$O$11,0)," ") | S16: =IFERROR(O16-Q16," ") | U16: ﾌﾞﾙｰﾅｲﾌ(RM85) | W16: 0244-89200 | Y16: 950
A17: 倉庫（ | C17: ） | F17: 伝票NO： | I17: =SUM(I11:J16) -> 0 | M17: =IFERROR(VLOOKUP(A15,商品コード!A:C,3,FALSE)," ") | N17: ＠ | O17: =IFERROR(ROUNDDOWN(M17*$O$11,0)," ") | S17: =IFERROR(O17-Q17," ")
F18: 出荷確認 | H18: 受注可否検討 | J18: 連絡書作成 | M18: =IFERROR(VLOOKUP(A16,商品コード!A:C,3,FALSE)," ") | N18: ＠ | O18: =IFERROR(ROUNDDOWN(M18*$O$11,0)," ") | S18: =IFERROR(O18-Q18," ")
F19: 承認 | H19: 承認 | J19: 作成者
C20: 便名： | D20: 持込済み
G22: 詳細
A23: （様式：EL-97A03） | D23: ﾌﾞﾙｰ･ｸﾞﾘｰﾝ ﾅｲﾌ | E23: 【値引】 | G23: ：売上区分3 「値引」
A24: 引き合い内容連絡書 | J24: 株式会社オーレック
A25: 得意先NO： | B25: 得意先名 及び 担当者名： | I25: 受注日：
A26: =A4 -> 0 | C26: =C4 | I26: =I4 -> 46201
A27: 納入先NO： | B27: 納入先名及び 担当者名： | I27: 出荷希望日：
A28: =A6 -> 0 | C28: =C6 | I28: =I6 -> 0
B29: 住所： | I29: TEL
A32: 商品番号 | B32: 商品名 | E32: 数量 | F32: 値引後(仕切) | H32: 単価 | J32: 合計
A33: =A11 -> 0 | B33: =B11 | E33: =E11 -> 0 | F33: =Q13 -> 0 | H33: =IFERROR(-(S13)," ") | J33: =IFERROR(H33*E33," ")
A34: =A12 -> 0 | B34: =B12 | E34: =E12 -> 0 | F34: =Q14 -> 0 | H34: =IFERROR(-(S14)," ") | J34: =IFERROR(H34*E34," ")
A35: =A13 -> 0 | B35: =B13 | E35: =E13 -> 0 | F35: =Q15 -> 0 | H35: =IFERROR(-(S15)," ") | J35: =IFERROR(H35*E35," ")
A36: =A14 -> 0 | B36: =B14 | E36: =E14 -> 0 | F36: =Q16 -> 0 | H36: =IFERROR(-(S16)," ") | J36: =IFERROR(H36*E36," ")
A37: =A15 -> 0 | B37: =B15 | E37: =E15 -> 0 | F37: =Q17 -> 0 | H37: =IFERROR(-(S17)," ") | J37: =IFERROR(H37*E37," ")
A38: =A16 -> 0 | B38: =B16 | E38: =E16 -> 0 | F38: =Q18 -> 0 | H38: =IFERROR(-(S18)," ") | J38: =IFERROR(H38*E38," ")
C39: 単価 | D39: OBIC照合 | F39: 伝票NO： | H39: 合計 | J39: =SUM(J33:J38) -> 0
C40: =Q13 -> 0 | D40: =IFERROR((E33*C40)," ") -> 0 | F40: 出荷確認 | H40: 受注可否検討 | J40: 連絡書作成
C41: =Q14 -> 0 | D41: =IFERROR((E34*C41)," ") -> 0 | F41: 承認 | H41: 承認 | J41: 作成者
C42: =Q15 -> 0 | D42: =IFERROR((E35*C42)," ") -> 0
D43: =IFERROR((E36*C43)," ") -> 0 | E43: OBIC計
A44: 値引理由； | B44: 予約対応価格 | E44: =SUM(D40:D43) -> 0
